Workbook
Name CreativeShifts: Lists!$E$1:$E$7
Name Errors: Lists!$D$1:$D$1
Name Omissions: Lists!$C$1:$C$2
Name Reproduction: Lists!$B$1:$B$4

Sheet Lists
A1: 1. Reproduction | B1: Retention | C1: Creative Omission | D1: Error | E1: Abstraction – Superordinate Term | G1: 1. Reproduction | H1: Reproduction
A2: 2. Omissions | B2: Specification | C2: Shortcut Solution | E2: Abstraction – Paraphrase | G2: 2. Omissions | H2: Omissions
A3: 3. Errors | B3: Direct Translation | E3: Concretisation – Addition | G3: 3. Errors | H3: Errors
A4: 4. Creative Shifts | B4: Official Translation | E4: Concretisation – Completion | G4: 4. Creative Shifts | H4: CreativeShifts
E5: Modification – Cultural
E6: Modification – Situational
E7: Modification – Historical

Sheet Dashboard
B1: EVALUATION DASHBOARD — Category Distribution (4 Models × 5 Prompts)
B3: ℹ Fill dropdowns in the Evaluation sheet — counts update here automatically.
B5: Model A
B6: Prompt | C6: Reproduction | D6: Omissions | E6: Errors | F6: Creative Shifts | G6: Total | H6: % Done
B7: Baseline | C7: =COUNTIF(Evaluation!K3:K202,"1. Reproduction") -> 38 | D7: =COUNTIF(Evaluation!K3:K202,"2. Omissions") -> 10 | E7: =COUNTIF(Evaluation!K3:K202,"3. Errors") -> 16 | F7: =COUNTIF(Evaluation!K3:K202,"4. Creative Shifts") -> 129 | G7: =COUNTIF(Evaluation!K3:K202,"<>") -> 193 | H7: =IFERROR(G7/200,"") -> 0.965
B8: Few-shot 1 | C8: =COUNTIF(Evaluation!Q3:Q202,"1. Reproduction") -> 46 | D8: =COUNTIF(Evaluation!Q3:Q202,"2. Omissions") -> 8 | E8: =COUNTIF(Evaluation!Q3:Q202,"3. Errors") -> 15 | F8: =COUNTIF(Evaluation!Q3:Q202,"4. Creative Shifts") -> 124 | G8: =COUNTIF(Evaluation!Q3:Q202,"<>") -> 193 | H8: =IFERROR(G8/200,"") -> 0.965
B9: Few-shot 2 | C9: =COUNTIF(Evaluation!W3:W202,"1. Reproduction") -> 46 | D9: =COUNTIF(Evaluation!W3:W202,"2. Omissions") -> 12 | E9: =COUNTIF(Evaluation!W3:W202,"3. Errors") -> 13 | F9: =COUNTIF(Evaluation!W3:W202,"4. Creative Shifts") -> 122 | G9: =COUNTIF(Evaluation!W3:W202,"<>") -> 193 | H9: =IFERROR(G9/200,"") -> 0.965
B10: CoT 1 | C10: =COUNTIF(Evaluation!AC3:AC202,"1. Reproduction") -> 42 | D10: =COUNTIF(Evaluation!AC3:AC202,"2. Omissions") -> 11 | E10: =COUNTIF(Evaluation!AC3:AC202,"3. Errors") -> 12 | F10: =COUNTIF(Evaluation!AC3:AC202,"4. Creative Shifts") -> 128 | G10: =COUNTIF(Evaluation!AC3:AC202,"<>") -> 193 | H10: =IFERROR(G10/200,"") -> 0.965
B11: CoT 2 | C11: =COUNTIF(Evaluation!AI3:AI202,"1. Reproduction") -> 41 | D11: =COUNTIF(Evaluation!AI3:AI202,"2. Omissions") -> 13 | E11: =COUNTIF(Evaluation!AI3:AI202,"3. Errors") -> 14 | F11: =COUNTIF(Evaluation!AI3:AI202,"4. Creative Shifts") -> 125 | G11: =COUNTIF(Evaluation!AI3:AI202,"<>") -> 193 | H11: =IFERROR(G11/200,"") -> 0.965
B14: Model B
B15: Prompt | C15: Reproduction | D15: Omissions | E15: Errors | F15: Creative Shifts | G15: Total | H15: % Done
B16: Baseline | C16: =COUNTIF(Evaluation!AO3:AO202,"1. Reproduction") -> 77 | D16: =COUNTIF(Evaluation!AO3:AO202,"2. Omissions") -> 3 | E16: =COUNTIF(Evaluation!AO3:AO202,"3. Errors") -> 21 | F16: =COUNTIF(Evaluation!AO3:AO202,"4. Creative Shifts") -> 92 | G16: =COUNTIF(Evaluation!AO3:AO202,"<>") -> 193 | H16: =IFERROR(G16/200,"") -> 0.965
B17: Few-shot 1 | C17: =COUNTIF(Evaluation!AU3:AU202,"1. Reproduction") -> 76 | D17: =COUNTIF(Evaluation!AU3:AU202,"2. Omissions") -> 3 | E17: =COUNTIF(Evaluation!AU3:AU202,"3. Errors") -> 17 | F17: =COUNTIF(Evaluation!AU3:AU202,"4. Creative Shifts") -> 97 | G17: =COUNTIF(Evaluation!AU3:AU202,"<>") -> 193 | H17: =IFERROR(G17/200,"") -> 0.965
B18: Few-shot 2 | C18: =COUNTIF(Evaluation!BA3:BA202,"1. Reproduction") -> 76 | D18: =COUNTIF(Evaluation!BA3:BA202,"2. Omissions") -> 6 | E18: =COUNTIF(Evaluation!BA3:BA202,"3. Errors") -> 17 | F18: =COUNTIF(Evaluation!BA3:BA202,"4. Creative Shifts") -> 94 | G18: =COUNTIF(Evaluation!BA3:BA202,"<>") -> 193 | H18: =IFERROR(G18/200,"") -> 0.965
B19: CoT 1 | C19: =COUNTIF(Evaluation!BG3:BG202,"1. Reproduction") -> 82 | D19: =COUNTIF(Evaluation!BG3:BG202,"2. Omissions") -> 2 | E19: =COUNTIF(Evaluation!BG3:BG202,"3. Errors") -> 18 | F19: =COUNTIF(Evaluation!BG3:BG202,"4. Creative Shifts") -> 91 | G19: =COUNTIF(Evaluation!BG3:BG202,"<>") -> 193 | H19: =IFERROR(G19/200,"") -> 0.965
B20: CoT 2 | C20: =COUNTIF(Evaluation!BM3:BM202,"1. Reproduction") -> 79 | D20: =COUNTIF(Evaluation!BM3:BM202,"2. Omissions") -> 2 | E20: =COUNTIF(Evaluation!BM3:BM202,"3. Errors") -> 20 | F20: =COUNTIF(Evaluation!BM3:BM202,"4. Creative Shifts") -> 92 | G20: =COUNTIF(Evaluation!BM3:BM202,"<>") -> 193 | H20: =IFERROR(G20/200,"") -> 0.965
B23: Model C
B24: Prompt | C24: Reproduction | D24: Omissions | E24: Errors | F24: Creative Shifts | G24: Total | H24: % Done
B25: Baseline | C25: =COUNTIF(Evaluation!BS3:BS202,"1. Reproduction") -> 95 | D25: =COUNTIF(Evaluation!BS3:BS202,"2. Omissions") -> 4 | E25: =COUNTIF(Evaluation!BS3:BS202,"3. Errors") -> 12 | F25: =COUNTIF(Evaluation!BS3:BS202,"4. Creative Shifts") -> 82 | G25: =COUNTIF(Evaluation!BS3:BS202,"<>") -> 193 | H25: =IFERROR(G25/200,"") -> 0.965
B26: Few-shot 1 | C26: =COUNTIF(Evaluation!BY3:BY202,"1. Reproduction") -> 82 | D26: =COUNTIF(Evaluation!BY3:BY202,"2. Omissions") -> 9 | E26: =COUNTIF(Evaluation!BY3:BY202,"3. Errors") -> 12 | F26: =COUNTIF(Evaluation!BY3:BY202,"4. Creative Shifts") -> 90 | G26: =COUNTIF(Evaluation!BY3:BY202,"<>") -> 193 | H26: =IFERROR(G26/200,"") -> 0.965
B27: Few-shot 2 | C27: =COUNTIF(Evaluation!CE3:CE202,"1. Reproduction") -> 95 | D27: =COUNTIF(Evaluation!CE3:CE202,"2. Omissions") -> 2 | E27: =COUNTIF(Evaluation!CE3:CE202,"3. Errors") -> 8 | F27: =COUNTIF(Evaluation!CE3:CE202,"4. Creative Shifts") -> 88 | G27: =COUNTIF(Evaluation!CE3:CE202,"<>") -> 193 | H27: =IFERROR(G27/200,"") -> 0.965
B28: CoT 1 | C28: =COUNTIF(Evaluation!CK3:CK202,"1. Reproduction") -> 93 | D28: =COUNTIF(Evaluation!CK3:CK202,"2. Omissions") -> 4 | E28: =COUNTIF(Evaluation!CK3:CK202,"3. Errors") -> 11 | F28: =COUNTIF(Evaluation!CK3:CK202,"4. Creative Shifts") -> 85 | G28: =COUNTIF(Evaluation!CK3:CK202,"<>") -> 193 | H28: =IFERROR(G28/200,"") -> 0.965
B29: CoT 2 | C29: =COUNTIF(Evaluation!CQ3:CQ202,"1. Reproduction") -> 93 | D29: =COUNTIF(Evaluation!CQ3:CQ202,"2. Omissions") -> 4 | E29: =COUNTIF(Evaluation!CQ3:CQ202,"3. Errors") -> 9 | F29: =COUNTIF(Evaluation!CQ3:CQ202,"4. Creative Shifts") -> 87 | G29: =COUNTIF(Evaluation!CQ3:CQ202,"<>") -> 193 | H29: =IFERROR(G29/200,"") -> 0.965
B32: Model D
B33: Prompt | C33: Reproduction | D33: Omissions | E33: Errors | F33: Creative Shifts | G33: Total | H33: % Done
B34: Baseline | C34: =COUNTIF(Evaluation!#REF!,"1. Reproduction") -> #REF! | D34: =COUNTIF(Evaluation!#REF!,"2. Omissions") -> #REF! | E34: =COUNTIF(Evaluation!#REF!,"3. Errors") -> #REF! | F34: =COUNTIF(Evaluation!#REF!,"4. Creative Shifts") -> #REF! | G34: =COUNTIF(Evaluation!#REF!,"<>") -> #REF! | H34: =IFERROR(G34/200,"")
B35: Few-shot 1 | C35: =COUNTIF(Evaluation!#REF!,"1. Reproduction") -> #REF! | D35: =COUNTIF(Evaluation!#REF!,"2. Omissions") -> #REF! | E35: =COUNTIF(Evaluation!#REF!,"3. Errors") -> #REF! | F35: =COUNTIF(Evaluation!#REF!,"4. Creative Shifts") -> #REF! | G35: =COUNTIF(Evaluation!#REF!,"<>") -> #REF! | H35: =IFERROR(G35/200,"")
B36: Few-shot 2 | C36: =COUNTIF(Evaluation!#REF!,"1. Reproduction") -> #REF! | D36: =COUNTIF(Evaluation!#REF!,"2. Omissions") -> #REF! | E36: =COUNTIF(Evaluation!#REF!,"3. Errors") -> #REF! | F36: =COUNTIF(Evaluation!#REF!,"4. Creative Shifts") -> #REF! | G36: =COUNTIF(Evaluation!#REF!,"<>") -> #REF! | H36: =IFERROR(G36/200,"")
B37: CoT 1 | C37: =COUNTIF(Evaluation!#REF!,"1. Reproduction") -> #REF! | D37: =COUNTIF(Evaluation!#REF!,"2. Omissions") -> #REF! | E37: =COUNTIF(Evaluation!#REF!,"3. Errors") -> #REF! | F37: =COUNTIF(Evaluation!#REF!,"4. Creative Shifts") -> #REF! | G37: =COUNTIF(Evaluation!#REF!,"<>") -> #REF! | H37: =IFERROR(G37/200,"")
B38: CoT 2 | C38: =COUNTIF(Evaluation!#REF!,"1. Reproduction") -> #REF! | D38: =COUNTIF(Evaluation!#REF!,"2. Omissions") -> #REF! | E38: =COUNTIF(Evaluation!#REF!,"3. Errors") -> #REF! | F38: =COUNTIF(Evaluation!#REF!,"4. Creative Shifts") -> #REF! | G38: =COUNTIF(Evaluation!#REF!,"<>") -> #REF! | H38: =IFERROR(G38/200,"")

Sheet Evaluation
J1: Model A - TranslateGemma | AN1: Model B - Qwen | BR1: Model C - Salamandra
A2: text_previous | B2: text_analyzed | C2: text_after | D2: text_analyzed | E2: macrocategory | F2: subcategory_num | G2: subcategory | H2: Definition or Translation | I2: Referencia | J2: translation_translategemma_baseline | K2: Baseline ▼ Category | L2: Baseline ▼ Subcategory | M2: Mantains informal register? | N2: Intensity of informality | O2: Baseline Comments | P2: translation_translategemma_fewshot1 | Q2: Few-shot 1 ▼ Category | R2: Few-shot 1 ▼ Subcategory | S2: Mantains informal register? | U2: Few-shot 1 Comments | V2: translation_translategemma_fewshot2 | W2: Few-shot 2 ▼ Category | X2: Few-shot 2 ▼ Subcategory | Y2: Mantains informal register? | Z2: Intensity of informality | AA2: Few-shot 2 Comments | AB2: translation_translategemma_CoT1 | AC2: CoT 1 ▼ Category | AD2: CoT 1 ▼ Subcategory | AE2: Mantains informal register? | AF2: Intensity of informality | AG2: CoT 1 Comments | AH2: translation_translategemma_CoT2 | AI2: CoT 2 ▼ Category | AJ2: CoT 2 ▼ Subcategory | AK2: Mantains informal register? | AL2: Intensity of informality | AM2: CoT 2 Comments | AN2: translation_qwen_baseline | AO2: Baseline ▼ Category | AP2: Baseline ▼ Subcategory | AQ2: Mantains informal register? | AR2: Intensity of informality | AS2: Baseline Comments | AT2: translation_qwen_fewshot1 | AU2: Few-shot 1 ▼ Category | AV2: Few-shot 1 ▼ Subcategory | AW2: Mantains informal register? | AX2: Intensity of informality | AY2: Few-shot 1 Comments | AZ2: translation_qwen_fewshot2 | BA2: Few-shot 2 ▼ Category | BB2: Few-shot 2 ▼ Subcategory | BC2: Mantains informal register? | BD2: Intensity of informality | BE2: Few-shot 2 Comments | BF2: translation_qwen_CoT1 | BG2: CoT 1 ▼ Category | BH2: CoT 1 ▼ Subcategory | BI2: Mantains informal register? | BJ2: Intensity of informality | BK2: CoT 1 Comments | BL2: translation_qwen_CoT2 | BM2: CoT 2 ▼ Category | BN2: CoT 2 ▼ Subcategory | BO2: Mantains informal register? | BP2: Intensity of informality | BQ2: CoT 2 Comments | BR2: translation_salam_baseline | BS2: Baseline ▼ Category | BT2: Baseline ▼ Subcategory | BU2: Mantains informal register? | BV2: Intensity of informality | BW2: Baseline Comments | BX2: translation_salam_fewshot1 | BY2: Few-shot 1 | BZ2: Few-shot 1 ▼ Subcategory | CA2: Mantains informal register? | CB2: Intensity of informality | CC2: Few-shot 1 Comments | CD2: translation_salam_fewshot2 | CE2: Few-shot 2 ▼ Category | CF2: Few-shot 2 ▼ Subcategory | CG2: Mantains informal register? | CH2: Intensity of informality | CI2: Few-shot 2 Comments | CJ2: translation_salam_CoT1 | CK2: CoT 1 ▼ Category | CL2: CoT 1 ▼ Subcategory | CM2: Mantains informal register? | CN2: Intensity of informality | CO2: CoT 1 Comments | CP2: translation_salam_CoT2 | CQ2: CoT 2 ▼ Category | CR2: CoT 2 ▼ Subcategory | CS2: Mantains informal register? | CT2: Intensity of informality | CU2: CoT 2 Comments
A3: [empieza tema de conversación] | B3: Hay sitios que va todo el mundo y yo de verdad que quiero saber los entresijos de los personajacos que deben de ir al MediaMarkt. | C3: Es que esto tiene que ser maravilloso porque te puedes encontrar de to. De una idea, nos lo va a contar el invitado de hoy. | D3: Hay sitios que va todo el mundo y yo de verdad que quiero saber los entresijos de los personajacos que deben de ir al MediaMarkt. | E3: 1. Lexicon and Vocabulary | F3: 1.2 | G3: Colloquial lexicon and slang | J3: There are places that everyone goes to, and I'm genuinely curious to know the details about the types of people who visit MediaMarkt. | K3: 4. Creative Shifts | L3: Abstraction – Superordinate Term | M3: NO | O3: Cambridge / WordReference | P3: There are places that everyone goes to, and I'm genuinely curious to know all the details about the characters who are supposed to be going to MediaMarkt. | Q3: 4. Creative Shifts | R3: Abstraction – Superordinate Term | S3: NO | U3: Cambridge / WordReference | V3: There are places that everyone goes to, and I'm genuinely curious about the inner workings of the people who must go to MediaMarkt. | W3: 4. Creative Shifts | X3: Abstraction – Superordinate Term | Y3: NO | AB3: There are places that everyone goes to, and I'm genuinely curious about the details of the people who must go to MediaMarkt. | AC3: 4. Creative Shifts | AD3: Abstraction – Superordinate Term | AE3: NO | AH3: There are places that everyone goes to, and I really want to know the ins and outs of the people who are supposed to be going to MediaMarkt. | AI3: 4. Creative Shifts | AJ3: Abstraction – Superordinate Term | AK3: NO | AN3: There are places that everyone goes to, and I really want to know the behind-the-scenes stuff about these little characters who should be going to MediaMarkt. | AO3: 4. Creative Shifts | AP3: Abstraction – Superordinate Term | AQ3: NO | AS3: Cambridge / WordReference | AT3: There are places everyone goes to, and I really want to know the ins and outs of those little characters who must go to MediaMarkt. | AU3: 4. Creative Shifts | AV3: Abstraction – Superordinate Term | AW3: NO | AY3: Cambridge / WordReference | AZ3: There are places everyone goes, and I really want to know the inside stories of those characters who must go to MediaMarkt. | BA3: 4. Creative Shifts | BB3: Abstraction – Superordinate Term | BC3: YES | BE3: Cambridge / WordReference | BF3: "There are places that everyone goes to, and I really want to know the inside stories of those little characters who must go to MediaMarkt." | BG3: 4. Creative Shifts | BH3: Modification – Situational | BI3: NO | BK3: Cambridge / WordReference | BL3: There are shows that everyone watches, and I really want to know the behind-the-scenes stuff about those characters that air on MediaMarkt. | BM3: 4. Creative Shifts | BN3: Abstraction – Superordinate Term | BO3: YES | BQ3: Cambridge / WordReference | BR3: There are places that everyone goes and I really want to know the ins and outs of the characters who must go to MediaMarkt. | BS3: 4. Creative Shifts | BT3: Abstraction – Superordinate Term | BU3: NO | BW3: Cambridge / WordReference | BX3: There are places that everyone goes and I really want to know the ins and outs of the characters who must go to MediaMarkt. | BY3: 4. Creative Shifts | BZ3: Abstraction – Superordinate Term | CA3: NO | CC3: Cambridge / WordReference | CD3: There are places that everyone goes and I really want to know the ins and outs of the character types who must go to the MediaMarkt. | CE3: 4. Creative Shifts | CF3: Abstraction – Superordinate Term | CG3: NO | CI3: Cambridge / WordReference | CJ3: There are places that everyone goes and I really want to know the ins and outs of the characters who must go to MediaMarkt. | CK3: 4. Creative Shifts | CL3: Abstraction – Superordinate Term | CM3: NO | CO3: Cambridge / WordReference | CP3: There are places that everyone goes and I really want to know the ins and outs of the character types who must go to MediaMarkt | CQ3: 4. Creative Shifts | CR3: Abstraction – Superordinate Term | CS3: NO | CU3: Cambridge / WordReference
A4: [empieza tema de conversación] | B4: Gente que te intenta regatear, se cree que si se lleva 2 portátiles, se lo voy a, se le va a bajar el precio. Efectivamente, ni que yo fuera el dueño de allí de la tienda. Hermano, si yo me llevo estos 2 portátiles, ¿en cuánto me lo dejas? | C4: Efectivamente, ni que yo fuera el dueño de allí de la tienda. Hermano, si yo me llevo estos 2 portátiles, ¿en cuánto me lo dejas? Pues al mismo precio. | D4: Gente que te intenta regatear, se cree que si se lleva 2 portátiles, se lo voy a, se le va a bajar el precio. Efectivamente, ni que yo fuera el dueño de allí de la tienda. Hermano, si yo me llevo estos 2 portátiles, ¿en cuánto me lo dejas? | E4: 3. Pragmatics and Discourse | F4: 3.2 | G4: Familiar address or vocatives | H4: Brother | I4: WordReference | J4: People try to haggle with you, thinking that if they buy two laptops, they'll get a discount. It's as if they think I'm the owner of the shop. Listen, if I buy these two laptops, what price will you give them to me for? | K4: 4. Creative Shifts | L4: Modification – Situational | M4: NO | P4: People try to haggle with you, thinking that if they buy two laptops, I'll, or they'll, get a lower price. As if I'm the owner of the shop. Mate, if I buy these two laptops, how much will you let me have them for? | Q4: 4. Creative Shifts | R4: Modification – Cultural | S4: YES | U4: WordReference | V4: People who try to haggle with you, they think that if they buy two laptops, I'm going to give them a discount. As if I own the shop! Mate, if I buy these two laptops, how much will you let me have them for? | W4: 4. Creative Shifts | X4: Modification – Cultural | Y4: YES | AA4: WordReference | AB4: People try to haggle with you, thinking that if they buy two laptops, I'm going to, or they're going to, get a discount. It's as if I own the shop. Mate, if I buy these two laptops, how much will you let me have them for? | AC4: 4. Creative Shifts | AD4: Modification – Cultural | AE4: YES | AG4: WordReference | AH4: People try to haggle with you, thinking that if they buy two laptops, I'll give them a discount. As if I own the shop! Mate, if I buy these two laptops, how much will you let me have them for? | AI4: 4. Creative Shifts | AJ4: Modification – Cultural | AK4: YES | AM4: WordReference | AN4: People who try to haggle with you, thinking that if they take two laptops, I'll give them a discount. Yeah, like I was the owner of the store. Bro, if I take these two laptops, how much would you charge me? Well, at the same price. | AO4: 4. Creative Shifts | AP4: Modification – Cultural | AQ4: YES | AS4: WordReference | AT4: Sure, like he thinks if he takes two laptops, I'm gonna give them to him, he's gonna get a discount. Yeah, like I was the owner of that store. Bro, if I take these two laptops, how much would you charge me? Well, the same price. | AU4: 4. Creative Shifts | AV4: Modification – Cultural | AW4: YES | AY4: WordReference | AZ4: Bro, people who try to haggle with you, thinking that if they take two laptops, I'm gonna give them a deal, like the price will drop. Yeah, like I was the owner of that store. Bro, if I take these two laptops, how much are you gonna charge me? Well, the same price. | BA4: 4. Creative Shifts | BB4: Modification – Situational | BC4: YES | BF4: People who try to haggle with you, thinking that if they take two laptops, I'll give them a better price. Indeed, as if I were the owner of the store. Bro, if I take these two laptops, how much would you charge me? Well, the same price. | BG4: 4. Creative Shifts | BH4: Concretisation – Addition | BI4: YES | BL4: People who try to haggle with you, thinking that if you take two laptops, I'm going to, they're going to lower the price. Yeah, as if I were the owner of that store. Bro, if I take these two laptops, how much will you let me have them for? | BM4: 4. Creative Shifts | BN4: Modification – Cultural | BO4: YES | BR4: People who try to haggle with you, they think that if they take 2 laptops, the price will go down. Indeed, as if I were the owner of the store. Brother, if I take these 2 laptops, how much do you leave me? | BS4: 1. Reproduction | BT4: Direct Translation | BU4: YES | BW4: Wordreference | BX4: People who try to haggle with you, they think that if he takes two laptops, then his price will go down. Well actually, like I own this store. Brother, if I take these two laptops, how much do you leave them? | BY4: 1. Reproduction | BZ4: Direct Translation | CA4: YES | CC4: WordReference | CD4: People who try to haggle, they think that if they take 2 laptops, the price will go down. Effectively, as if I were the owner of the store. Brother, if I take these 2 laptops, how much do you leave me? | CE4: 1. Reproduction | CF4: Direct Translation | CG4: YES | CI4: WordReference | CJ4: People who try to haggle with you, they think that if they take 2 laptops, the price will go down. Indeed, as if I were the owner of the store. Brother, if I take these 2 laptops, how much do you leave me? | CK4: 1. Reproduction | CL4: Direct Translation | CM4: YES | CO4: WordReference | CP4: People who try to haggle with you, they think that if they take 2 laptops, the price will go down. Indeed, as if I were the owner of the store. Brother, if I take these 2 laptops, what price do you leave me? Indeed, at the same price. | CQ4: 1. Reproduction | CR4: Direct Translation | CS4: YES | CU4: WordReference
A5: [empieza tema de conversación] | B5: Esta vez, una de mis regiones favoritas, la región del fish and chips, de la peña con los dientes de aquella manera, de esa gente que todo el mundo habla en su idioma, pero ellos no hablan en el idioma de nadie. Vamos a conocer cómo es Inglaterra. | C5: Vamos a conocer cómo es Inglaterra. | D5: Esta vez, una de mis regiones favoritas, la región del fish and chips, de la peña con los dientes de aquella manera, de esa gente que todo el mundo habla en su idioma, pero ellos no hablan en el idioma de nadie. Vamos a conocer cómo es Inglaterra. | E5: 1. Lexicon and Vocabulary | F5: 1.2 | G5: Colloquial lexicon and slang | H5: Folks | I5: WordReference | J5: This time, we're visiting one of my favourite regions, the land of fish and chips, of those people with that distinctive look, those folks that everyone talks about in their own language, but who don't speak anyone else's language. Let's find out what England is really like. | K5: 4. Creative Shifts | L5: Abstraction – Superordinate Term | M5: NO | P5: This time, we're heading to one of my favourite regions: the land of fish and chips, the place with all those people with funny teeth, that crowd everyone talks about, who speak in their own language, but don't speak anyone else's. Let's find out what England is really like. | Q5: 4. Creative Shifts | R5: Abstraction – Superordinate Term | S5: NO | V5: This time, we're going to one of my favourite regions, the land of fish and chips, of those people with the distinctive teeth, of those folks that everyone talks about in their own language, but who don't speak anyone else's language. Let's find out what England is really like. | W5: 4. Creative Shifts | X5: Abstraction – Superordinate Term | Y5: NO | AB5: "This time, we're going to one of my favourite regions – the land of fish and chips, of those people with that distinctive way of speaking, that group who everyone talks about in their own language, but who don't speak anyone else's language. Let's find out what England is really like. | AC5: 4. Creative Shifts | AD5: Abstraction – Superordinate Term | AE5: NO | AH5: "This time, we're heading to one of my favourite regions – the land of fish and chips, the place with those distinctive teeth, that group of people everyone talks about in their own language, but who don't speak anyone else's language. Let's find out what England is really like." | AI5: 3. Errors | AK5: NO | AN5: This time, one of my favorite regions, the fish and chips region, the group with those teeth in that way, the people everyone talks about in their own language, but they don't speak anyone else's language. Let's find out what England is like. | AO5: 4. Creative Shifts | AP5: Abstraction – Superordinate Term | AQ5: NO | AT5: This time, one of my favorite regions, the fish and chips region, the area with those teeth-like things, the people who everyone talks about in their own language, but they don't speak anyone else's language. Let's find out what England is like. | AU5: 3. Errors | AW5: NO | AZ5: This time, one of my favorite regions, the fish and chips region, the area with those teeth-like things, the people who everyone talks about in their own language, but they don’t speak anyone else’s language. Let’s find out what England is like. | BA5: 3. Errors | BC5: NO | BF5: This time, one of my favorite regions, the fish and chips region, the area with those teeth in that way, the people everyone talks about in their own language, but they don't speak anyone else's language. Let's find out what England is like. | BG5: 3. Errors | BI5: NO | BL5: This time, one of my favorite regions, the fish and chips region, the group with those teeth in that way, that bunch of people everyone talks about in their own language, but they don’t speak anyone else’s language. Let’s find out what England is like. | BM5: 4. Creative Shifts | BN5: Abstraction – Superordinate Term | BO5: NO | BR5: This time, one of my favorite regions, the region of fish and chips, of the people with teeth like that, of that people who everyone talks about in their language, but they don't talk in the language of no one. Let's get to know England. | BS5: 4. Creative Shifts | BT5: Abstraction – Superordinate Term | BU5: NO | BX5: This time, one of my favorite regions, the region of fish and chips, people with teeth like that, those people who everyone talks about their own language, but they don’t speak anyone’s language. Let’s go see how England is." | BY5: 4. Creative Shifts | BZ5: Abstraction – Superordinate Term | CA5: NO | CD5: This time, one of my favorite regions, the fish and chips region, of the people with teeth like that, of that people that everyone talks about in their language, but they don't speak in the language of no one. Let's get to know England. | CE5: 4. Creative Shifts | CF5: Abstraction – Superordinate Term | CG5: NO | CJ5: This time, one of my favorite regions, the region of fish and chips, of the person with teeth like that, of that people who everyone talks about in their language, but they don't speak in the language of no one. Let's get to know England. | CK5: 4. Creative Shifts | CL5: Abstraction – Superordinate Term | CM5: NO | CP5: This time, one of my favorite regions, the region of fish and chips, of the person with teeth like that, of that people who everyone talks about in their language, but they don't speak in the language of no one. Let's get to know England. | CQ5: 4. Creative Shifts | CR5: Abstraction – Superordinate Term | CS5: NO
A6: [empieza tema de conversación] | B6: Tío, ¿quién te enseñó español para hablar tan bien? | C6: Hice una carrera de Estudios Hispánicos, por eso hablo español. Aparte de eso, siempre estaba con mis amigos españoles. O sea, estando en Japón, de entre 4 a 7 hablaban en español y era el único japonés en ese grupo hispanohablante. | D6: Tío, ¿quién te enseñó español para hablar tan bien? | E6: 3. Pragmatics and Discourse | F6: 3.2 | G6: Familiar address or vocatives | H6: brother / mate / buddy / pal / dude / bro / man | I6: WordReference | J6: "Mate, who taught you Spanish so you could speak it so well?" | K6: 4. Creative Shifts | L6: Modification – Cultural | M6: YES | P6: "Mate, who taught you Spanish so you could speak it so well?" | Q6: 4. Creative Shifts | R6: Modification – Cultural | S6: YES | V6: "Mate, who taught you Spanish so you could speak it so well?" | W6: 4. Creative Shifts | X6: Modification – Cultural | Y6: YES | AB6: "Mate, who taught you Spanish so you could speak it so well?" | AC6: 4. Creative Shifts | AD6: Modification – Cultural | AE6: YES | AH6: "Mate, who taught you Spanish so you could speak it so well?" | AI6: 4. Creative Shifts | AJ6: Modification – Cultural | AK6: YES | AN6: Uncle, who taught you Spanish to speak so well? | AO6: 1. Reproduction | AP6: Direct Translation | AQ6: NO | AT6: Bro, who taught you Spanish to speak so well? | AU6: 4. Creative Shifts | AV6: Modification – Cultural | AW6: YES | AZ6: Bro, who taught you Spanish to speak so well? | BA6: 4. Creative Shifts | BB6: Modification – Cultural | BC6: YES | BF6: Uncle, who taught you Spanish to speak so well? | BG6: 1. Reproduction | BH6: Direct Translation | BI6: NO | BL6: Dude, who taught you Spanish to speak so well? | BM6: 4. Creative Shifts | BN6: Modification – Cultural | BO6: YES | BR6: Dude, who taught you Spanish to speak so well? | BS6: 4. Creative Shifts | BT6: Modification – Cultural | BU6: YES | BX6: Oui, who taught you how to speak Spanish so well? | BY6: 3. Errors | CA6: NO | CD6: Bro, who taught you Spanish to speak so well? | CE6: 4. Creative Shifts | CF6: Modification – Cultural | CG6: YES | CJ6: Dude, who taught you Spanish to speak so well? | CK6: 4. Creative Shifts | CL6: Modification – Cultural | CM6: YES | CP6: Dude, who taught you Spanish to speak so well? | CQ6: 4. Creative Shifts | CR6: Modification – Cultural | CS6: YES
A7: [empieza tema de conversación] | B7: ¿La música española te gusta? Sí, Canto del Loco, Amaral, La Oreja de Van Gogh. Esto es muy fuerte, tío. | C7: Me encanta. Amaral me parece la mejor artista de España. | D7: ¿La música española te gusta? Sí, Canto del Loco, Amaral, La Oreja de Van Gogh. Esto es muy fuerte, tío. | E7: 3. Pragmatics and Discourse | F7: 3.2 | G7: Familiar address or vocatives | H7: brother / mate / buddy / pal / dude / bro / man | I7: WordReference | J7: Do you like Spanish music? Yes, Canto del Loco, Amaral, La Oreja de Van Gogh. This is really good, mate. | K7: 4. Creative Shifts | L7: Modification – Cultural | M7: YES | P7: Do you like Spanish music? Yeah, Canto del Loco, Amaral, La Oreja de Van Gogh. This is really good, mate. | Q7: 4. Creative Shifts | R7: Modification – Cultural | S7: YES | V7: "Do you like Spanish music? Yeah, Canto del Loco, Amaral, La Oreja de Van Gogh. This is really good, man." | W7: 4. Creative Shifts | X7: Modification – Cultural | Y7: YES | AB7: Do you like Spanish music? Yes, Canto del Loco, Amaral, La Oreja de Van Gogh. This is really good, mate. | AC7: 4. Creative Shifts | AD7: Modification – Cultural | AE7: YES | AH7: Do you like Spanish music? Yeah, Canto del Loco, Amaral, La Oreja de Van Gogh. This is really good, mate. | AI7: 4. Creative Shifts | AJ7: Modification – Cultural | AK7: YES | AN7: Do you like Spanish music? Yeah, Canto del Loco, Amaral, La Oreja de Van Gogh. That's really strong, dude. | AO7: 4. Creative Shifts | AP7: Modification – Cultural | AQ7: YES | AT7: Do you like Spanish music? Yeah, Canto del Loco, Amaral, La Oreja de Van Gogh. That's really strong, dude. | AU7: 4. Creative Shifts | AV7: Modification – Cultural | AW7: YES | AZ7: Do you like Spanish music? Yeah, Canto del Loco, Amaral, La Oreja de Van Gogh. That's really strong, man. | BA7: 4. Creative Shifts | BB7: Modification – Cultural | BC7: YES | BF7: Do you like Spanish music? Yeah, Canto del Loco, Amaral, La Oreja de Van Gogh. That's really strong, dude. | BG7: 4. Creative Shifts | BH7: Modification – Cultural | BI7: YES | BL7: "Do you like Spanish music? Yeah, Canto del Loco, Amaral, La Oreja de Van Gogh. This is really strong, dude." | BM7: 4. Creative Shifts | BN7: Modification – Cultural | BO7: YES | BR7: Do you like Spanish music? Yes, Canto del Loco, Amaral, La Oreja de Van Gogh. This is very strong, dude. | BS7: 4. Creative Shifts | BT7: Modification – Cultural | BU7: YES | BX7: "The Spanish music do you like? Yes, ""Canto del Loco"", ""Amaral"", ""La Oreja de Van Gogh""." This is very strong, man. | BY7: 4. Creative Shifts | BZ7: Modification – Cultural | CA7: YES | CD7: Do you like Spanish music? Yes, Canto del Loco, Amaral, La Oreja de Van Gogh. This is very strong, dude. | CE7: 4. Creative Shifts | CF7: Modification – Cultural | CG7: YES | CJ7: Do you like Spanish music? Yes, Canto del Loco, Amaral, La Oreja de Van Gogh. This is very strong, dude. | CK7: 4. Creative Shifts | CL7: Modification – Cultural | CM7: YES | CP7: Do you like Spanish music? Yes, Canto del Loco, Amaral, La Oreja de Van Gogh. This is very strong, dude. | CQ7: 4. Creative Shifts | CR7: Modification – Cultural | CS7: YES
A8: [empieza tema de conversación] | B8: Como una persona que eres japonés: ¿no te parece como un poco raro que prácticamente todo el mundo esté que no caga con Japón? | C8: Sí, la verdad es que sí. Todo el mundo está metido en el tema de animes y viene aquí comprando figuras y todo eso. A mí me parece bien, pero que es raro. | D8: Como una persona que eres japonés: ¿no te parece como un poco raro que prácticamente todo el mundo esté que no caga con Japón? | E8: 1. Lexicon and Vocabulary | F8: 1.4 | G8: Idiomatic expressions and colloquial phraseology | H8: To be hyped / Over the moon | J8: "As a Japanese person, don't you think it's a bit strange that practically everyone seems to have a negative opinion of Japan?" | K8: 3. Errors | M8: NO | P8: As a person who is Japanese, don't you think it's a bit weird that practically everyone is so obsessed with Japan? | Q8: 4. Creative Shifts | R8: Abstraction – Paraphrase | S8: NO | V8: As someone who's Japanese, doesn't it seem a bit odd that almost everyone is so obsessed with Japan? | W8: 4. Creative Shifts | X8: Abstraction – Paraphrase | Y8: NO | AB8: As a Japanese person, doesn't it seem a bit strange to you that practically everyone is so keen on Japan? | AC8: 4. Creative Shifts | AD8: Abstraction – Paraphrase | AE8: NO | AH8: As someone who is Japanese, don't you think it's a bit strange that practically everyone is so obsessed with Japan? | AI8: 4. Creative Shifts | AJ8: Abstraction – Paraphrase | AK8: NO | AN8: As someone who's Japanese: don't you think it's kind of weird that practically everyone is obsessed with Japan? | AO8: 4. Creative Shifts | AP8: Abstraction – Paraphrase | AQ8: NO | AT8: As a person who's Japanese: Doesn't it seem a little weird that practically everyone's all over Japan these days? | AU8: 3. Errors | AW8: NO | AZ8: As someone who's Japanese: Doesn't it seem a bit weird that practically everyone's obsessed with Japan? | BA8: 4. Creative Shifts | BB8: Abstraction – Paraphrase | BC8: NO | BF8: As a person who is Japanese: doesn't it seem a bit weird that practically everyone is into Japan these days? | BG8: 4. Creative Shifts | BH8: Abstraction – Paraphrase | BI8: NO | BL8: As a Japanese person, don’t you think it’s kind of weird that practically everyone is all over Japan these days? | BM8: 3. Errors | BO8: NO | BR8: As a person who is Japanese: don't you think it's a bit weird that practically everyone is obsessed with Japan? | BS8: 4. Creative Shifts | BT8: Abstraction – Paraphrase | BU8: NO | BX8: As a person who is Japanese: Doesn’t it seem like kind of weird that practically everyone seems obsessed with Japan?"} | BY8: 4. Creative Shifts | BZ8: Abstraction – Paraphrase | CA8: NO | CD8: As a Japanese person: Don't you think it's a bit weird that practically everyone is obsessed with Japan? | CE8: 4. Creative Shifts | CF8: Abstraction – Paraphrase | CG8: NO | CJ8: As a person who is Japanese: don't you think it's a bit strange that practically everyone is obsessed with Japan? | CK8: 4. Creative Shifts | CL8: Abstraction – Paraphrase | CM8: NO | CP8: As a person who is Japanese: Don't you think it's a bit strange that practically everyone is obsessed with Japan? | CQ8: 4. Creative Shifts | CR8: Abstraction – Paraphrase | CS8: NO
A9: [empieza tema de conversación] | B9: Yo trabajaba en un edificio, en una multinacional. Lanzan un comunicado, una agencia de todos súper pijos y todos súper moneymakers y aquí somos todos la hostia, pues había un zurullo, tío, un zurullo fuera del váter. | C9: Eso se hizo viral y todo el mundo, claro, al final los conocemos todos, aunque estéis en agencias diferentes, todo el mundo empezó a hacerse eco, salió hasta en Twitter... | D9: Yo trabajaba en un edificio, en una multinacional. Lanzan un comunicado, una agencia de todos superpijos y todos súper moneymakers y aquí somos todos la hostia, pues había un zurullo, tío, un zurullo fuera del váter. | E9: 1. Lexicon and Vocabulary | F9: 1.3 | G9: Lexical shortening and abbreviations | J9: I used to work in a building, at a multinational company. They put out a statement – a really posh agency, full of people obsessed with making money, and they acted like they were the best. But there was this incident, you know, something happened outside the toilet. | K9: 2. Omissions | L9: Shortcut Solution | M9: NO | P9: So, I used to work in a building, at a multinational company. They put out a statement – this agency was full of posh people, all making loads of money, and we were all supposed to be the best. But then, there was this incident, mate, a real mess. It happened outside the toilet. | Q9: 4. Creative Shifts | R9: Abstraction – Superordinate Term | S9: NO | V9: "I used to work in a building, at a multinational company. They put out a statement – it was an agency full of really posh people, all about making money, and we were all supposed to be the best. But there was this... incident, mate, this thing happened outside the toilet. | W9: 4. Creative Shifts | X9: Abstraction – Superordinate Term | Y9: NO | AB9: "I worked in a building, at a multinational company. They put out a statement – it was an agency full of really posh people, all obsessed with making money, and we were all supposed to be the best. But there was this... incident, you know, a mess outside the toilet." | AC9: 4. Creative Shifts | AD9: Abstraction – Superordinate Term | AE9: NO | AH9: "I used to work in a building, at a multinational company. They put out a statement – this agency was full of really posh people, all obsessed with making money, and we were all supposed to be the best. But then, there was this incident, you know, something happened outside the toilet. | AI9: 4. Creative Shifts | AJ9: Modification – Situational | AK9: NO | AN9: I used to work in a building, at a multinational company. They released a statement, through an agency full of super posh people and all these super money-makers, and here we were all just the worst, man, there was a total mess, like, a complete disaster outside the bathroom. | AO9: 1. Reproduction | AP9: Direct Translation | AQ9: YES | AT9: I used to work in a building, at a multinational company. They released a statement, through an agency full of super posh people and all these super money-makers, and here we were, everyone was totally messed up, there was this guy, dude, a total loser, like, outside the bathroom. | AU9: 1. Reproduction | AV9: Direct Translation | AW9: YES | AZ9: I used to work in a building, in a multinational company. They released a statement, through an agency full of super posh people and all these super money-makers, and here we were, everyone was totally messed up, because there was this guy, man, a total mess-up, outside the toilet. | BA9: 1. Reproduction | BB9: Direct Translation | BC9: YES | BF9: I used to work in a building, at a multinational company. They released a statement, through an agency full of super posh people and all these super money-makers, and here we were all the talk, because there was this guy, man, a real loser, outside the restroom. | BG9: 1. Reproduction | BH9: Direct Translation | BI9: YES | BL9: I used to work in a building, in a multinational. They released a statement, an agency full of all super posh people and all super money-makers, and here we were all the worst, because there was a total idiot, dude, an idiot outside the toilet. | BM9: 1. Reproduction | BN9: Direct Translation | BO9: YES | BR9: I used to work in an office, in a multinational company. They send out a press release, a super posh PR agency and everyone's super money-makers and we're all so cool, there was a turd, dude, a turd outside the toilet. | BS9: 1. Reproduction | BT9: Direct Translation | BU9: YES | BX9: I worked in a building at a multinational company. They issued a statement, all their employees were very posh and they were all making money, and here we are all like hell, there was a turd outside the toilet. | BY9: 1. Reproduction | BZ9: Direct Translation | CA9: YES | CD9: I used to work in a building, in a multinational company. They send out a statement, a super posh agency and all the super moneymakers and here we are all amazing, well there was a turd, dude, a turd outside the toilet. | CE9: 1. Reproduction | CF9: Direct Translation | CG9: YES | CJ9: I used to work in a building, in a multinational. They send out a statement, a super posh agency and all the super money makers and here we are all the hype, there was a turd, dude, a turd outside the toilet. | CK9: 1. Reproduction | CL9: Direct Translation | CM9: YES | CP9: I used to work in a building, in a multinational. They send out a statement, a super posh agency and all the super moneymakers and here we are all the hype, there was a turd, dude, a turd outside the toilet. | CQ9: 1. Reproduction | CR9: Direct Translation | CS9: YES
A10: [empieza tema de conversación] | B10: Yo voy a abrir un melón. En tus vídeos se critica mucho a los franceses. Yo hoy vengo a defenderles, tío. Son los menos tocahuevos. | C10: De verdad, te lo juro, o sea, llegan, te piden su café latte y ya está, y no te dan por culo Pero es que tengo 3 nacionalidades, les metí a un patadón, tengo top 3 Empezando por abajo, los chinos son unos maleducados Y yo les volví a decir Pero bueno, por lo menos nos han pedido en mi cara que te agradece Eso está bien, eh Luego los segundos, bueno, es que están ahí los portugueses y los italianos | D10: Yo voy a abrir un melón. En tus vídeos se critica mucho a los franceses. Yo hoy vengo a defenderles, tío. Son los menos tocahuevos. | E10: 1. Lexicon and Vocabulary | F10: 1.2 | G10: Colloquial lexicon and slang | H10: Pain in the ass / butt | I10: Cambridge | J10: Okay, I'm going to open a melon. In your videos, you criticise the French a lot. But today, I'm here to defend them, mate. They're the least intrusive. | K10: 3. Errors | M10: NO | P10: I'm going to open up about something. In your videos, you criticise the French a lot. Today, I'm here to defend them, mate. They're the least annoying. | Q10: 4. Creative Shifts | R10: Abstraction – Superordinate Term | S10: NO | V10: "I'm going to cut open a melon. In your videos, you criticize the French a lot. I'm here today to defend them, mate. They're the least intrusive. | W10: 3. Errors | Y10: NO | AB10: "I'm going to cut open a melon. In your videos, you criticise the French a lot. But today, I'm here to defend them, mate. They're the least intrusive." | AC10: 3. Errors | AE10: NO | AH10: I'm going to open a melon. In your videos, you criticise the French a lot. I'm here today to defend them, mate. They're the least nosy. | AI10: 3. Errors | AK10: NO | AN10: I'm going to open a watermelon. In your videos, the French are criticized a lot. I'm here today to defend them, man. They're the least of the touchy-feely types. | AO10: 3. Errors | AQ10: NO | AT10: I'm gonna open up a watermelon. In your videos, you criticize the French a lot. I'm here today to defend them, dude. They're the least of the touchy-feely types. | AU10: 3. Errors | AW10: NO | AZ10: I'm gonna cut open a watermelon. In your videos, the French are criticized a lot. Today I'm here to defend them, man. They're the least of the annoying ones. | BA10: 4. Creative Shifts | BB10: Abstraction – Superordinate Term | BC10: NO | BF10: "I'm gonna open a watermelon. In your videos, the French are criticized a lot. Today I'm here to defend them, dude. They're the least of the tocahuevos." | BG10: 1. Reproduction | BH10: Retention | BI10: NO | BL10: I'm going to open a watermelon. In your videos, the French are criticized a lot. I'm here today to defend them, dude. They're the least annoying ones. | BM10: 4. Creative Shifts | BN10: Abstraction – Superordinate Term | BO10: NO | BR10: I am going to open a melon. In your videos, French people are criticized a lot. Today I come to defend them, dude. They are the least annoying. | BS10: 4. Creative Shifts | BT10: Abstraction – Superordinate Term | BU10: NO | BX10: I am going to open a melon. In your videos they criticize France a lot. Today I come to defend them, man. They are the least annoying | BY10: 4. Creative Shifts | BZ10: Abstraction – Superordinate Term | CA10: NO | CD10: I am going to open a melon. In your videos, the French are criticized a lot. Today I come to defend them, dude. They are the least annoying. | CE10: 4. Creative Shifts | CF10: Abstraction – Superordinate Term | CG10: NO | CJ10: I am going to open a melon. In your videos, French people are criticized a lot. Today I come to defend them, dude. They are the least touchy-feely. | CK10: 3. Errors | CM10: NO | CP10: I'm going to open a can of worms. In your videos, you criticize the French a lot. Today I'm here to defend them, man. They're the least annoying. | CQ10: 4. Creative Shifts | CR10: Abstraction – Superordinate Term | CS10: NO
A11: [empieza tema de conversación] | B11: Era por la mañana, pero te estoy hablando 7 y media. Vemos entrar a una chica y a un chico jovencitos. Se pusieron ahí enfrente de la barra y empezaron a magrearse, a darse unos buenos besitos y nosotras diciendo, bueno, pues bien. | C11: Limpiando un vaso, sí. Y se estaban comiendo, literal. Se levanta el chico y se va al baño. 30 segundos, se levanta la chica y se va para el baño. Pasa media hora, me da por preguntarle a mi compañera, oye, ¿tú has visto salir a estos 2 de la tienda? Porque no había nadie, yo salgo al baño de los chicos Pone el código y estaban ahí Pasándoselo súper bien | D11: Era por la mañana, pero te estoy hablando 7 y media. Vemos entrar a una chica y a un chico jovencitos. Se pusieron ahí enfrente de la barra y empezaron a magrearse, a darse unos buenos besitos y nosotras diciendo, bueno, pues bien. | E11: 1. Lexicon and Vocabulary | F11: 1.2 | G11: Colloquial lexicon and slang | H11: To grope / Make out | I11: WordReference | J11: It was in the morning, but I'm telling you this at 7:30. We saw a young girl and a young guy walk in. They went and sat at the bar and started getting all affectionate, giving each other proper kisses, and we were just thinking, "Okay, fine." | K11: 4. Creative Shifts | L11: Abstraction – Paraphrase | M11: NO | P11: It was in the morning, but I'm telling you this at 7:30. We saw a young girl and a young guy walk in. They went and stood in front of the bar and started getting all lovey-dovey, giving each other proper kisses, and we were just like, "Okay, good for them." | Q11: 4. Creative Shifts | R11: Abstraction – Paraphrase | S11: NO | V11: It was in the morning, but I'm telling you this at 7:30. We saw a young girl and a young guy walk in. They went to the bar and started getting all lovey-dovey, giving each other proper kisses, and we were just like, "Okay, whatever." | W11: 4. Creative Shifts | X11: Abstraction – Paraphrase | Y11: NO | AB11: It was in the morning, but I'm telling you this at 7:30. We saw a young girl and a young boy walk in. They went and sat at the bar and started getting all affectionate, giving each other proper kisses, and we were just thinking, "Okay, fine." | AC11: 4. Creative Shifts | AD11: Abstraction – Paraphrase | AE11: NO | AH11: It was in the morning, but I'm telling you this at 7:30. We saw a young girl and a young guy walk in. They went and sat at the bar and started getting all cosy, giving each other proper kisses, and we were just thinking, "Okay, fine." | AI11: 4. Creative Shifts | AJ11: Abstraction – Paraphrase | AK11: NO | AN11: It was in the morning, but I'm talking to you at 7:30. We saw a young guy and girl walk in. They stood right in front of the bar and started getting all affectionate, giving each other some big kisses, and us saying, "Well, that's nice." | AO11: 4. Creative Shifts | AP11: Abstraction – Paraphrase | AQ11: NO | AT11: It was morning, but I'm talking to you at 7:30. We saw a girl and a young guy walking in. They stood right in front of the bar and started getting all affectionate, giving each other some big kisses, and us saying, "Well, okay, that's fine." | AU11: 4. Creative Shifts | AV11: Abstraction – Paraphrase | AW11: NO | AZ11: It was morning, but I'm talking to you at 7:30. We see a girl and a young guy walking in. They stood right in front of the bar and started getting all affectionate, giving each other nice kisses, and us saying, "Well, okay, that's fine." | BA11: 4. Creative Shifts | BB11: Abstraction – Paraphrase | BC11: NO | BF11: It was in the morning, but I'm talking to you at 7:30. We saw a young girl and a young guy walk in. They stood right in front of the bar and started making out, giving each other some good kisses, and us saying, "Well, that's nice." | BG11: 1. Reproduction | BH11: Direct Translation | BI11: YES | BL11: It was morning, but I’m talking to you at 7:30. We saw a girl and a young guy walk in. They stood right in front of the bar and started flirting, giving each other some nice kisses, and we were saying, well, okay, that’s fine. | BM11: 4. Creative Shifts | BN11: Abstraction – Paraphrase | BO11: NO | BR11: It was morning, but I'm talking to you at 7:30. We see a girl and a young boy enter. They stood there in front of the bar and started groping each other, giving each other big kisses, and we were saying, well, that's good. | BS11: 1. Reproduction | BT11: Direct Translation | BU11: YES | BX11: It was morning, but I am talking to you at seven thirty. We see a girl and a young guy enter. They stood there facing the bar and started groping each other, giving themselves good kisses and we saying, well, okay | BY11: 1. Reproduction | BZ11: Direct Translation | CA11: YES | CD11: It was in the morning, but I'm talking to you at 7:30. We see a girl and a young boy enter. They stood there in front of the bar and started to caress each other, giving each other good kisses and we were saying, well, that's good. | CE11: 4. Creative Shifts | CF11: Abstraction – Paraphrase | CG11: NO | CJ11: It was in the morning, but I'm talking to you at 7:30. We see a girl and a young boy enter. They stood there in front of the bar and started to caress each other, giving each other good kisses and we were saying, well, that's good. | CK11: 4. Creative Shifts | CL11: Abstraction – Paraphrase | CM11: NO | CP11: It was in the morning, but I'm talking to you at 7:30. We see a girl and a young boy enter. They stood there in front of the bar and started touching each other, giving each other big kisses, and we were saying, well, that's good. | CQ11: 4. Creative Shifts | CR11: Abstraction – Paraphrase | CS11: NO
A12: [empieza tema de conversación] | B12: Entonces fui, miraba los pisos, era a lo mejor como un bajo a tomar por el culo con humedades 1 habitación asquerosa. Mil euros cada uno. Conseguí llorarle un montón a los de la residencia. Puede que haya un sitio, pero tienes que compartir con 5 israelíes. Me doy con un canto en los dientes. | C12: Yo no sabía que Jerusalén iba a hacer un frío que te cagas. No tenía edredón y me pasé, no sé si te digo, a lo mejor los 6 meses durmiendo en el saco de dormir hasta que no me compré una almohada. | D12: Entonces fui, miraba los pisos, era a lo mejor como un bajo a tomar por el culo con humedades 1 habitación asquerosa. Mil euros cada uno. Conseguí llorarle un montón a los de la residencia. Puede que haya un sitio, pero tienes que compartir con 5 israelíes. Me doy con un canto en los dientes. | E12: 1. Lexicon and Vocabulary | F12: 1.4 | G12: Idiomatic expressions and colloquial phraseology | H12: count your lucky stars / count your blessings / consider yourself lucky | I12: WordReference | J12: So, I went to look at some flats, and they were all awful – basically, damp, cramped one-bedroom places. And they were charging a thousand euros each. I managed to get the people at the student accommodation to feel sorry for me. There might be a place available, but you'd have to share with five Israelis. I'm just grateful to have somewhere to stay. | K12: 4. Creative Shifts | L12: Abstraction – Paraphrase | M12: NO | P12: So, I went there, looking at the flats. They were, at best, tiny studios, probably damp, with one disgusting room. And they were charging a thousand euros each. I managed to get on the good side of the people at the residence, so hopefully, there might be a place, but you'd have to share with five Israelis. Still, I'm happy enough. | Q12: 3. Errors | S12: NO | V12: So, I went there, looking at the apartments, and it was probably like a tiny, damp basement, one disgusting room. A thousand euros each. I managed to get on their good side, really pull at their heartstrings. There might be a place, but you have to share with five Israelis. I'm happy just to have somewhere. | W12: 4. Creative Shifts | X12: Abstraction – Paraphrase | Y12: NO | AB12: "So, I went to look at the apartments, and they were, well, maybe like a ground-floor flat, damp, with one disgusting room. And they were asking a thousand euros each. I managed to really plead with the people at the residence. There might be a place, but you'd have to share with five Israelis. I'm just glad to have somewhere. | AC12: 4. Creative Shifts | AD12: Abstraction – Paraphrase | AE12: NO | AH12: So, I went to look at the apartments, and they were awful – basically, damp, one-bedroom dumps. And they were charging a thousand euros each. I managed to get the people at the residence to lower the price a bit. There might be a place available, but you'd have to share with five Israelis. I'm just grateful to have somewhere. | AI12: 4. Creative Shifts | AJ12: Abstraction – Paraphrase | AK12: NO | AN12: So I went, I was looking at the apartments, it was maybe like a basement with dampness, one disgusting room. A thousand euros each. I managed to cry a lot to the housing office. There might be a place, but you have to share with five Israelis. I'm just biting my tongue. | AO12: 3. Errors | AQ12: NO | AT12: So I went, I was looking at the apartments, it was maybe like a basement to take a dump with dampness, one filthy room. Each one was a thousand euros. I begged the housing office so much, maybe there's a place, but you have to share with five Israelis. I'm just shaking my head in disbelief. | AU12: 3. Errors | AW12: NO | AZ12: Then I went, looking at the apartments—it was basically like a basement to take a dump with dampness, one disgusting room. Each one was a thousand euros. I cried a lot to the housing office. There might be a spot, but you have to share with five Israelis. I'm just glad I got it. | BA12: 4. Creative Shifts | BB12: Abstraction – Paraphrase | BC12: NO | BF12: So I went, I was looking at apartments—it was kind of like a basement with dampness, one disgusting room. Each one was a thousand euros. I cried a lot to the people at the housing office. There might be a place, but you have to share with five Israelis. I'm just laughing through my teeth. | BG12: 3. Errors | BI12: NO | BL12: So I went there, looking at the apartments — it was maybe like a basement that was a total mess, with dampness and just one filthy room. Each one cost a thousand euros. I really pleaded with the people at the housing office. There might be a place, but you have to share it with five Israelis. I’m going to end up laughing at myself. | BM12: 3. Errors | BO12: NO | BR12: So I went, I looked at the flats, it was maybe like a basement to take the piss with damp 1 disgusting room. A thousand euros each. I managed to cry a lot to the people at the residence. Maybe there's a place, but you have to share with 5 Israelis. I give myself a pat on the back. | BS12: 3. Errors | BU12: NO | BX12: So then I went there, looked at the flats - maybe like a basement somewhere with mould, one disgusting room, each one costs a thousand Euros. Managed to make them cry a lot at the hostel. Maybe there will be a place, but you have to share with five Israelis. I give myself credit. | BY12: 3. Errors | CA12: NO | CD12: Then I went, I looked at the flats, it was maybe like a basement to take the piss with damp 1 disgusting room. 1,000 euros each. I managed to cry a lot to the people at the residence. Maybe there's a place, but you have to share with 5 Israelis. I give myself a pat on the back. | CE12: 3. Errors | CG12: NO | CJ12: Then I went, I looked at the flats, it was maybe like a basement to take the piss with damp 1 disgusting room. A thousand euros each. I managed to cry a lot to the people at the residence. Maybe there's a place, but you have to share with 5 Israelis. I give myself a pat on the back | CK12: 3. Errors | CM12: NO | CP12: Then I went, I looked at the flats, it was maybe like a basement to take the piss with damp 1 disgusting room. A thousand euros each. I managed to cry a lot to the people at the residence. There may be a place, but you have to share with 5 Israelis. I give myself a pat on the back. | CQ12: 3. Errors | CS12: NO
A13: [empieza tema de conversación] | B13: Había una chica, esta tía era del Reino Unido, y su familia era súper religiosa, pero súper religiosa a lo bestia, protestante. Lo típico de falda hasta los tobillos, nunca había hecho nada con nadie y tal. | C13: ¿Sabes el síndrome de Jerusalén, que es que la gente viene y le da un sentimiento muy heavy de no a Jesucristo? Pues yo creo que le pasa lo contrario, sea, fue heavy metal. | D13: Había una chica, esta tía era del Reino Unido, y su familia era súper religiosa, pero súper religiosa a lo bestia, protestante. Lo típico de falda hasta los tobillos, nunca había hecho nada con nadie y tal. | E13: 1. Lexicon and Vocabulary | F13: 1.5 | G13: Informal intensifiers and quantifiers | H13: Like crazy / Like mad / Like there was no tomorrow | I13: WordReference | J13: There was this girl, she was from the UK, and her family was incredibly religious, like, extremely religious, Protestant. The typical thing, you know, skirts down to her ankles, she'd never done anything with anyone before. | K13: 4. Creative Shifts | L13: Abstraction – Superordinate Term | M13: NO | P13: There was this girl, she was from the UK, and her family was incredibly religious, like, extremely religious, Protestant. The usual – long skirts down to her ankles, she'd never done anything with anyone, you know. | Q13: 4. Creative Shifts | R13: Abstraction – Superordinate Term | S13: NO | V13: "There was this girl, she was from the UK, and her family were incredibly religious, like, seriously extreme, Protestant. The typical thing, skirts down to her ankles, she'd never done anything with anyone, you know? | W13: 4. Creative Shifts | X13: Abstraction – Superordinate Term | Y13: NO | AB13: There was this girl, she was from the UK, and her family were extremely religious, like, incredibly religious, Protestant. The typical thing, skirts down to her ankles, she'd never done anything with anyone, you know. | AC13: 4. Creative Shifts | AD13: Abstraction – Superordinate Term | AE13: NO | AH13: There was this girl, she was from the UK, and her family was incredibly religious, like, extremely religious, Protestant. The typical thing, skirts down to her ankles, she'd never done anything with anyone, you know? | AI13: 4. Creative Shifts | AJ13: Abstraction – Superordinate Term | AK13: NO | AN13: There was this girl, this chick was from the UK, and her family was super religious, like really religious, Protestant. The typical stuff—skirt down to the knees, never done anything with anyone, you know. | AO13: 4. Creative Shifts | AP13: Abstraction – Paraphrase | AQ13: NO | AT13: There was this girl, this chick was from the UK, and her family was super religious, like super religious in the most extreme way, Protestant. The typical stuff—skirt down to the knees, never done anything with anyone, you know. | AU13: 4. Creative Shifts | AV13: Abstraction – Paraphrase | AW13: NO | AZ13: There was this girl, this chick was from the UK, and her family was super religious, like really religious, Protestant. The typical stuff—skirt down to the ankles, never done anything with anyone, you know. | BA13: 4. Creative Shifts | BB13: Abstraction – Superordinate Term | BC13: NO | BF13: There was this girl, this chick was from the UK, and her family was super religious, like super religious in the most extreme way, Protestant. The typical stuff—skirt down to the ankles, never done anything with anyone, you know. | BG13: 4. Creative Shifts | BH13: Abstraction – Paraphrase | BI13: NO | BL13: There was this girl, this chick was from the UK, and her family was super religious, like super religious in the most extreme, Protestant way. The typical stuff—long skirts all the way down to her ankles, never done anything with anyone, you know. | BM13: 4. Creative Shifts | BN13: Abstraction – Paraphrase | BO13: NO | BR13: There was a girl, this girl was from the UK, and her family was super religious, but super religious to the extreme, Protestant. The typical skirt to the ankles, had never done anything with anyone and so on. | BS13: 4. Creative Shifts | BT13: Abstraction – Paraphrase | BU13: NO | BX13: There was this girl, this chick was from Britain, and her family was super religious, but super religious hardcore Protestant. Like typical skirt all the way down to their heels never did anything with anyone like that | BY13: 4. Creative Shifts | BZ13: Modification – Situational | CA13: NO | CD13: There was a girl, this girl was from the UK, and her family was super religious, but super religious to the extreme, Protestant. The typical skirt to the ankles, had never done anything with anyone and such. | CE13: 4. Creative Shifts | CF13: Abstraction – Paraphrase | CG13: NO | CJ13: There was a girl, this girl was from the UK, and her family was super religious, but super religious to the extreme, Protestant. The typical skirt to the ankles, had never done anything with anyone and so on. | CK13: 4. Creative Shifts | CL13: Abstraction – Paraphrase | CM13: NO | CP13: There was a girl, this girl was from the UK, and her family was super religious, but super religious to the extreme, Protestant. The typical skirt to the ankles, had never done anything with anyone and so on. | CQ13: 4. Creative Shifts | CR13: Abstraction – Paraphrase | CS13: NO
A14: [empieza tema de conversación] | B14: ¿Y el Cairo qué tal? Está muy guapo como unas pirámides que dices, Dios, es probablemente la cosa más tocha de la humanidad. | C14: Hicimos una ruta de 14 días. Íbamos a Urgeada y hay un tío muy random que nos empieza a seguir. No me acuerdo ni cómo se llama. | D14: ¿Y el Cairo qué tal? Está muy guapo como unas pirámides que dices, Dios, es probablemente la cosa más tocha de la humanidad. | E14: 1. Lexicon and Vocabulary | F14: 1.5 | G14: Informal intensifiers and quantifiers | J14: "And what about Cairo? It's really beautiful, like you said, with those pyramids. Wow, it's probably the most impressive thing humanity has ever created. | K14: 4. Creative Shifts | L14: Abstraction – Superordinate Term | M14: NO | P14: So, how was Cairo? It's really beautiful, with those pyramids you mentioned. God, it's probably the most impressive thing humanity has ever created. | Q14: 4. Creative Shifts | R14: Abstraction – Superordinate Term | S14: NO | V14: "And how was Cairo? It's supposed to be really beautiful, with those pyramids you mentioned. God, it's probably the most impressive thing humanity has ever created." | W14: 4. Creative Shifts | X14: Abstraction – Superordinate Term | Y14: NO | AB14: "And how was Cairo? It's really beautiful, like those pyramids you mentioned. Wow, it's probably the most impressive thing humanity has ever created." | AC14: 4. Creative Shifts | AD14: Abstraction – Superordinate Term | AE14: NO | AH14: "And how was Cairo? It's really beautiful, like you said, with those pyramids. Wow, it's probably the most impressive thing humanity has ever created." | AI14: 4. Creative Shifts | AJ14: Abstraction – Superordinate Term | AK14: NO | AN14: And how was Cairo? It's really nice, like the pyramids you were talking about—God, it's probably the weirdest thing in humanity. | AO14: 3. Errors | AQ14: NO | AT14: How's Cairo? It's really nice, like the pyramids you mentioned, man, God, it's probably the weirdest thing in humanity. | AU14: 3. Errors | AW14: NO | AZ14: How's Cairo? It's really cool, like the pyramids you mentioned, God, it's probably the most messed-up thing in humanity. | BA14: 3. Errors | BC14: NO | BF14: And how's Cairo? It's really nice, like the pyramids you mentioned, God, it's probably the most weird thing in humanity. | BG14: 3. Errors | BI14: NO | BL14: And how was Cairo? It's really cool, like the pyramids you mentioned, God, it's probably the weirdest thing in humanity. | BM14: 3. Errors | BO14: NO | BR14: And Cairo, how was it? It's very cool with those pyramids you say, God, it's probably the most awesome thing in the world. | BS14: 4. Creative Shifts | BT14: Modification – Situational | BU14: NO | BX14: "Cairo how about?" It's very beautiful like some pyramids that say God, it's probably the most stupid thing in humanity. | BY14: 3. Errors | CA14: NO | CD14: And Cairo, how was it? It's very cool with those pyramids you say, God, it's probably the most awesome thing in the world. | CE14: 4. Creative Shifts | CF14: Modification – Situational | CG14: NO | CJ14: And Cairo, how was it? It's very cool with those pyramids you say, God, it's probably the most awesome thing in the world. | CK14: 4. Creative Shifts | CL14: Modification – Situational | CM14: NO | CP14: And Cairo, how was it? It's very cool with those pyramids you say, God, it's probably the most awesome thing in the world. | CQ14: 4. Creative Shifts | CR14: Modification – Situational | CS14: NO
A15: [empieza tema de conversación] | B15: Yo me fui de Jerusalén como en julio del 2023 y había muchas tensiones muy heavies. A lo mejor tiraban en un día cinco mil misiles encima de Tel Aviv, que nunca tiran a Tel Aviv. | C15: A lo mejor tiraban en un día cinco mil misiles encima de Tel Aviv, que nunca tiran a Tel Aviv. Claro, yo me acuerdo muchas veces que a lo mejor estaba donde mi joyero, porque yo tenía allí un joyero en Jerusalén que el tío estaba pinzado de cojones. | D15: Yo me fui de Jerusalén como en julio del 2023 y había muchas tensiones muy heavies. A lo mejor tiraban en un día cinco mil misiles encima de Tel Aviv, que nunca tiran a Tel Aviv. | E15: 1. Lexicon and Vocabulary | F15: 1.8 | G15: Neologisms | H15: heavy | I15: WordReference | J15: "I left Jerusalem in July 2023, and there was a lot of very intense tension. They might launch five thousand missiles at Tel Aviv in a single day, which they never usually do." | K15: 4. Creative Shifts | L15: Abstraction – Superordinate Term | M15: NO | P15: "I left Jerusalem in July 2023, and there were a lot of really heavy tensions. They might launch five thousand missiles at Tel Aviv in a single day, which they never usually do." | Q15: 1. Reproduction | R15: Retention | S15: NO | V15: I left Jerusalem in July 2023, and there were a lot of really heavy tensions. They might have fired five thousand missiles at Tel Aviv in a single day, which they never usually do. | W15: 1. Reproduction | X15: Retention | Y15: NO | AB15: "I left Jerusalem in July 2023, and there was a lot of very intense tension. They might have fired five thousand missiles at Tel Aviv in a single day, which they never usually do." | AC15: 4. Creative Shifts | AD15: Abstraction – Superordinate Term | AE15: NO | AH15: I left Jerusalem in July 2023, and there was a lot of really intense tension. They might have fired five thousand missiles at Tel Aviv in a single day, which they never usually do. | AI15: 4. Creative Shifts | AJ15: Abstraction – Superordinate Term | AK15: NO | AN15: I left Jerusalem around July 2023, and there were a lot of heavy tensions. Maybe they launched five thousand missiles over Tel Aviv in one day, which they never do to Tel Aviv. | AO15: 1. Reproduction | AP15: Retention | AQ15: NO | AT15: I left Jerusalem around July 2023, and there were a lot of heavy tensions. Maybe they launched five thousand missiles over Tel Aviv in one day, which they never do to Tel Aviv. | AU15: 1. Reproduction | AV15: Retention | AW15: NO | AZ15: I left Jerusalem around July 2023 and there were a lot of heavy tensions. Maybe they launched five thousand missiles over Tel Aviv in one day, but they never actually hit Tel Aviv. Of course, I remember many times that maybe I was where my jeweler was, because I had a jeweler in Jerusalem and the guy was totally stressed out. | BA15: 1. Reproduction | BB15: Retention | BC15: NO | BF15: I left Jerusalem around July 2023, and there were a lot of heavy tensions. Maybe they launched five thousand missiles over Tel Aviv in one day, which they never do to Tel Aviv. | BG15: 1. Reproduction | BH15: Retention | BI15: NO | BL15: I left Jerusalem around July 2023, and there were a lot of heavy tensions. Maybe they launched five thousand missiles over Tel Aviv in one day, which they never do to Tel Aviv. Of course, I remember many times when maybe I was where my jeweler was, because I had a jeweler in Jerusalem, and the guy was really on edge. | BM15: 1. Reproduction | BN15: Retention | BO15: NO | BR15: I left Jerusalem around July 2023 and there were many very heavy tensions. Maybe they fired five thousand missiles on top of Tel Aviv in a day, which they never fire on Tel Aviv. Of course, I remember many times that maybe I was at my jeweler, because I had a jeweler in Jerusalem and the guy was stuck up his ass. | BS15: 1. Reproduction | BT15: Retention | BU15: NO | BX15: "I went out of Jerusalem like July last year and there were many heavy tensions. Maybe they fired five thousand missiles above Tel Aviv one day, which never fire on Tel Aviv | BY15: 1. Reproduction | BZ15: Retention | CA15: NO | CD15: I left Jerusalem around July 2023 and there were a lot of very heavy tensions. Maybe they fired five thousand missiles on top of Tel Aviv in a day, which they never fire on Tel Aviv. Of course, I remember many times that maybe I was at my jeweler, because I had a jeweler in Jerusalem and the guy was stuck up his ass. | CE15: 1. Reproduction | CF15: Retention | CG15: NO | CJ15: I left Jerusalem around July 2023 and there were a lot of very heavy tensions. Maybe they fired five thousand missiles on Tel Aviv in a day, which they never fire on Tel Aviv. Of course, I remember many times that maybe I was at my jeweler, because I had a jeweler in Jerusalem and the guy was stuck up his ass. | CK15: 1. Reproduction | CL15: Retention | CM15: NO | CP15: I left Jerusalem around July 2023 and there were many very heavy tensions. Maybe they fired five thousand missiles on top of Tel Aviv in a day, which they never fire on Tel Aviv. Of course, I remember many times that maybe I was at my jeweler, because I had a jeweler in Jerusalem and the guy was stuck up his ass. | CQ15: 1. Reproduction | CR15: Retention | CS15: NO
A16: [empieza tema de conversación] | B16: ¿Y tu profesor sigue por allí? Creo que se jubiló ya porque la había estado trabajando muchísimos años en plan en un montón de colegios de todos lados. | C16: Estuvo en Botsuana. Y yo sí que he mantenido contacto por email. Algún día me gustaría reencontrarme con él. | D16: ¿Y tu profesor sigue por allí? Creo que se jubiló ya porque la había estado trabajando muchísimos años en plan en un montón de colegios de todos lados. | E16: 3. Pragmatics and Discourse | F16: 3.1 | G16: Discourse markers | H16: As / Like | I16: WordREference | J16: Is your teacher still there? I think he's probably retired now, because he worked for a very long time, at loads of different schools all over the place. | K16: 2. Omissions | L16: Shortcut Solution | M16: NO | P16: Is your teacher still there? I think he retired, as he'd been working there for many years, at a whole bunch of schools all over the place. | Q16: 2. Omissions | R16: Shortcut Solution | S16: NO | V16: "And is your teacher still there? I think he's retired now, because he'd been working there for so many years, at loads of different schools all over the place." | W16: 2. Omissions | X16: Shortcut Solution | Y16: NO | AB16: Is your teacher still there? I think he probably retired already, because he'd been working there for a very long time, at a whole bunch of schools all over the place. | AC16: 2. Omissions | AD16: Shortcut Solution | AE16: NO | AH16: Is your teacher still there? I think he probably retired already, because he'd been working for a very long time, in a lot of different schools all over the place. | AI16: 2. Omissions | AJ16: Shortcut Solution | AK16: NO | AN16: And your teacher, is he still around? I think he already retired because he was working there for a really long time, teaching in a bunch of schools all over the place. | AO16: 2. Omissions | AP16: Shortcut Solution | AQ16: NO | AT16: And your teacher still around there? I think he already retired because he'd been working there for so many years, like in a bunch of schools all over the place. | AU16: 4. Creative Shifts | AV16: Modification – Cultural | AW16: YES | AZ16: **And your teacher is still around? I think he retired already because he was working there for years, teaching in a bunch of schools all over the place.** | BA16: 2. Omissions | BB16: Shortcut Solution | BC16: NO | BF16: "And your teacher, is he still there? I think he already retired because he had been working there for a lot of years, teaching in a bunch of schools all over the place." | BG16: 2. Omissions | BH16: Shortcut Solution | BI16: NO | BL16: And your teacher is still around there? I think he already retired because he had been working there for a lot of years, kind of like teaching in a bunch of schools all over the place. | BM16: 4. Creative Shifts | BN16: Modification – Cultural | BO16: YES | BR16: And your teacher is still there? I think he retired already because he had been working so many years in so many schools all over the place. | BS16: 2. Omissions | BT16: Shortcut Solution | BU16: NO | BX16: "And your teacher is still there? I think he retired already since he had worked so many years in lots of schools all over the place | BY16: 2. Omissions | BZ16: Shortcut Solution | CA16: NO | CD16: And your teacher is still there? I think he retired already because he had been working so many years in so many schools all over the place. | CE16: 2. Omissions | CF16: Shortcut Solution | CG16: NO | CJ16: And your teacher is still there? I think he retired already because he had been working so many years in a bunch of schools all over the place. | CK16: 2. Omissions | CL16: Shortcut Solution | CM16: NO | CP16: And your teacher is still there? I think he retired already because he had been working so many years in a bunch of schools all over the place. | CQ16: 2. Omissions | CR16: Shortcut Solution | CS16: NO
A17: [empieza tema de conversación] | B17: Bueno, pues estaban las gárgolas de las iglesias, tal, tal, tal, tal. Una iglesia en Barcelona que se llama Santilli Pereri, que es una iglesia preciosa, fue bombardeada en la Guerra Civil. | C17: Hay gente que pregunta que si las gárgolas son cañones para disparar. | D17: Bueno, pues estaban las gárgolas de las iglesias, tal, tal, tal, tal. Una iglesia en Barcelona que se llama Santilli Pereri, que es una iglesia preciosa, fue bombardeada en la Guerra Civil. | E17: 3. Pragmatics and Discourse | F17: 3.1 | G17: Discourse markers | J17: Okay, so there were the gargoyles on the churches, you know, like that. There's a church in Barcelona called Santilli Pereri, which is a beautiful church, that was bombed during the Civil War. | K17: 4. Creative Shifts | L17: Modification – Situational | M17: YES | P17: Okay, so there were the gargoyles on the churches, like, you know, all over the place. There's a church in Barcelona called Santilli Pereri, which is a beautiful church, but it was bombed during the Civil War. | Q17: 4. Creative Shifts | R17: Modification – Situational | S17: YES | V17: Right, so there were the gargoyles on the churches, you know, like that. There's a church in Barcelona called Santilli Pereri, which is a beautiful church, but it was bombed during the Civil War. | W17: 4. Creative Shifts | X17: Modification – Situational | Y17: YES | AB17: Right, so there were the gargoyles on the churches, you know, like that. There's a church in Barcelona called Santilli Pereri, which is a beautiful church, that was bombed during the Spanish Civil War. | AC17: 4. Creative Shifts | AD17: Modification – Situational | AE17: YES | AH17: Okay, so there were the gargoyles on the churches, you know, like that. There's a church in Barcelona called Santilli Pereri, which is a beautiful church, that was bombed during the Spanish Civil War. | AI17: 4. Creative Shifts | AJ17: Modification – Situational | AK17: YES | AN17: "Well, there were these gargoyles on churches, like, like, like, like. There's a church in Barcelona called Santilli Pereri, which is a beautiful church, that was bombed during the Civil War." | AO17: 1. Reproduction | AP17: Direct Translation | AQ17: YES | AT17: Well, so there were these gargoyles on churches, like, like, like, like. There's a church in Barcelona called Santilli Pereri, which is a beautiful church, and it was bombed during the Civil War. | AU17: 1. Reproduction | AV17: Direct Translation | AW17: YES | AZ17: Well, so there were these gargoyles on churches, like, like, like, like. There's a church in Barcelona called Santilli Pereri, which is a beautiful church, and it was bombed during the Civil War. | BA17: 1. Reproduction | BB17: Direct Translation | BC17: YES | BF17: "Well, there were the gargoyles on the churches, like, like, like, like. A church in Barcelona called Santilli Pereri, which is a beautiful church, was bombed during the Civil War. Some people ask if the gargoyles are actually cannons for shooting." | BG17: 1. Reproduction | BH17: Direct Translation | BI17: YES | BL17: Well, there were the gargoyles on the churches, like, like, like, like. There's a church in Barcelona called Santilli Pereri, which is a beautiful church, that was bombed during the Civil War. | BM17: 1. Reproduction | BN17: Direct Translation | BO17: YES | BR17: Well, there were the gargoyles of the churches, such, such, such, such. One church in Barcelona called Santilli Pereri, which is a beautiful church, was bombed in the Civil War. | BS17: 1. Reproduction | BT17: Direct Translation | BU17: YES | BX17: Well, there were gargoyles on churches, like this... One church in Barcelona called St. Ildefons which is a beautiful church was bombed during the civil war. There are people who ask whether the gargoyles are cannons to shoot | BY17: 4. Creative Shifts | BZ17: Modification – Situational | CA17: YES | CD17: Well, there were the gargoyles of the churches, such, such, such, such. One church in Barcelona called Santilli Pereri, which is a beautiful church, was bombed in the Civil War. | CE17: 1. Reproduction | CF17: Direct Translation | CG17: YES | CJ17: Well, there were the gargoyles of the churches, such, such, such, such. One church in Barcelona called Santilli Pereri, which is a beautiful church, was bombed in the Civil War. | CK17: 1. Reproduction | CL17: Direct Translation | CM17: YES | CP17: Well, there were the gargoyles of the churches, such, such, such, such. One church in Barcelona called Santilli Pereri, which is a beautiful church, was bombed in the Civil War. | CQ17: 1. Reproduction | CR17: Direct Translation | CS17: YES
A18: [empieza tema de conversación] | B18: Hay muchísima gente que se piensa que aquí en España es como que nos educan con que Colón era el salvador y bla, bla, bla. Cuando vienen aquí, yo creo que de buena fe como que nos quieren cambiar totalmente esa visión. | C18: Hay gente que no sabe lo que es Cataluña. Gente de Argentina, México, Colombia. Yo cuando viajo a un sitio, intento mirar un poco dónde voy, ¿no? Hay gente que este paso lo suele omitir y te dice que si Cataluña es la capital de Barcelona. | D18: Hay muchísima gente que se piensa que aquí en España es como que nos educan con que Colón era el salvador y bla, bla, bla. Cuando vienen aquí, yo creo que de buena fe como que nos quieren cambiar totalmente esa visión. | E18: 1. Lexicon and Vocabulary | F18: 1.7 | G18: Onomatopoeia and sound representation | H18: blah blah blah | I18: ReversoContext | J18: A lot of people think that here in Spain, we're taught from a young age that Columbus was the saviour, and all that kind of thing. But when they come here, I believe that, in good faith, they genuinely want to completely change that perspective. | K18: 4. Creative Shifts | L18: Abstraction – Paraphrase | M18: NO | P18: There are a lot of people who think that here in Spain, we're taught from a young age that Columbus was the saviour, and all that sort of thing. But when they come here, I believe that, in good faith, they want to completely change that perspective. | Q18: 4. Creative Shifts | R18: Abstraction – Paraphrase | S18: NO | V18: There are a lot of people who think that here in Spain, we're taught that Columbus was the saviour and all that rubbish. But when they come here, I think they genuinely want to change that perspective completely. | W18: 3. Errors | Y18: NO | AB18: There are a lot of people who think that here in Spain, we're taught from a young age that Columbus was the saviour, and all that sort of thing. When they come here, I believe that, in good faith, they genuinely want to completely change that perspective. | AC18: 4. Creative Shifts | AD18: Abstraction – Paraphrase | AE18: NO | AH18: There are a lot of people who think that here in Spain, we're taught from a young age that Columbus was the saviour, and all that sort of thing. But when they come here, I think, in good faith, they really want to change that perception completely. | AI18: 4. Creative Shifts | AJ18: Abstraction – Paraphrase | AK18: NO | AN18: There's a lot of people who think here in Spain that we're educated to believe Columbus was a savior and bla, bla, bla. When they come here, I think they genuinely want to change that whole view entirely. | AO18: 1. Reproduction | AP18: Retention | AQ18: YES | AT18: There's a lot of people who think here in Spain we're taught that Columbus was a savior and bla, bla, bla. When they come here, I think they do it in good faith, like they want to completely change that view. | AU18: 1. Reproduction | AV18: Retention | AW18: YES | AZ18: There's a lot of people who think here in Spain we're taught that Columbus was the savior and bla, bla, bla. When they come here, I think they genuinely want to completely change that perspective. | BA18: 1. Reproduction | BB18: Retention | BC18: YES | BF18: There's a lot of people who think here in Spain it's as if we're educated to believe that Columbus was the savior and bla, bla, bla. When they come here, I think with good intentions, as if they want to completely change that view. | BG18: 1. Reproduction | BH18: Retention | BI18: YES | BL18: There are a lot of people who think here in Spain that we're taught that Columbus was a savior, and bla, bla, bla. When they come here, I think they do it in good faith, as if they want to completely change that view. | BM18: 1. Reproduction | BN18: Retention | BO18: YES | BR18: There's a lot of people who think that here in Spain we're brought up with the idea that Columbus was the savior and blah, blah, blah. When they come here, I think with good faith they want to totally change that vision. | BS18: 1. Reproduction | BT18: Direct Translation | BU18: YES | BX18: There’s so many people who think that Spain is like we grow up thinking Columbus was our savior and blah-blah-blah. When they come over here, I think good faith wants to totally change that vision | BY18: 1. Reproduction | BZ18: Direct Translation | CA18: YES | CD18: There are a lot of people who think that here in Spain we are educated with the idea that Columbus was the savior and bla, bla, bla. When they come here, I think that with good faith they want to totally change that vision. | CE18: 1. Reproduction | CF18: Retention | CG18: YES | CJ18: There's a lot of people who think that here in Spain it's like we're brought up with the idea that Columbus was the savior and blah, blah, blah. When they come here, I think with good faith they want to totally change that vision. | CK18: 1. Reproduction | CL18: Direct Translation | CM18: YES | CP18: There is a lot of people who think that here in Spain we are like that we are educated with that Columbus was the savior and bla, bla, bla. When they come here, I think that with good faith they want to totally change that vision. | CQ18: 1. Reproduction | CR18: Retention | CS18: YES
A19: [empieza tema de conversación] | B19: ¿Pero Antonio Gaudí sigue vivo? Una polla que te han preguntado si sigue vivo. | C19: Y te han dicho algo del tranvía, pero ¿cómo le pude pillar? | D19: ¿Pero Antonio Gaudí sigue vivo? Una polla que te han preguntado si sigue vivo. | E19: 3. Pragmatics and Discourse | F19: 3.3 | G19: Irony and sarcasm | J19: But is Antonio Gaudí still alive? Seriously, someone actually asked me if he was still alive. | K19: 1. Reproduction | L19: Direct Translation | M19: YES | P19: Seriously, is Antoni Gaudí still alive? They actually asked me if he was still alive. | Q19: 4. Creative Shifts | R19: Concretisation – Addition | S19: YES | V19: "But is Antonio Gaudí still alive? Seriously, they asked me if he was still alive. | W19: 1. Reproduction | X19: Direct Translation | Y19: YES | AB19: But is Antonio Gaudí still alive? They actually asked me if he's still alive. | AC19: 1. Reproduction | AD19: Direct Translation | AE19: YES | AH19: "But is Antonio Gaudí still alive? Seriously, someone actually asked me if he's still alive." | AI19: 1. Reproduction | AJ19: Direct Translation | AK19: YES | AN19: But is Antonio Gaudí still alive? A question that's been asked to you if he's still alive. | AO19: 1. Reproduction | AP19: Direct Translation | AQ19: YES | AT19: But does Antonio Gaudí still live? A question that's asked to you like, "Is he still alive?" | AU19: 1. Reproduction | AV19: Direct Translation | AW19: YES | AZ19: But is Antonio Gaudí still alive? A question you get asked if he's still around. | BA19: 1. Reproduction | BB19: Direct Translation | BC19: YES | BF19: But does Antonio Gaudí still live? A question that's been asked to you if he's still alive. | BG19: 4. Creative Shifts | BH19: Abstraction – Superordinate Term | BI19: NO | BL19: But does Antonio Gaudí still live? A big deal they asked you if he's still alive. | BM19: 4. Creative Shifts | BN19: Abstraction – Superordinate Term | BO19: NO | BR19: But is Antonio Gaudí still alive? Dude, they've asked you if he's still alive. | BS19: 1. Reproduction | BT19: Direct Translation | BU19: YES | BX19: But does Antoni Gaudi still live? Someone fucking asked you if he’s alive. And they said something about the tramway, but how could I catch him | BY19: 4. Creative Shifts | BZ19: Abstraction – Superordinate Term | CA19: NO | CD19: But is Antonio Gaudí still alive? A cock that they asked you if he is still alive. | CE19: 1. Reproduction | CF19: Direct Translation | CG19: YES | CJ19: But is Antonio Gaudí still alive? A dick that they've asked you if he's still alive. | CK19: 1. Reproduction | CL19: Direct Translation | CM19: YES | CP19: But is Antonio Gaudí still alive? A cock that they have asked you if he is still alive. | CQ19: 1. Reproduction | CR19: Direct Translation | CS19: YES
A20: [empieza tema de conversación] | B20: Una de las cosas que me gusta es el cuñado histórico. Yo lo identifico siempre con las catedrales. Un imán para los cuñados históricos que se pongan delante de una fachada y digan esto es románico, esto es gótico, esto tiene de todo. | C20: Gente que le dice a su amigo, a su pareja, lo ves. | D20: Una de las cosas que me gusta es el cuñado histórico. Yo lo identifico siempre con las catedrales. Un imán para los cuñados históricos que se pongan delante de una fachada y digan esto es románico, esto es gótico, esto tiene de todo. | E20: 3. Pragmatics and Discourse | F20: 3.3 | G20: Irony and sarcasm | H20: busybody / know-it-all / know-all / windbag | I20: WordReference / Collins | J20: One of the things I like is the "historical know-it-all." I always associate them with cathedrals. They're like a magnet for these people who stand in front of a facade and say things like, "This is Romanesque, this is Gothic, this has everything." | K20: 4. Creative Shifts | L20: Abstraction – Superordinate Term | M20: NO | P20: One of the things I like is the "historical know-it-all." I always associate them with cathedrals. They're like a magnet for historical know-it-alls who stand in front of a facade and say, "This is Romanesque, this is Gothic, this has everything." | Q20: 4. Creative Shifts | R20: Modification – Cultural | S20: YES | V20: One of the things I like is the "know-it-all" type of relative. I always associate them with historical sites. They're like magnets for those relatives who stand in front of a building and say, "This is Romanesque, this is Gothic, this has everything." | W20: 4. Creative Shifts | X20: Abstraction – Superordinate Term | Y20: NO | AB20: "One of the things I like is the "historical relative" phenomenon. I always associate it with cathedrals. It's like a magnet for those "historical relatives" who stand in front of a facade and say, "This is Romanesque, this is Gothic, this has everything." | AC20: 4. Creative Shifts | AD20: Abstraction – Superordinate Term | AE20: NO | AH20: "One of the things I like is the 'historical relative' stereotype. I always associate it with cathedrals. It's like a magnet for those historical relatives who stand in front of a facade and say, 'This is Romanesque, this is Gothic, this has everything!' | AI20: 4. Creative Shifts | AJ20: Abstraction – Superordinate Term | AK20: NO | AN20: One of the things I like is historical architecture. I always associate it with cathedrals. It's like a magnet for history buffs who stand in front of a facade and say, "This is Romanesque, this is Gothic, this has it all." | AO20: 3. Errors | AQ20: NO | AT20: One of the things I like is historical aunts and uncles. I always associate them with cathedrals. They're like magnets for historical aunts and uncles who stand in front of a facade and say, "This is Romanesque, this is Gothic, this has it all." | AU20: 3. Errors | AW20: NO | AZ20: One of the things I like is historical architecture. I always associate it with cathedrals. It's like a magnet for historical architects who stand in front of a facade and say, "This is Romanesque, this is Gothic, this has everything." | BA20: 3. Errors | BC20: NO | BF20: One of the things I like is historical architecture. I always associate it with cathedrals. It's like a magnet for history buffs who stand in front of a façade and say, "This is Romanesque, this is Gothic, this has everything." | BG20: 3. Errors | BI20: NO | BL20: One of the things I like is historical architecture. I always associate it with cathedrals. It’s like a magnet for those history buffs who stand in front of a façade and say, “This is Romanesque, this is Gothic, this has it all.” | BM20: 3. Errors | BO20: NO | BR20: One of the things I like is the historical uncle. I always identify it with cathedrals. An attraction for historical uncles who stand in front of a facade and say this is Romanesque, this is Gothic, this has everything. | BS20: 3. Errors | BU20: NO | BX20: One of the things that I like is historical cousin. I always identify him with cathedrals. An attraction for historic cousins who stand in front of a facade and say this is Romanesque, this is Gothic, this has everything. | BY20: 3. Errors | CA20: NO | CD20: One of the things I like is the historical uncle. I always identify him with the cathedrals. A magnet for historical uncles who stand in front of a facade and say this is Romanesque, this is Gothic, this has everything. | CE20: 3. Errors | CG20: NO | CJ20: One of the things I like is the historical uncle. I always identify it with cathedrals. An attraction for historical uncles who stand in front of a facade and say this is Romanesque, this is Gothic, this has everything. | CK20: 3. Errors | CM20: NO | CP20: One of the things I like is the historical uncle. I always identify it with cathedrals. A magnet for historical uncles who stand in front of a facade and say this is Romanesque, this is Gothic, this has everything. | CQ20: 3. Errors | CS20: NO
A21: [empieza tema de conversación] | B21: ¿A ti te habrán vacilado los más grandes? Te vacilan sabiendo que te están vacilando. | C21: Tú, 10 minutos menos de recreo, ¿qué te dicen con toda la cara? Ey, que me han castigado también. | D21: ¿A ti te habrán vacilado los más grandes? Te vacilan sabiendo que te están vacilando. | E21: 1. Lexicon and Vocabulary | F21: 1.2 | G21: Colloquial lexicon and slang | H21: to tease somebody / take the mickey out of somebody / rib | I21: Collins / WordReference | J21: Did the older kids ever tease you? They tease you knowing they're teasing you. | K21: 4. Creative Shifts | L21: Abstraction – Superordinate Term | M21: NO | P21: Have the older kids ever teased you? They tease you knowing they're teasing you. | Q21: 4. Creative Shifts | R21: Abstraction – Superordinate Term | S21: NO | V21: "Were the older kids ever mean to you? They tease you knowing they're teasing you. | W21: 4. Creative Shifts | X21: Abstraction – Superordinate Term | Y21: NO | AB21: "Were the older kids ever cheeky with you? They're cheeky knowing they're being cheeky. | AC21: 4. Creative Shifts | AD21: Modification – Situational | AE21: NO | AH21: Were the older kids ever cheeky with you? They're cheeky knowing they're being cheeky. | AI21: 4. Creative Shifts | AJ21: Modification – Situational | AK21: NO | AN21: Have the biggest ones ever messed with you? They mess with you knowing they're messing with you. | AO21: 4. Creative Shifts | AP21: Modification – Situational | AQ21: NO | AT21: Dude, have the big names ever messed with you? They mess with you knowing they're messing with you. | AU21: 4. Creative Shifts | AV21: Modification – Situational | AW21: NO | AZ21: Have the big ones ever messed with you? They mess with you knowing they're messing with you. | BA21: 4. Creative Shifts | BB21: Modification – Situational | BC21: NO | BF21: Have the big guys ever messed with you? They mess with you knowing they're messing with you. | BG21: 4. Creative Shifts | BH21: Modification – Situational | BI21: NO | BL21: Have the bigger kids ever messed with you? They mess with you knowing they're messing with you. | BM21: 4. Creative Shifts | BN21: Modification – Situational | BO21: NO | BR21: Have you ever been taken advantage of by the big ones? They take advantage of you knowing that they are taking advantage of you. | BS21: 4. Creative Shifts | BT21: Modification – Situational | BU21: NO | BX21: Have they ever played tricks on you? They play knowing they’re playing tricks." | BY21: 4. Creative Shifts | BZ21: Modification – Situational | CA21: NO | CD21: Have the big kids been messing with you? They mess with you knowing they're messing with you. | CE21: 4. Creative Shifts | CF21: Abstraction – Superordinate Term | CG21: NO | CJ21: Have you ever been taken advantage of by the big ones? They take advantage of you knowing that they are taking advantage of you. | CK21: 4. Creative Shifts | CL21: Modification – Situational | CM21: NO | CP21: Have you ever been taken advantage of by the big ones? They take advantage of you knowing that they are taking advantage of you. | CQ21: 4. Creative Shifts | CR21: Modification – Situational | CS21: NO
A22: [empieza tema de conversación] | B22: Uno de ellos, por, ejemplo, le llamaban el Patillas, que no sé por qué le llamaban el Patillas, porque no tenía patillas. Era un hombre mayor con mucha mala leche. Venía con su bastón y siempre pasaba por las cajas de autopago. | C22: Le tenían prohibido pasar por las cajas normales porque siempre insultaba y agredía a las compañeras con el bastón. | D22: Uno de ellos, por, ejemplo, le llamaban el Patillas, que no sé por qué le llamaban el Patillas, porque no tenía patillas. Era un hombre mayor con mucha mala leche. Venía con su bastón y siempre pasaba por las cajas de autopago. | E22: 1. Lexicon and Vocabulary | F22: 1.2 | G22: Colloquial lexicon and slang | H22: tetchy / moodiness / ill humor / bad egg | I22: Wordreference | J22: One of them, for example, they called him "Patillas" (which means "sideburns"), although I don't know why they called him that, because he didn't have sideburns. He was an older man, and he had a really bad temper. He would come along with his walking stick, and he always went through the self-checkout lanes. | K22: 4. Creative Shifts | L22: Abstraction – Paraphrase | M22: NO | P22: One of them, for example, they called him "The Moustache," although I don't know why they called him that, because he didn't actually have a moustache. He was an older man with a really bad attitude. He'd come along with his walking stick and always went through the self-checkout lanes. | Q22: 4. Creative Shifts | R22: Abstraction – Paraphrase | S22: NO | V22: One of them, for example, was called "The Moustache," although I don't know why they called him that, because he didn't actually have a moustache. He was an older man with a really bad attitude. He'd come along with his walking stick and always went through the self-checkout lanes. | W22: 4. Creative Shifts | X22: Abstraction – Paraphrase | Y22: NO | AB22: "One of them, for example, they called him 'Patillas' (which roughly translates to 'Mustache'), although I don't know why they called him that, because he didn't actually have a mustache. He was an older man with a really bad temper. He would come along with his walking stick and always went through the self-checkout lanes. | AC22: 4. Creative Shifts | AD22: Abstraction – Paraphrase | AE22: NO | AH22: One of them, for example, they called him "Patillas" (which roughly translates to "Sideburns"), and I don't know why they called him that, because he didn't actually have sideburns. He was an older man, and a really unpleasant character. He would come in with his walking stick and always used the self-checkout lanes. | AI22: 4. Creative Shifts | AJ22: Abstraction – Paraphrase | AK22: NO | AN22: One of them, for example, was called "Patillas," but I don't know why they called him that since he didn't have any mustache. He was an older man with a lot of attitude. He came with his cane and always went through the self-checkout lanes. | AO22: 3. Errors | AQ22: NO | AT22: One of them, for example, was called "Patillas," and I don't know why they called him that, because he didn't have any mustache. He was an older guy with a lot of temper. He came with his cane and always went through the self-checkout lanes. | AU22: 4. Creative Shifts | AV22: Abstraction – Paraphrase | AW22: NO | AZ22: One of them, for example, was called "Patillas," but I don't know why they called him that since he didn't have any mustache. He was an older guy with a lot of temper. He came with his cane and always went through the self-checkout counters. | BA22: 4. Creative Shifts | BB22: Abstraction – Paraphrase | BC22: NO | BF22: One of them, for example, was called "Patillas," but I don't know why they called him that since he didn't have any mustache. He was an older man with a lot of temper. He came with his cane and always went through the self-checkout lanes. | BG22: 4. Creative Shifts | BH22: Abstraction – Paraphrase | BI22: NO | BL22: One of them, for example, was called "El Patillas"—I don’t know why they called him that, because he didn’t even have a mustache. He was an older guy with a lot of bad temper. He came with his cane and always went through the self-checkout counters. | BM22: 4. Creative Shifts | BN22: Abstraction – Paraphrase | BO22: NO | BR22: One of them, for example, they called him the Patillas, I don't know why they called him the Patillas, because he didn't have any patillas. He was an older man with a lot of bad attitude. He would come with his cane and always pass by the self-service payment boxes. | BS22: 4. Creative Shifts | BT22: Abstraction – Paraphrase | BU22: NO | BX22: "One of them, for example, they called him El Patillas, which I don’t know why they called him El Patillas, because he didn’t have sideburns. He was an older man with lots of bad attitude. He would come with his cane and always go through the self-checkout lanes. | BY22: 4. Creative Shifts | BZ22: Abstraction – Paraphrase | CA22: NO | CD22: One of them, for example, they called him the Patillas, I don't know why they called him the Patillas, because he didn't have any sideburns. He was an older man with a lot of bad attitude. He would come with his cane and always pass through the self-service payment boxes. | CE22: 4. Creative Shifts | CF22: Abstraction – Paraphrase | CG22: NO | CJ22: One of them, for example, they called him the Patillas, who I don't know why they called him the Patillas, because he didn't have any patillas. He was an older man with a lot of bad attitude. He would come with his cane and always pass by the self-service payment boxes. | CK22: 4. Creative Shifts | CL22: Abstraction – Paraphrase | CM22: NO | CP22: One of them, for example, they called him the Patillas, who I don't know why they called him the Patillas, because he didn't have any patillas. He was an older man with a lot of bad attitude. He would come with his cane and always pass through the self-service payment boxes. | CQ22: 4. Creative Shifts | CR22: Abstraction – Paraphrase | CS22: NO
A23: [empieza tema de conversación] | B23: Lo mismo. te encontrabas a la señora que decías que llevo 50 años comprando aquí, pero luego, cada vez que venía, te preguntaba dónde estaban los huevos unas fantasmadas, tío | C23: [cambio de tema] | D23: Lo mismo. te encontrabas a la señora que decías que llevo 50 años comprando aquí, pero luego, cada vez que venía, te preguntaba dónde estaban los huevos unas fantasmadas, tío | E23: 1. Lexicon and Vocabulary | F23: 1.2 | G23: Colloquial lexicon and slang | H23: boasting / showing off / bravado / swagger / bluster | I23: WordReference / Collins | J23: The same thing happened. I met the lady you mentioned, the one you said you've been buying from here for 50 years, but then, every time I came, she'd ask me where the eggs were – it was completely absurd, mate. | K23: 4. Creative Shifts | L23: Abstraction – Paraphrase | M23: NO | P23: It's the same. You'd meet the lady I told you about, the one I said I've been buying things from here for 50 years, but then, every time I came, she'd ask me where the eggs were – it was ridiculous, mate. | Q23: 4. Creative Shifts | R23: Abstraction – Paraphrase | S23: NO | V23: Same here. I met the lady you mentioned, the one you said you've been buying things from here for 50 years, but then, every time I came, she'd ask me where the eggs were – it was all a bit weird, mate. | W23: 4. Creative Shifts | X23: Abstraction – Paraphrase | Y23: NO | AB23: The same thing happened. I met the lady you mentioned, the one you said you'd been buying from here for 50 years, but then, every time I came, she'd ask me where the eggs were – it was ridiculous, mate. | AC23: 4. Creative Shifts | AD23: Abstraction – Paraphrase | AE23: NO | AH23: The same thing. I remember the lady you mentioned, the one you said you've been buying from for 50 years, but then, every time I went, she'd ask me where the eggs were... it was all a bit bizarre, mate. | AI23: 4. Creative Shifts | AJ23: Abstraction – Paraphrase | AK23: NO | AN23: Same thing. You'd run into the lady who said she's been buying here for 50 years, but then every time she came, she'd ask where the eggs were... some crazy stuff, man. | AO23: 4. Creative Shifts | AP23: Abstraction – Paraphrase | AQ23: YES | AT23: Same thing. You'd run into the lady who said she's been buying here for 50 years, but then every time she came, she'd ask where the eggs were… some crazy stuff, man. | AU23: 4. Creative Shifts | AV23: Abstraction – Paraphrase | AW23: YES | AZ23: Same thing. You'd run into the lady who said she's been buying here for 50 years, but then every time she came, she'd ask where the eggs were... total nonsense, man. | BA23: 4. Creative Shifts | BB23: Abstraction – Paraphrase | BC23: YES | BF23: Same thing. You'd run into the lady who said she's been buying here for 50 years, but then every time she came, she'd ask where the eggs were... some crazy stuff, man. | BG23: 4. Creative Shifts | BH23: Abstraction – Paraphrase | BI23: YES | BL23: Same thing. You'd run into the lady who said she'd been buying here for 50 years, but then every time she came, she'd ask you where the eggs were… total drama, dude. | BM23: 4. Creative Shifts | BN23: Modification – Situational | BO23: YES | BR23: The same. You meet the lady who says she has been buying there for 50 years, but then, every time she comes, she asks where the eggs are... some fantasies, dude | BS23: 4. Creative Shifts | BT23: Modification – Situational | BU23: YES | BX23: The same thing. You ran into the lady who said she had been buying there for 50 years, but then every time she came, she would ask where the eggs were... some nonsense, man | BY23: 4. Creative Shifts | BZ23: Abstraction – Paraphrase | CA23: YES | CD23: The same. You met the lady who said she had been buying there for 50 years, but then, every time she came, she asked where the eggs were... some fantasies, dude | CE23: 4. Creative Shifts | CF23: Modification – Situational | CG23: YES | CJ23: The same. You met the lady who said she had been buying there for 50 years, but every time she came, she would ask where the eggs were... some fantasies, dude | CK23: 4. Creative Shifts | CL23: Modification – Situational | CM23: YES | CP23: The same. You met the lady who said she had been buying there for 50 years, but then, every time she came, she asked where the eggs were... some fantasies, dude | CQ23: 4. Creative Shifts | CR23: Modification – Situational | CS23: YES
A24: [empieza tema de conversación] | B24: Fue una vez una mujer y llevaba un carro de la compra petado hasta arriba. Lo pasé tal y ya me empezó a decir de malas formas, que necesitaba otro carro. Pues, ves a buscarlo, ¿no? | C24: Oye, estoy pasando la compra, yo no te voy a traer otro carro. Me dijo: ah, que no me lo vas a ir a buscar tú. | D24: Fue una vez una mujer y llevaba un carro de la compra petado hasta arriba. Lo pasé tal y ya me empezó a decir de malas formas, que necesitaba otro carro. Pues, ves a buscarlo, ¿no? | E24: 3. Pragmatics and Discourse | F24: 3.1 | G24: Discourse markers | J24: Once upon a time, there was a woman, and she was pushing a shopping trolley that was completely full. I walked past, and she started talking to me in a really rude way, saying she needed another trolley. So, I said, "Well, why don't you go and get one, then?" | K24: 4. Creative Shifts | L24: Concretisation – Addition | M24: YES | P24: Once upon a time, there was a woman, and she was pushing a shopping trolley that was completely full. I passed by, and she started speaking to me rudely, saying she needed another trolley. Well, go and get it yourself, right? | Q24: 1. Reproduction | R24: Direct Translation | S24: YES | V24: Once upon a time, there was a woman who was pushing a shopping trolley that was completely overflowing. She started giving me a hard time, saying she needed another trolley. So, I told her, "Well, go and get one, then!" | W24: 4. Creative Shifts | X24: Concretisation – Addition | Y24: YES | AB24: Once upon a time, there was a woman, and she had a shopping trolley that was completely full. I walked past, and she started speaking to me very rudely, saying she needed another trolley. So, I said, "Well, go and get one, then," didn't I? | AC24: 1. Reproduction | AD24: Direct Translation | AE24: YES | AH24: Once upon a time, there was a woman, and she had a shopping trolley that was completely full. I was just passing by, and she started speaking to me very rudely, saying she needed another trolley. So, I said, "Well, why don't you go and get one?" | AI24: 2. Omissions | AJ24: Shortcut Solution | AK24: NO | AN24: It was once a woman and she had a shopping cart completely full. I passed by and she started talking to me in a rude way, saying she needed another cart. So, go look for one, right? | AO24: 1. Reproduction | AP24: Direct Translation | AQ24: YES | AT24: It was once a woman and she had a shopping cart completely full. I passed by and she started talking to me in a rude way, saying she needed another cart. So, go look for one, right? | AU24: 1. Reproduction | AV24: Direct Translation | AW24: YES | AZ24: Once there was a woman and she had a shopping cart full to the brim. I passed by and she started talking to me in a bad way, saying she needed another cart. So, go look for one, right? | BA24: 1. Reproduction | BB24: Direct Translation | BC24: YES | BF24: It was once a woman and she had a shopping cart completely full. I passed by and she started talking to me in a rude way, saying she needed another cart. So, go look for one, right? | BG24: 1. Reproduction | BH24: Direct Translation | BI24: YES | BL24: It was once a woman, and she had a shopping cart completely full. I went through it like that, and she started talking to me in a rude way, saying she needed another cart. Well, go and get it, right? | BM24: 1. Reproduction | BN24: Direct Translation | BO24: YES | BR24: Once upon a time, there was a woman and she had a shopping cart full of things. I passed by and she started to say rudely that she needed another cart. Well, go and get it, right? | BS24: 1. Reproduction | BT24: Direct Translation | BU24: YES | BX24: It was once a woman and she had a shopping cart full of things. It went so badly that she started saying rudely that she needed another one. Well, go and look for it, don't you? | BY24: 1. Reproduction | BZ24: Direct Translation | CA24: YES | CD24: Once upon a time, there was a woman and she had a shopping cart full of things. I passed by and she started yelling at me in a bad way, that she needed another cart. Well, go and get it, right? | CE24: 1. Reproduction | CF24: Direct Translation | CG24: YES | CJ24: Once upon a time, there was a woman and she had a shopping cart full of things. I passed by and she started to say rudely that she needed another cart. Well, go and get it, right? | CK24: 1. Reproduction | CL24: Direct Translation | CM24: YES | CP24: Once upon a time, there was a woman and she had a shopping cart full of things. I passed by and she started to say rudely that she needed another cart. Well, go and get it, right? | CQ24: 1. Reproduction | CR24: Direct Translation | CS24: YES
A25: [empieza tema de conversación] | B25: Había mucha gente que me decía que quería venir de vacaciones a España. Y yo le decía a ti en el aeropuerto, cuando te pregunten, di que vas a Portugal. Y no me pillaban el lore. | C25: ¿Y los niños conocen el lore? Los niños saben que nos conquistaron, sí. | D25: Había mucha gente que me decía que quería venir de vacaciones a España. Y yo le decía en el aeropuerto, cuando te pregunten, di que vas a Portugal. Y no me pillaban el lore. | E25: 1. Lexicon and Vocabulary | F25: 1.8 | G25: Neologisms | H25: lore | I25: WordReference | J25: People often told me they wanted to come on holiday to Spain. And I would tell them, "When you're at the airport, if they ask you where you're going, say you're going to Portugal." And they wouldn't suspect a thing. | K25: 4. Creative Shifts | L25: Abstraction – Paraphrase | M25: NO | P25: A lot of people told me they wanted to come on holiday to Spain. And I told you, at the airport, when they ask you, say you're going to Portugal. And they wouldn't catch on to the joke. | Q25: 4. Creative Shifts | R25: Abstraction – Superordinate Term | S25: NO | V25: "Loads of people were telling me they wanted to come on holiday to Spain. And I told you at the airport, when they ask, say you're going to Portugal. And they wouldn't catch on." | W25: 4. Creative Shifts | X25: Abstraction – Paraphrase | Y25: NO | AB25: People often told me they wanted to come on holiday to Spain. And I would tell them, "When you're at the airport, if they ask you, say you're going to Portugal." And they wouldn't suspect a thing. | AC25: 4. Creative Shifts | AD25: Abstraction – Paraphrase | AE25: NO | AH25: "Loads of people used to tell me they wanted to come on holiday to Spain. And I'd tell them, 'When you're at the airport, just say you're going to Portugal.' And they wouldn't get caught out." | AI25: 4. Creative Shifts | AJ25: Abstraction – Paraphrase | AK25: NO | AN25: There were a lot of people who told me they wanted to come on vacation to Spain. And I'd tell you at the airport, when they ask you, say you're going to Portugal. And they never caught on to the joke. | AO25: 4. Creative Shifts | AP25: Abstraction – Superordinate Term | AQ25: NO | AT25: There were a lot of people who told me they wanted to come on vacation to Spain. And I'd tell you at the airport, when they ask you, say you're going to Portugal. And they never caught on to the story. | AU25: 4. Creative Shifts | AV25: Abstraction – Superordinate Term | AW25: NO | AZ25: There were a lot of people who told me they wanted to come on vacation to Spain. And I'd tell you at the airport, when they ask you, say you're going to Portugal. And they never caught on to the story. | BA25: 4. Creative Shifts | BB25: Abstraction – Superordinate Term | BC25: NO | BF25: There were a lot of people who told me they wanted to come on vacation to Spain. And I'd tell you at the airport, when they ask you, say you're going to Portugal. And they never caught on to the trick. | BG25: 4. Creative Shifts | BH25: Abstraction – Superordinate Term | BI25: NO | BL25: There were a lot of people who used to tell me they wanted to come on vacation to Spain. And I’d tell you at the airport, when they ask you, say you’re going to Portugal. And they never caught on to the story. | BM25: 4. Creative Shifts | BN25: Abstraction – Superordinate Term | BO25: NO | BR25: There were a lot of people who told me they wanted to come on vacation to Spain. And I would tell you at the airport, when they ask you, say that you are going to Portugal. And they don't catch on. | BS25: 4. Creative Shifts | BT25: Abstraction – Paraphrase | BU25: NO | BX25: There were many people who told me they wanted to come to Spain on holiday. And I said to them at the airport, when asked, say that you are going to Portugal. They didn't catch my story. | BY25: 4. Creative Shifts | BZ25: Abstraction – Superordinate Term | CA25: NO | CD25: There were a lot of people who told me they wanted to come on vacation to Spain. And I told you at the airport, when they ask you, say you're going to Portugal. And they didn't catch on. | CE25: 4. Creative Shifts | CF25: Abstraction – Paraphrase | CG25: NO | CJ25: There were many people who told me they wanted to come on vacation to Spain. And I would tell you at the airport, when they ask you, say that you are going to Portugal. And they don't catch on. | CK25: 4. Creative Shifts | CL25: Abstraction – Paraphrase | CM25: NO | CP25: There was a lot of people who told me they wanted to come on vacation to Spain. And I would tell you at the airport, when they ask you, say that you are going to Portugal. And they don't catch the lore. | CQ25: 1. Reproduction | CR25: Retention | CS25: NO
A26: [empieza tema de conversación] | B26: Me soltaron un zasca con el tema de novios. Un niño de 13 años que me dejó temblando. | C26: Son chavales, entonces yo intentaba encontrar puntos en común con ellos. Y a mí los videojuegos me gustan mucho. Y digo, pues mira, yo juego un poco de todo. Me gusta mucho Assassin's Creed. He jugado al LOL. Me mira fijamente y me dice, ¿tú has jugado al LOL? ¿Tú no tienes novio, ¿verdad? | D26: Me soltaron un zasca con el tema de novios. Un niño de 13 años que me dejó temblando. | E26: 1. Lexicon and Vocabulary | F26: 1.2 | G26: Colloquial lexicon and slang | H26: dig / swipe | I26: Collins | J26: They completely blindsided me with the boyfriend topic. A 13-year-old boy who left me speechless. | K26: 4. Creative Shifts | L26: Modification – Situational | M26: NO | P26: They completely blindsided me with the boyfriend question. A 13-year-old kid who left me speechless. | Q26: 4. Creative Shifts | R26: Modification – Situational | S26: NO | V26: They completely blindsided me with the whole boyfriend thing. A 13-year-old kid who left me shaking. | W26: 4. Creative Shifts | X26: Modification – Situational | Y26: NO | AB26: They completely blindsided me with the boyfriend question. A 13-year-old boy who left me speechless. | AC26: 4. Creative Shifts | AD26: Modification – Situational | AE26: NO | AH26: They completely blindsided me with the boyfriend topic. A 13-year-old kid who left me completely speechless. | AI26: 4. Creative Shifts | AJ26: Modification – Situational | AK26: NO | AN26: They dropped the boyfriend topic on me. A 13-year-old kid who left me all shook up. | AO26: 4. Creative Shifts | AP26: Abstraction – Paraphrase | AQ26: NO | AT26: They gave me a real talking-to about the boyfriend thing. A 13-year-old kid who left me shaking. | AU26: 4. Creative Shifts | AV26: Modification – Situational | AW26: NO | AZ26: They gave me a real talking-to about being in a relationship. A 13-year-old kid left me shaking. | BA26: 4. Creative Shifts | BB26: Modification – Situational | BC26: NO | BF26: They hit me with the "boyfriend" topic. A 13-year-old kid who left me shaking. | BG26: 4. Creative Shifts | BH26: Modification – Situational | BI26: NO | BL26: They gave me a hard time about the whole boyfriend thing. A 13-year-old kid who left me shaking. | BM26: 3. Errors | BO26: NO | BR26: Someone threw a zinger at me about boyfriends. A 13-year-old boy who left me shaking. | BS26: 4. Creative Shifts | BT26: Modification – Situational | BU26: NO | BX26: They gave me a zass with the boyfriend thing. A 13-year-old boy who left me shaking. | BY26: 3. Errors | CA26: NO | CD26: They gave me a zass with the boyfriend thing. A 13-year-old boy who left me shaking. | CE26: 3. Errors | CG26: NO | CJ26: Someone threw a zinger at me about boyfriends. A 13-year-old boy who left me shaking. | CK26: 3. Errors | CM26: NO | CP26: Someone threw a "zasca" at me about the topic of boyfriends. A 13-year-old boy who left me trembling. | CQ26: 1. Reproduction | CR26: Retention | CS26: NO
A27: [empieza tema de conversación] | B27: Una de las cosas también muy bonitas de esa edad son los amoríos. ¡Uf, qué puterío! Habían unos baños mixtos en el instituto. Yo en esos baños no entré nunca. | C27: Habían unos que eran en la planta baja. Me da miedo lo que me pueda encontrar en este baño. | D27: Una de las cosas también muy bonitas de esa edad son los amoríos. ¡Uf, qué puterío! Habían unos baños mixtos en el instituto. Yo en esos baños no entré nunca. | E27: 1. Lexicon and Vocabulary | F27: 1.7 | G27: Onomatopoeia and sound representation | H27: Phew / Ugh | I27: WordReference / Collins | J27: One of the lovely things about that age is the romances. Oh, what a mess! There were mixed-sex bathrooms at the school. I never went into those bathrooms. | K27: 4. Creative Shifts | L27: Modification – Situational | M27: YES | P27: One of the lovely things about that age is the romances. Ugh, what a mess! There were mixed-gender bathrooms at the school. I never went into those bathrooms. | Q27: 4. Creative Shifts | R27: Modification – Situational | S27: YES | V27: One of the really nice things about that age is the romances. Oh wow, what a mess! There were some mixed-gender bathrooms at the school. I never went into those bathrooms. | W27: 4. Creative Shifts | X27: Modification – Situational | Y27: YES | AB27: One of the lovely things about that age is the romances. Oh, what a mess! There were mixed-gender bathrooms at the school. I never went into those bathrooms. | AC27: 4. Creative Shifts | AD27: Modification – Situational | AE27: YES | AH27: One of the nice things about that age is the romances. Oh, what a state! There were mixed-sex bathrooms at the school. I never went into those bathrooms. | AI27: 4. Creative Shifts | AJ27: Modification – Situational | AK27: YES | AN27: One of the really nice things about that age is the crushes. Ugh, what a mess! There were some mixed-gender showers at school. I never went into those showers. | AO27: 4. Creative Shifts | AP27: Modification – Situational | AQ27: YES | AT27: One of the really nice things about that age is the flings. Ugh, what a mess! There were some mixed-gender bathrooms at school. I never went into those bathrooms. | AU27: 4. Creative Shifts | AV27: Modification – Situational | AW27: YES | AZ27: One of the really nice things about that age is the crushes. Ugh, what a mess! There were mixed showers at school. I never went into those showers. | BA27: 4. Creative Shifts | BB27: Modification – Situational | BC27: YES | BF27: One of the really nice things about that age is the crushes. Ugh, what a mess! There were some mixed-gender showers at school. I never went into those showers | BG27: 4. Creative Shifts | BH27: Modification – Situational | BI27: YES | BL27: One of the really nice things about that age is the romantic flings. Ugh, what a mess! There were some mixed-gender showers at school. I never went into those showers. There were some on the ground floor. I’m scared of what I might find in this bathroom. | BM27: 4. Creative Shifts | BN27: Modification – Situational | BO27: YES | BR27: One of the very nice things about that age are romances. Ugh, what a mess! There were mixed bathrooms in high school. I never went into those bathrooms. | BS27: 4. Creative Shifts | BT27: Modification – Situational | BU27: YES | BX27: One of the things that are also very nice at this age is love affairs. God, how filthy! There were mixed bathrooms in high school. I never went into those bathrooms. | BY27: 4. Creative Shifts | BZ27: Modification – Cultural | CA27: YES | CD27: One of the very nice things about that age are romances. Ugh, what a mess! There were mixed bathrooms in high school. I never went into those bathrooms. | CE27: 4. Creative Shifts | CF27: Modification – Situational | CG27: YES | CJ27: One of the very nice things about that age are romances. Oh, what a mess! There were mixed bathrooms in high school. I never went into those bathrooms. | CK27: 4. Creative Shifts | CL27: Modification – Situational | CM27: YES | CP27: One of the very nice things about that age are romances. Ugh, what a mess! There were mixed bathrooms in high school. I never went into those bathrooms. | CQ27: 4. Creative Shifts | CR27: Modification – Situational | CS27: YES
A28: [empieza tema de conversación] | B28: Ya no es la caca, ya no son los guiris, ya es el ambiente del centro por la noche. Desde los NPCs que te rapean con el micro en plan, no, yo, la chica pelirroja, no sé qué, Está el de Michael Jackson, que lleva como un guante. Es una persona que se le ve que algo no está bien, llevaba como un guante blanco y hacía lo de caminar para atrás. | C28: [acaba la conversación] | D28: Ya no es la caca, ya no son los guiris, ya es el ambiente del centro por la noche. Desde los NPCs que te rapean con el micro en plan, no, yo, la chica pelirroja, no sé qué, Está el de Michael Jackson, que lleva como un guante. Es una persona que se le ve que algo no está bien, llevaba como un guante blanco y hacía lo de caminar para atrás. | E28: 1. Lexicon and Vocabulary | F28: 1.6 | G28: References to popular culture and memes | H28: NPC | I28: WordReference | J28: It's not just about the bad things anymore, or the tourists. It's about the atmosphere in the city centre at night. There are these people, the "NPCs," who come up to you with a microphone and start talking, like, "No, it's me, the redhead girl, I don't know what." And there's the one dressed as Michael Jackson, wearing a glove. You can tell something's not quite right with him; he was wearing a white glove and just walking backwards. | K28: 1. Reproduction | L28: Retention | M28: YES | P28: "It's not just about the bad food anymore, or the tourists; it's the atmosphere in the city centre at night. There are these people, these 'NPCs' as they call themselves, who are rapping into a microphone, like, "No, it's me, the redhead," or whatever. And there's this guy dressed as Michael Jackson, wearing a glove. You can tell something's not quite right with him; he's wearing a white glove and just walking backwards." | Q28: 1. Reproduction | R28: Retention | S28: YES | V28: "It's not just about the bad food anymore, or the tourists, it's the atmosphere in the city centre at night. There are all these people – the "NPCs" as they call themselves – who are harassing you with their microphones, going on about "no, it's me, the redhead," or whatever. And then there's the Michael Jackson guy, wearing a glove. You can tell something's not quite right with him; he was wearing a white glove and just walking backwards." | W28: 1. Reproduction | X28: Retention | Y28: YES | AB28: "It's not just about the bad stuff anymore, or the tourists; it's about the atmosphere in the city centre at night. There are these characters, these NPCs, who come up to you with a microphone and start rapping, like, "No, it's me, the redhead girl, I don't know what." And there's the one dressed as Michael Jackson, wearing a glove. You can tell something's not quite right with him; he was wearing a white glove and walking backwards." | AC28: 1. Reproduction | AD28: Retention | AE28: YES | AH28: It's not just about the bad stuff anymore, or the tourists. It's about the atmosphere in the city centre at night. There are these characters, these "NPCs" as they call themselves, who accost you with microphones, saying things like, "No, it's me, the red-haired girl, I don't know what..." Then there's the one dressed as Michael Jackson, wearing a glove. You can tell something's not quite right with him. He was wearing a white glove and walking backwards. | AI28: 1. Reproduction | AJ28: Retention | AK28: YES | AN28: It's not the poop anymore, it's not the tourists either—it's the atmosphere in the city center at night. From the NPCs who rap at you with the mic, like, no, me, the red-haired girl, I don't know what, there's the one who looks like Michael Jackson, he wore it like a glove. He's someone who clearly isn't well, wearing a white glove and doing that backwards walking thing. | AO28: 1. Reproduction | AP28: Retention | AQ28: NO | AT28: So it's not the poop anymore, it's not the tourists, it's the atmosphere in the center at night. From the NPCs who try to hit on you with the mic, like, no, me, the red-haired girl, I don't know, there's this one like Michael Jackson, who wears it like a glove. He's someone who looks like something's not quite right, he wore a white glove and did that backwards walking thing. | AU28: 1. Reproduction | AV28: Retention | AW28: NO | AZ28: It's not about the crap anymore, it's not about the tourists anymore—it's the vibe in the city center at night. From the NPCs who try to hit on you with their microphones, no, me, the red-haired girl, I don't know, there's this one like Michael Jackson, who's got it down to a T. He's the kind of person who looks like something's off, wearing this white glove and doing that backwards walking thing. | BA28: 1. Reproduction | BB28: Retention | BC28: NO | BF28: It's not the poop anymore, it's not the tourists either—it's the atmosphere in the city center at night. From the NPCs who rap at you with the mic, no, me, the red-haired girl, I don't know what, there's the one like Michael Jackson, who wears it like a glove. He's someone who looks like something's not right, he wore a white glove and did the backwards walking thing. | BG28: 1. Reproduction | BH28: Retention | BI28: NO | BL28: It's not about the crap anymore, it's not about the tourists anymore—it's about the vibe in the city center at night. From the NPCs who rap with the mic in a flashy way, no, me, the red-haired girl, I don't know what, there's Michael Jackson guy, who looks like he's got it down to a T. He's the kind of person who looks like something's off, wearing that white glove and doing the walk backwards. | BM28: 1. Reproduction | BN28: Retention | BO28: NO | BR28: It's no longer the crap, it's no longer the foreigners, it's the atmosphere in the center at night. From the NPCs who rap you with the microphone in a, no, I, the red-haired girl, don't know what, there's the one of Michael Jackson, who has like a white glove. It's a person who you can see that something is not right, he was walking backwards with a white glove on. | BS28: 1. Reproduction | BT28: Retention | BU28: NO | BX28: It's not anymore the shit, it's not anymore the foreigners, now its the atmosphere downtown during night time. From the NPCs who rap you with the mic like \"I am this girl\", there is also one who looks like Michael Jackson wearing something white and walking backwards. It seems he doesn't feel well, he walks very strange | BY28: 1. Reproduction | BZ28: Retention | CA28: NO | CD28: It's not the crap, it's not the foreigners, it's the atmosphere in the center at night. From the NPCs who rap with the microphone in a, no, I, the red-haired girl, doesn't know what, There's the one of Michael Jackson, who wears like a white glove. It's a person who is seen that something is not right, he wore like a backward walk. | CE28: 1. Reproduction | CF28: Retention | CG28: NO | CJ28: It's no longer the crap, it's no longer the foreigners, it's the atmosphere in the center at night. From the NPCs who rap you with the microphone in a, no, I, the red-haired girl, don't know what, There's the one of Michael Jackson, who has like a glove. It's a person who is seen that something is not right, he was wearing like a white glove and did the walk backwards. | CK28: 1. Reproduction | CL28: Retention | CM28: NO | CP28: It's no longer the crap, it's no longer the foreigners, it's the atmosphere in the center at night. From the NPCs who rap you with the microphone in a, no, I, the red-haired girl, don't know what, there's the one of Michael Jackson, who has like a glove. It's a person who is seen that something is not right, he was wearing like a white glove and he did the walk backwards. | CQ28: 1. Reproduction | CR28: Retention | CS28: NO
A29: [empieza tema de conversación] | B29: Aquí donde me viese una cámara súper simpática. Lo que pasa es que si me tocas los cojones, hermano, había gente que me decía, no, pero ponme la copa más larga. | C29: Le digo, ¿vas a dejar propina? Y yo, sí. Y le digo, pues si tienes para dejar propina, tienes dinero para pagarte otra. | D29: Aquí donde me viese una cámara súper simpática. Lo que pasa es que si me tocas los cojones, hermano, había gente que me decía, no, pero ponme la copa más larga. | E29: 3. Pragmatics and Discourse | F29: 3.2 | G29: Familiar address or vocatives | H29: brother / mate / buddy / pal / dude / bro | I29: WordReference | J29: Here, I saw this really friendly-looking camera. But, you know, if you're messing with me, mate, there were people who would say, "No, but give me the longest glass." | K29: 4. Creative Shifts | L29: Modification – Cultural | M29: YES | P29: Here, I saw this really friendly-looking camera. The thing is, if anyone messed with me, you know, my friends would say, "No, but give me the biggest glass." | Q29: 4. Creative Shifts | R29: Modification – Situational | S29: NO | V29: Here, I spotted a really friendly-looking camera. The thing is, if someone's being a pain, mate, there were people who would say, "No, but give me the biggest glass." | W29: 4. Creative Shifts | X29: Modification – Cultural | Y29: YES | AB29: Here, I saw this really friendly-looking camera. The thing is, if someone was being a pain, you know, if they were being a real nuisance, there were people who would say, "No, but give me the biggest glass." | AC29: 4. Creative Shifts | AD29: Modification – Situational | AE29: NO | AH29: Here, I saw a really friendly-looking camera. The thing is, if someone was being a pain, you know, a real nuisance, there were people who would say, "No, but give me the tallest glass." | AI29: 4. Creative Shifts | AJ29: Modification – Situational | AK29: NO | AN29: Here's where I'd see a super friendly camera. What happens is, if you touch my nuts, brother, there were people who would say, no, but put the longest cup on. | AO29: 1. Reproduction | AP29: Direct Translation | AQ29: YES | AT29: Here's where I saw a super friendly camera. The thing is, if you touch my nuts, brother, there were people who would say, no, but give me the longest cup. | AU29: 1. Reproduction | AV29: Direct Translation | AW29: YES | AZ29: Here's where I'd see a super friendly camera. What happens is, if you touch my nuts, brother, there were people who would say, no, but put me on the longest cup. | BA29: 1. Reproduction | BB29: Direct Translation | BC29: YES | BF29: Here's where I'd see a super friendly camera. The thing is, if you touch my nuts, brother, there were people who would say, no, but put me on the longest cup. | BG29: 1. Reproduction | BH29: Direct Translation | BI29: YES | BL29: Here's where I saw a super friendly camera. What happens is, if you mess with me, brother, there were people who would say, no, but give me the longest glass. | BM29: 1. Reproduction | BN29: Direct Translation | BO29: YES | BR29: Here where I see a super nice camera. What happens is that if you touch my balls, brother, there was people who told me, no, but put me the longer cup. | BS29: 1. Reproduction | BT29: Direct Translation | BU29: YES | BX29: Here where I saw a super nice camera. What happens is that if you touch my balls, brother, there were people who told me, no, but give me the longest drink. | BY29: 1. Reproduction | BZ29: Direct Translation | CA29: YES | CD29: Here where I see a very nice camera. What happens is that if you touch my balls, brother, there were people who told me, no, but put me the longest cup. | CE29: 1. Reproduction | CF29: Direct Translation | CG29: YES | CJ29: Here where I see a super nice camera. What happens is that if you touch my balls, brother, there was people who told me, no, but put me the longer cup. | CK29: 1. Reproduction | CL29: Direct Translation | CM29: YES | CP29: Here where I see a super nice camera. What happens is that if you touch my balls, brother, there was people who told me, no, but put me the longer cup. | CQ29: 1. Reproduction | CR29: Direct Translation | CS29: YES
A30: [empieza tema de conversación] | B30: Hay una movida que yo le llamo el volcán, que es cuando un váter se atasca, atasca un váter con diarrea, ojo, es jodidísimo. Tienes que estar muy fucked por dentro. | C30: Y pasa mucho en los váteres que si tú tiras una vez de la cadena, hace como el y luego vuelve a subir un poco, ¿vale? Entonces se queda un poco elevado el nivel del agua. | D30: Hay una movida que yo le llamo el volcán, que es cuando un váter se atasca, atasca un váter con diarrea, ojo, es jodidísimo. Tienes que estar muy fucked por dentro. | E30: 1. Lexicon and Vocabulary | F30: 1.8 | G30: Neologisms | H30: fucked | I30: WordReference | J30: There's this thing that I call "the volcano," which happens when a toilet gets blocked, especially if someone's had diarrhoea – it's a nightmare. You really have to be in a bad state to experience that. | K30: 4. Creative Shifts | L30: Abstraction – Paraphrase | M30: NO | P30: There's this thing I call "the volcano," which is when a toilet gets blocked, specifically when it's blocked with diarrhoea – and believe me, that's really unpleasant. You have to be in a really bad state to experience that. | Q30: 4. Creative Shifts | R30: Abstraction – Paraphrase | S30: NO | V30: There's this thing that I call "the volcano," which is when a toilet gets blocked – a toilet blocked while someone's having diarrhoea, mind you, which is a complete nightmare. You have to be in a really awful state. | W30: 4. Creative Shifts | X30: Abstraction – Paraphrase | Y30: NO | AB30: There's something that I call "the volcano," which is when a toilet gets blocked – specifically, when a toilet gets blocked while someone's having diarrhoea. It's a complete nightmare. You have to be in a really awful state. | AC30: 4. Creative Shifts | AD30: Abstraction – Paraphrase | AE30: NO | AH30: There's this thing that I call "the volcano," which is when a toilet gets blocked – specifically, when it gets blocked while someone's having diarrhoea. Seriously, it's a nightmare. You have to be in a really bad state. | AI30: 4. Creative Shifts | AJ30: Abstraction – Paraphrase | AK30: NO | AN30: There's this thing I call the volcano, which is when a toilet gets clogged, especially with diarrhea—oh man, it's a nightmare. You've got to be really messed up inside. | AO30: 4. Creative Shifts | AP30: Abstraction – Paraphrase | AQ30: YES | AT30: There's this thing I call the volcano, which is when a toilet gets clogged, especially with diarrhea, okay, it's totally hellish. You've got to be really fucked up inside. . | AU30: 1. Reproduction | AV30: Retention | AW30: NO | AZ30: There's this thing I call the volcano, which is when a toilet gets clogged, clogs a toilet with diarrhea, okay, it's a total nightmare. You've got to be really fucked up inside. | BA30: 1. Reproduction | BB30: Retention | BC30: NO | BF30: There's this thing I call the "volcano," which is when a toilet gets clogged—specifically, when it's clogged with diarrhea, okay? It's a total nightmare. You've got to be really fucked up inside. | BG30: 1. Reproduction | BH30: Retention | BI30: NO | BL30: There's this thing I call the volcano, which is when a toilet gets clogged, like with diarrhea, hey, it's a total pain. You have to be really fucked up inside. | BM30: 1. Reproduction | BN30: Retention | BO30: NO | BR30: There is a thing that I call the volcano, which is when a toilet gets clogged, clogs a toilet with diarrhea, watch out, it's really hard. You have to be really fucked up inside. | BS30: 1. Reproduction | BT30: Retention | BU30: NO | BX30: There is a thing that I call the volcano, which is when a toilet gets clogged, clogs a toilet with diarrhea, eye, it's very difficult. You have to be very fucked up inside. | BY30: 1. Reproduction | BZ30: Retention | CA30: NO | CD30: There's a thing I call the volcano, which is when a toilet gets clogged, clogged with diarrhea, watch out, it's really hard. You have to be really fucked up inside. | CE30: 1. Reproduction | CF30: Retention | CG30: NO | CJ30: There is a thing that I call the volcano, which is when a toilet gets clogged, clogs a toilet with diarrhea, watch out, it's really hard. You have to be really fucked up inside. | CK30: 1. Reproduction | CL30: Retention | CM30: NO | CP30: There is a thing that I call the volcano, which is when a toilet gets clogged, clogs a toilet with diarrhea, watch out, it's really hard. You have to be really fucked up inside. | CQ30: 1. Reproduction | CR30: Retention | CS30: NO
A31: [empieza tema de conversación] | B31: Obviamente, un poquito de postureo de vez en cuando. Un poco de decirte que has ido de vacaciones en tal sitio. Es que una foto bonita no hace daño a nadie. No hace falta no hacer fotos. | C31: Estar en una playa de puta madre, le echas una foto a la playa porque hay una puesta de sol impresionante, no hay ningún tipo de problema. Cada uno es libre de hacer lo que quiera como quiera. | D31: Obviamente, un poquito de postureo de vez en cuando. Un poco de decirte que has ido de vacaciones en tal sitio. Es que una foto bonita no hace daño a nadie. No hace falta no hacer fotos. | E31: 2. Non-standard linguistic features | F31: 2.2 | G31: Colloquial syntactic structures | J31: Obviously, a little bit of showing off now and then. A bit of telling people you've been on holiday in such and such a place. It's just that a nice photo doesn't hurt anyone. There's no need to avoid taking photos. | K31: 4. Creative Shifts | L31: Abstraction – Superordinate Term | M31: NO | P31: Obviously, a little bit of showing off now and then. Like, telling people you went on holiday to a certain place. It's not like a nice photo ever hurt anyone. There's no need to avoid taking photos altogether. | Q31: 4. Creative Shifts | R31: Abstraction – Superordinate Term | S31: NO | V31: Obviously, a bit of showing off now and then. Like telling people you went on holiday to a certain place. It's just that a nice photo doesn't hurt anyone. There's no need to avoid taking photos altogether. | W31: 4. Creative Shifts | X31: Abstraction – Superordinate Term | Y31: NO | AB31: Obviously, a little bit of showing off now and then. A little bit of telling people you've been on holiday in such and such a place. It's just that a nice photo doesn't hurt anyone. There's no need not to take photos. | AC31: 1. Reproduction | AD31: Direct Translation | AE31: YES | AH31: "Of course, a bit of showing off now and then. Like, telling people you went on holiday to a certain place. It's just that a nice photo doesn't hurt anyone. There's no need to avoid taking photos altogether. | AI31: 4. Creative Shifts | AJ31: Abstraction – Superordinate Term | AK31: NO | AN31: Obviously, a little bit of posing now and then. A little bit of telling you that you went on vacation to such and such a place. It's just that a nice photo doesn't hurt anyone. There's no need not to take photos. | AO31: 1. Reproduction | AP31: Direct Translation | AQ31: YES | AT31: Of course, a little bit of posing now and then. A little bit of telling you that you went on vacation to such and such place. It's just that a nice photo doesn't hurt anyone. There's no need not to take photos. | AU31: 1. Reproduction | AV31: Direct Translation | AW31: YES | AZ31: Of course, a little bit of posing now and then. A bit of telling you that you went on vacation to such-and-such place. It's just that a nice photo doesn't hurt anyone. There's no need to not take photos. | BA31: 1. Reproduction | BB31: Direct Translation | BC31: YES | BF31: Of course, a little bit of posing now and then. A little bit of telling you that you went on vacation to such-and-such place. It's just that a nice photo doesn't hurt anyone. There's no need not to take photos. | BG31: 1. Reproduction | BH31: Direct Translation | BI31: YES | BL31: Obviously, a little bit of showing off now and then. A little bit of telling you that you went on vacation to such-and-such place. It’s just that a nice photo doesn’t hurt anyone. You don’t have to avoid taking photos. | BM31: 4. Creative Shifts | BN31: Abstraction – Superordinate Term | BO31: NO | BR31: Of course, a bit of posing from time to time. A bit of saying you went on vacation somewhere. It's just that a nice photo doesn't hurt anyone. There's no need not to take photos. | BS31: 1. Reproduction | BT31: Direct Translation | BU31: YES | BX31: Sure, a little bit of posing every now and then. Saying something like \"I went on vacation somewhere\" - It's just one nice picture doesn't hurt anyone. There's no need not take pictures | BY31: 1. Reproduction | BZ31: Direct Translation | CA31: YES | CD31: Of course, a little bit of posing from time to time. A little bit of saying you went on vacation somewhere. It's just that a nice photo doesn't hurt anyone. There's no need not to take photos. | CE31: 1. Reproduction | CF31: Direct Translation | CG31: YES | CJ31: Of course, a bit of posing from time to time. A bit of saying you went on vacation somewhere. It's just that a nice photo doesn't hurt anyone. There's no need not to take photos. | CK31: 1. Reproduction | CL31: Direct Translation | CM31: YES | CP31: Of course, a bit of posing from time to time. A bit of saying you went on vacation somewhere. It's just that a nice photo doesn't hurt anyone. There's no need not to take photos. | CQ31: 1. Reproduction | CR31: Direct Translation | CS31: YES
A32: [empieza tema de conversación] | B32: Una señora mayor que me llama, me dice, la tarjeta que me han robado en un bar, no sé qué, bla, bla, bla. Es que fui a orinar y cuando volví ya no estaba. | C32: Y oigo una voz por detrás que le dice, pero para aquí no le digas que fuiste a orinar. | D32: Una señora mayor que me llama, me dice, la tarjeta que me han robado en un bar, no sé qué, bla, bla, bla. Es que fui a orinar y cuando volví ya no estaba. | E32: 1. Lexicon and Vocabulary | F32: 1.7 | G32: Onomatopoeia and sound representation | H32: blah blah blah | I32: ReversoContext | J32: An elderly woman called me and said, "They stole my card in a bar, I don't know what to do, blah, blah, blah." It's just that I went to the toilet, and when I came back, it was gone. | K32: 1. Reproduction | L32: Direct Translation | M32: YES | P32: An elderly woman calls me and tells me that her card was stolen in a bar, she doesn't know what happened, blah, blah, blah. She says she went to the toilet and when she came back, it was gone. | Q32: 1. Reproduction | R32: Direct Translation | S32: YES | V32: "An elderly woman called me, and she said her card had been stolen in a bar, blah, blah, blah. Apparently, I went to the toilet, and when I came back, it was gone." | W32: 1. Reproduction | X32: Direct Translation | Y32: YES | AB32: An elderly lady called me and told me her card had been stolen in a bar, she didn't know the details, just a lot of rambling. Apparently, she went to the toilet and when she came back, it was gone. | AC32: 4. Creative Shifts | AD32: Abstraction – Paraphrase | AE32: NO | AH32: "An elderly woman called me, and she said her card had been stolen in a bar, I don't know, blah, blah, blah. It's just that I went to the toilet, and when I came back, it was gone." | AI32: 1. Reproduction | AJ32: Direct Translation | AK32: YES | AN32: A lady calls me up, says, "The card they stole from you in a bar, I don't know what, bla, bla, bla." It's just that I went to pee and when I came back, it wasn't there anymore. | AO32: 1. Reproduction | AP32: Retention | AQ32: YES | AT32: A lady older than me calls me, says that the card they stole from me in a bar, I don't know what, bla, bla, bla. It's just that I went to pee and when I came back it wasn't there. | AU32: 1. Reproduction | AV32: Retention | AW32: YES | AZ32: A lady calls me, says, "The card they stole from me in a bar, I don't know, bla, bla, bla." It's just that I went to pee and when I came back, it wasn't there anymore. | BA32: 1. Reproduction | BB32: Retention | BC32: YES | BF32: An old lady called me and said, "The card they stole from me at a bar, I don't know what, bla, bla, bla." It's that I went to pee and when I came back, it wasn't there anymore. | BG32: 1. Reproduction | BH32: Retention | BI32: YES | BL32: An older lady called me and said, “The card they stole from me at a bar, I don’t know what, bla, bla, bla.” It’s that I went to pee and when I came back, it wasn’t there anymore. | BM32: 1. Reproduction | BN32: Retention | BO32: YES | BR32: An elderly lady calls me, says, the card they stole from me in a bar, I don't know what, bla, bla, bla. It's that I went to the bathroom and when I came back it wasn't there anymore. | BS32: 1. Reproduction | BT32: Retention | BU32: YES | BX32: A lady calls me, says she, they stole my credit card in a pub, don’t know what, blah, blah, blah. It’s that I went to pee and when I came back it wasn’t there anymore. And then I hear a voice behind her saying, but tell him you went to pee. | BY32: 1. Reproduction | BZ32: Direct Translation | CA32: YES | CD32: An older lady calls me, says, the card they stole from me in a bar, I don't know what, bla, bla, bla. I went to the bathroom and when I came back it wasn't there. | CE32: 1. Reproduction | CF32: Retention | CG32: YES | CJ32: An elderly lady calls me, she says, the card they have stolen from me in a bar, I don't know what, bla, bla, bla. It's that I went to the bathroom and when I came back it wasn't there anymore. | CK32: 1. Reproduction | CL32: Retention | CM32: YES | CP32: An elderly lady calls me, she says, the card they have stolen from me in a bar, I don't know what, bla, bla, bla. It's that I went to the bathroom and when I came back it wasn't there anymore. | CQ32: 1. Reproduction | CR32: Retention | CS32: YES
A33: [empieza tema de conversación] | B33: Yo lo cuento así y digo, jajaja, qué gracioso, porque en realidad no le estás haciendo nada malo, porque le estás cambiando la luz. Quiero decir que tampoco es que le estés poniendo la hipoteca de su vida. | C33: Normalmente las ofertas que había eran bastante buenas, pero sí que te ibas diciendo, joder, esta señora me ha llamado por lo de Nefertiti y le he hecho un contrato de luz totalmente innecesario, ¿sabes? | D33: Yo lo cuento así y digo, jajaja, qué gracioso, porque en realidad no le estás haciendo nada malo, porque le estás cambiando la luz. Quiero decir que tampoco es que le estés poniendo la hipoteca de su vida. | E33: 1. Lexicon and Vocabulary | F33: 1.7 | G33: Onomatopoeia and sound representation | J33: I tell the story like this, and I laugh, because in reality, you're not doing anything wrong, you're just changing the lightbulb. I mean, you're not completely ruining their life. | K33: 4. Creative Shifts | L33: Abstraction – Paraphrase | M33: NO | P33: "I tell it like this, and I say, 'Haha, how funny,' because in reality, you're not really doing anything wrong, you're just changing their lightbulb. I mean, it's not like you're completely ruining their life." | Q33: 1. Reproduction | R33: Direct Translation | S33: YES | V33: I tell it this way and I say, "Haha, how funny," because in reality, you're not really doing anything wrong, you're just changing the lightbulb. I mean, you're not completely ruining their life. | W33: 1. Reproduction | X33: Direct Translation | Y33: YES | AB33: "I tell the story like this, and I say, haha, how funny, because you're not actually doing anything bad, you're just changing the lightbulb. I mean, you're not putting their entire life on hold." | AC33: 1. Reproduction | AD33: Direct Translation | AE33: YES | AH33: I tell it like this, haha, it's so funny, because you're not actually doing anything bad, you're just changing the lightbulb. I mean, you're not putting her entire life on the line. | AI33: 1. Reproduction | AJ33: Direct Translation | AK33: YES | AN33: I tell it like that and say, haha, what a joke, because in reality you're not doing anything wrong, because you're just changing the light. I mean, it's not like you're putting her life savings on the line. | AO33: 1. Reproduction | AP33: Direct Translation | AQ33: YES | AT33: I tell it like that and say, haha, how funny, because in reality you're not doing anything wrong, because you're changing the light. I mean, you're not putting her life savings on the line. | AU33: 1. Reproduction | AV33: Direct Translation | AW33: YES | AZ33: I tell it like that and say, haha, what a joke, because in reality you're not doing anything wrong, because you're just changing the light. I mean, you're not putting his whole life mortgage on it. | BA33: 1. Reproduction | BB33: Direct Translation | BC33: YES | BF33: I tell it like that and say, jajaja, what a joke, because in reality you're not doing anything wrong, because you're changing the light. I mean, it's not like you're putting her life savings on the line. | BG33: 1. Reproduction | BH33: Retention | BI33: YES | BL33: I tell it like that and say, jajaja, what a joke, because in reality you're not doing anything wrong to them, you're just changing their light. I mean, you're not exactly giving them their life mortgage. | BM33: 1. Reproduction | BN33: Retention | BO33: YES | BR33: I tell it like that and I say, haha, what a joke, because in reality you're not doing him any harm, because you're changing the light. I mean, you're not putting him the mortgage of his life. | BS33: 1. Reproduction | BT33: Direct Translation | BU33: YES | BX33: I tell him like this and say, haha, how funny, because actually you aren't doing anything bad to them, because you're changing their light. I mean, you're not putting them through some mortgage of their lives." | BY33: 1. Reproduction | BZ33: Direct Translation | CA33: YES | CD33: I tell it like that and I say, haha, what a joke, because in reality you're not doing him any harm, because you're changing the light. I mean, you're not putting him the mortgage of his life. | CE33: 1. Reproduction | CF33: Direct Translation | CG33: YES | CJ33: I tell it like this and I say, haha, what a joke, because in reality you're not doing him any harm, because you're changing the light. I mean, you're not putting him the mortgage of his life. | CK33: 1. Reproduction | CL33: Direct Translation | CM33: YES | CP33: I tell it like that and I say, haha, what a joke, because in reality you're not doing him any harm, because you're changing the light. I mean, you're not putting him the mortgage of his life. | CQ33: 1. Reproduction | CR33: Direct Translation | CS33: YES
A34: [empieza tema de conversación] | B34: Raquel se quedó para nuestros corazones en este canal. Y cada 2 por 3 gente que ha vuelto a ver el vídeo, o gente nueva que ha descubierto los vídeos, dice, ¿cuándo va a volver esta chiquilla? Ha vuelto. | C34: ¡Hola! | D34: Raquel se quedó para nuestros corazones en este canal. Y cada 2 por 3 gente que ha vuelto a ver el vídeo, o gente nueva que ha descubierto los vídeos, dice, ¿cuándo va a volver esta chiquilla? Ha vuelto. | E34: 1. Lexicon and Vocabulary | F34: 1.4 | G34: Idiomatic expressions and colloquial phraseology | H34: every five minutes / keeps + gerund / | I34: WordReference | J34: Raquel will always hold a special place in our hearts on this channel. And every now and then, people who have rewatched the video, or new viewers who have discovered our videos, ask, "When is this young woman coming back?" Well, she's back. | K34: 4. Creative Shifts | L34: Modification – Situational | M34: YES | P34: Raquel will always hold a special place in our hearts on this channel. And every so often, people who have rewatched the video, or new viewers who have discovered our videos, ask, "When is this girl coming back?" Well, she's back. | Q34: 4. Creative Shifts | R34: Modification – Situational | S34: YES | V34: Raquel will always hold a special place in our hearts on this channel. And every so often, people who have rewatched the video, or new people who have discovered the videos, ask, "When is this girl coming back?" Well, she's back. | W34: 4. Creative Shifts | X34: Modification – Situational | Y34: YES | AB34: Raquel will always hold a special place in our hearts on this channel. And every so often, people who have rewatched the video, or new viewers who have discovered our videos, ask, "When is this young woman going to come back?" Well, she's back. | AC34: 4. Creative Shifts | AD34: Modification – Situational | AE34: YES | AH34: Raquel will always hold a special place in our hearts on this channel. And every so often, people who have rewatched the video, or new viewers who have discovered our videos, ask, "When is this girl coming back?" Well, she's back. | AI34: 4. Creative Shifts | AJ34: Modification – Situational | AK34: YES | AN34: Raquel stayed in our hearts on this channel. And every time 2 out of 3 people who watch the video again, or new people who discover the videos, say, "When is this little girl coming back?" She's back. | AO34: 3. Errors | AQ34: NO | AT34: Raquel stayed in our hearts on this channel. And every two out of three people who have watched the video again, or new people who discovered the videos, say, "When is this kid coming back?" She's back. | AU34: 3. Errors | AW34: NO | AZ34: Raquel stays in our hearts on this channel. And every two out of three people who watch the video again, or new folks who discover the videos, ask, "When is this kid coming back?" She's back. | BA34: 3. Errors | BC34: NO | BF34: Raquel stayed in our hearts on this channel. And every two out of three people who have watched the video again, or new people who discovered the videos, say, "When is this girl coming back?" She's back. | BG34: 3. Errors | BI34: NO | BL34: Raquel stayed in our hearts on this channel. And every two out of three people who have watched the video again, or new people who discovered the videos, say, "When is this little girl coming back?" She's back. | BM34: 3. Errors | BO34: NO | BR34: Raquel stayed in our hearts on this channel. And every now and then people who have re-watched the video, or new people who have discovered the videos, say, "When is this little girl going to come back?" She's back. | BS34: 4. Creative Shifts | BT34: Modification – Situational | BU34: YES | BX34: Raquel stayed in our hearts on this channel. And every now and then people who have re-watched the video, or new people who have discovered the videos say, when will this little girl come back? She came back." | BY34: 4. Creative Shifts | BZ34: Modification – Situational | CA34: YES | CD34: Raquel is still in our hearts on this channel. And every now and then people who have re-watched the video, or new people who have discovered the videos, say, "When is this little girl going to come back?" She's back. | CE34: 4. Creative Shifts | CF34: Modification – Situational | CG34: YES | CJ34: Raquel stayed in our hearts on this channel. And every now and then people who have re-watched the video, or new people who have discovered the videos, say, "When is this girl going to come back?" She's back. | CK34: 4. Creative Shifts | CL34: Modification – Situational | CM34: YES | CP34: Raquel stayed in our hearts on this channel. And every now and then people who have re-watched the video, or new people who have discovered the videos, say, "When will this little girl return?" She has returned. | CQ34: 4. Creative Shifts | CR34: Modification – Situational | CS34: YES
A35: [empieza tema de conversación] | B35: Fuimos a casa de un señor, de una pareja británica, muy monos, en la zona más rural de los rurales de los rurales de Burgos. Llevaban como pollas de años ahí. | C35: [cambio de tema] | D35: Fuimos a casa de un señor, de una pareja británica, muy monos, en la zona más rural de los rurales de los rurales de Burgos. Llevaban como pollas de años ahí. | E35: 1. Lexicon and Vocabulary | F35: 1.5 | G35: Informal intensifiers and quantifiers | H35: fuckload of / shit-ton of year | I35: Gemini | J35: We went to the house of a couple, a British couple, who were lovely. They lived in the most rural part of rural Burgos – it was really out in the sticks. They'd been living there for ages. | K35: 4. Creative Shifts | L35: Abstraction – Superordinate Term | M35: NO | P35: We went to the house of a couple, a British couple, who were really lovely. They lived in the most rural area you could imagine, way out in the countryside of Burgos. They'd been living there for ages. | Q35: 4. Creative Shifts | R35: Abstraction – Superordinate Term | S35: NO | V35: We went to the house of a couple, a British couple, really nice people, in the most rural part of rural Burgos. They've been living there for ages. | W35: 4. Creative Shifts | X35: Abstraction – Superordinate Term | Y35: NO | AB35: We went to the house of a couple, a British couple, who were really lovely. They lived in the most rural area you could imagine, way out in the countryside of Burgos. They'd been living there for ages. | AC35: 4. Creative Shifts | AD35: Abstraction – Superordinate Term | AE35: NO | AH35: We went to the house of a couple, a British couple, who were really lovely. They lived in the most rural part of rural Burgos – it was incredibly remote. They'd been living there for ages. | AI35: 4. Creative Shifts | AJ35: Abstraction – Superordinate Term | AK35: NO | AN35: We went to a guy's house, a British couple, really cute, in the most rural part of the rural areas of Burgos. They've been there for like years. | AO35: 4. Creative Shifts | AP35: Abstraction – Superordinate Term | AQ35: NO | AT35: We went to a guy's house, a British couple, really cute, in the most rural part of the rural areas of Burgos. They'd been there for like years. | AU35: 4. Creative Shifts | AV35: Abstraction – Superordinate Term | AW35: NO | AZ35: We went to a guy's house, a British couple, really cute, in the most rural part of the rural areas of Burgos. They've been there for like ages. | BA35: 4. Creative Shifts | BB35: Abstraction – Superordinate Term | BC35: NO | BF35: We went to the house of a guy, a British couple, really cute, in the most rural part of the rural areas of Burgos. They've been living there for like years. | BG35: 4. Creative Shifts | BH35: Abstraction – Superordinate Term | BI35: NO | BL35: We went to see a guy, a British couple, really cool people, in the most rural part of the rural areas of Burgos. They’d been living there for ages. | BM35: 4. Creative Shifts | BN35: Abstraction – Superordinate Term | BO35: NO | BR35: We went to the house of a British couple, very cute, in the most rural area of the rural areas of Burgos. They had been there for like years. | BS35: 4. Creative Shifts | BT35: Abstraction – Superordinate Term | BU35: NO | BX35: We went to the home of a very nice British couple in the most rural area of rural Burgos. They had been living there for years. | BY35: 4. Creative Shifts | BZ35: Abstraction – Superordinate Term | CA35: NO | CD35: We went to the house of a British couple, very cute, in the most rural area of the rural areas of Burgos. They had been living there for years. | CE35: 4. Creative Shifts | CF35: Abstraction – Superordinate Term | CG35: NO | CJ35: We went to the house of a British couple, very cute, in the most rural area of the rural areas of Burgos. They had been there for like years. | CK35: 4. Creative Shifts | CL35: Abstraction – Superordinate Term | CM35: NO | CP35: We went to the house of a British couple, very cute, in the most rural area of the rural areas of Burgos. They had been there for like years. | CQ35: 4. Creative Shifts | CR35: Abstraction – Superordinate Term | CS35: NO
A36: [empieza tema de conversación] | B36: Son tan orgullosos del francés. Francia lo mejor, los franceses lo mejor, la gastronomía francesa lo mejor y yo me cago en la gastronomía francesa. | C36: Es verdad. Yo he estado en restaurantes franceses y todo, comiendo gastronomía allí. Yo he hecho el intento y no está mal. | D36: Son tan orgullosos del francés. Francia lo mejor, los franceses lo mejor, la gastronomía francesa lo mejor y yo me cago en la gastronomía francesa. | E36: 1. Lexicon and Vocabulary | F36: 1.2 | G36: Colloquial lexicon and slang | H36: fuck you / go fuck yourself / not give a shit about / not give a damn about / | I36: WordReference | J36: They're so proud of French culture. France is the best, the French are the best, French cuisine is the best, and I, frankly, don't care for French cuisine. | K36: 4. Creative Shifts | L36: Abstraction – Paraphrase | M36: NO | P36: They're so proud of French culture. France is the best, the French are the best, French cuisine is the best, and I think French cuisine is overrated. | Q36: 4. Creative Shifts | R36: Abstraction – Paraphrase | S36: NO | V36: They're so proud of French culture. France is the best, the French are the best, French cuisine is the best, and I just don't care for French cuisine. | W36: 4. Creative Shifts | X36: Abstraction – Paraphrase | Y36: NO | AB36: They're so proud of French culture. France is the best, the French are the best, French cuisine is the best, and I, frankly, think French cuisine is overrated. | AC36: 4. Creative Shifts | AD36: Abstraction – Paraphrase | AE36: NO | AH36: They're so proud of French culture. France is the best, the French are the best, French cuisine is the best, and I, frankly, think French cuisine is rubbish. | AI36: 4. Creative Shifts | AJ36: Modification – Situational | AK36: NO | AN36: They're so proud of French things. France is the best, the French are the best, French cuisine is the best—and I take a dump on French cuisine. | AO36: 1. Reproduction | AP36: Direct Translation | AQ36: YES | AT36: They're so proud of French. France is the best, the French people are the best, French cuisine is the best, and I'm taking a dump on French cuisine. | AU36: 1. Reproduction | AV36: Direct Translation | AW36: YES | AZ36: They're so proud of French. France is the best, the French are the best, French cuisine is the best—and I'd rather crap on French cuisine. | BA36: 4. Creative Shifts | BB36: Modification – Situational | BC36: YES | BF36: They're so proud of French things. France is the best, the French are the best, French cuisine is the best—and I'm taking a dump on French cuisine. | BG36: 1. Reproduction | BH36: Direct Translation | BI36: YES | BL36: They’re so proud of the French. France is the best, the French are the best, French cuisine is the best—and I’m taking a dump on French cuisine. | BM36: 1. Reproduction | BN36: Direct Translation | BO36: YES | BR36: They are so proud of the French. France is the best, the French are the best, French gastronomy is the best and I shit on French gastronomy. | BS36: 1. Reproduction | BT36: Direct Translation | BU36: YES | BX36: They are so proud of French people. France is best, French people are best, French cuisine is best and I piss all over French cuisine | BY36: 4. Creative Shifts | BZ36: Modification – Situational | CA36: YES | CD36: They are so proud of the French. France is the best, the French are the best, French gastronomy is the best and I piss on French gastronomy. | CE36: 4. Creative Shifts | CF36: Modification – Situational | CG36: YES | CJ36: They are so proud of the French. France is the best, the French are the best, French gastronomy is the best and I piss on French gastronomy. | CK36: 4. Creative Shifts | CL36: Modification – Situational | CM36: YES | CP36: They are so proud of the French. France is the best, the French are the best, French gastronomy is the best and I shit on French gastronomy. | CQ36: 1. Reproduction | CR36: Direct Translation | CS36: YES
A37: [empieza tema de conversación] | B37: Mira, yo me llamo Iván, para todo aquel que no me conozca. Y como ya he explicado perfectamente, yo he trabajado hablando mal y pronto, dando el coñazo a la gente para intentar que acepten a algún compañero ir a la vivienda. | C37: Y ese era mi objetivo, que la gente fuera a la vivienda e intentar vender alarma. | D37: Mira, yo me llamo Iván, para todo aquel que no me conozca. Y como ya he explicado perfectamente, yo he trabajado hablando mal y pronto, dando el coñazo a la gente para intentar que acepten a algún compañero ir a la vivienda. | E37: 1. Lexicon and Vocabulary | F37: 1.4 | G37: Idiomatic expressions and colloquial phraseology | H37: pardon my French | I37: Tureng | J37: "Right, so my name is Iván, for anyone who doesn't know me. And as I've already explained perfectly, I used to work by being unpleasant and, frankly, a bit of a pain to people, trying to persuade them to let a colleague into their home. | K37: 4. Creative Shifts | L37: Abstraction – Superordinate Term | M37: YES | P37: Look, my name is Iván, for anyone who doesn't know me. And as I've already explained perfectly, I used to work by talking badly about things and, very quickly, by being a pain to people in order to try and get them to agree to let a colleague move into their accommodation. | Q37: 3. Errors | S37: NO | V37: Right, so my name is Iván, for anyone who doesn't know me. And as I've already explained perfectly, I used to work by bad-mouthing people and being a pain in the neck, trying to convince them to let a colleague move into their place. | W37: 2. Omissions | X37: Shortcut Solution | Y37: NO | AB37: Look, my name is Iván, for anyone who doesn't know me. And as I've already explained perfectly, I used to work by being negative and, frankly, being a pain to people, trying to convince them to let a colleague visit their home. | AC37: 4. Creative Shifts | AD37: Abstraction – Superordinate Term | AE37: YES | AH37: "Right, so my name's Iván, for anyone who doesn't know me. And as I've already explained perfectly, I used to work by being really negative and, frankly, annoying people to try and get them to agree to let a colleague visit their home." | AI37: 4. Creative Shifts | AJ37: Abstraction – Superordinate Term | AK37: YES | AN37: Look, my name is Ivan, for anyone who doesn't know me. And as I've explained perfectly already, I've worked by talking badly and quickly, annoying people in order to try and get them to accept some colleague going to the house. | AO37: 1. Reproduction | AP37: Direct Translation | AQ37: NO | AT37: Look, my name's Ivan, for anyone who doesn't know me. And as I've explained perfectly, I've worked by talking bad about people and annoying them to try and get them to agree to have a roommate move in with them. | AU37: 2. Omissions | AV37: Shortcut Solution | AW37: NO | AZ37: Hey, I'm Ivan, for anyone who doesn't know me. And as I've explained perfectly, I've been pushing my luck, annoying people to try to get someone to accept a colleague to come to the house | BA37: 2. Omissions | BB37: Shortcut Solution | BC37: NO | BF37: Look, my name is Ivan, for anyone who doesn't know me. And as I've explained perfectly, I've worked speaking poorly and quickly, annoying people to try to get them to accept a colleague to go to the housing. | BG37: 1. Reproduction | BH37: Direct Translation | BI37: NO | BL37: Look, my name is Ivan, for everyone who doesn't know me. And as I've already explained perfectly, I've worked by talking badly and quickly, annoying people in order to try to get them to accept some colleague going to the house. | BM37: 1. Reproduction | BN37: Direct Translation | BO37: NO | BR37: Look, my name is Iván, for anyone who doesn't know me. And as I have already explained perfectly, I have worked talking badly and soon, giving the crap to people to try to get some companion to go to the apartment. | BS37: 1. Reproduction | BT37: Direct Translation | BU37: NO | BX37: Iván is my name, by the way, in case anyone doesn’t know. And as I have already explained perfectly, I worked talking badly and soon, giving people a hard time trying to get them to accept some colleague going to their home. | BY37: 1. Reproduction | BZ37: Direct Translation | CA37: NO | CD37: Look, my name is Iván, for anyone who doesn't know me. And as I have already explained perfectly, I have worked talking badly and soon, bothering people to try to get some companion to go to the housing. | CE37: 1. Reproduction | CF37: Direct Translation | CG37: NO | CJ37: Look, my name is Iván, for anyone who doesn't know me. And as I have already explained perfectly, I have worked talking badly and soon, giving the crap to people to try to get someone to accept going to the apartment. | CK37: 1. Reproduction | CL37: Direct Translation | CM37: NO | CP37: Look, my name is Iván, for anyone who doesn't know me. And as I have already explained perfectly, I have worked talking badly and soon, giving the crap to people to try to get someone to accept going to the apartment. | CQ37: 1. Reproduction | CR37: Direct Translation | CS37: NO
A38: [empieza tema de conversación] | B38: La Cruz Roja dijo que iba a denunciar a la policía en mi nombre, que no sé qué. Luego la policía pidió perdón. Una movida más rara, tío. Jódeme más esta vida gitana que tengo, vamos. | C38: [cambio de tema] | D38: La Cruz Roja dijo que iba a denunciar a la policía en mi nombre, que no sé qué. Luego la policía pidió perdón. Una movida más rara, tío. Jódeme más esta vida gitana que tengo, vamos. | E38: 1. Lexicon and Vocabulary | F38: 1.6 | G38: References to popular culture and memes | H38: Spanish meme that describes a bohemian chaotic complicated stylelife | J38: The Red Cross said they were going to report the police on my behalf, I don't know what for. Then the police apologised. It was just another weird thing, mate. Honestly, this nomadic life I have is really getting to me. | K38: 3. Errors | M38: NO | P38: The Red Cross said they were going to report the police on my behalf, I don't know what for. Then the police apologised. Another really strange thing, mate. This nomadic life I'm living is just driving me crazy, to be honest. | Q38: 3. Errors | S38: NO | V38: The Red Cross said they were going to report the police on my behalf, I don't know what for. Then the police apologised. Just another weird thing, mate. This nomadic life I'm living is really getting to me, honestly. | W38: 3. Errors | Y38: NO | AB38: The Red Cross said they were going to report the police on my behalf, I don't know what for. Then the police apologised. Just another bizarre thing, mate. This nomadic lifestyle I have really gets to me, to be honest. | AC38: 3. Errors | AE38: NO | AH38: The Red Cross said they were going to report the police on my behalf, I don't know what for. Then the police apologised. It was just another bizarre situation, mate. Honestly, this nomadic lifestyle I'm living is really getting to me. | AI38: 3. Errors | AK38: NO | AN38: The Red Cross said they were going to report the police on my behalf, I don't know what for. Then the police apologized. Another weird move, man. Hell, I wish I had a gypsy life like this, let's go. | AO38: 3. Errors | AQ38: NO | AT38: The Red Cross said they were going to report the police on my behalf, I don't know what. Then the police apologized. Another weird move, dude. Jeez, this gypsy life I've got, man, I wish I could just curse it out. | AU38: 3. Errors | AW38: NO | AZ38: The Red Cross said they were going to report the police on my behalf, I don't know what. Then the police apologized. Another weird move, man. God, this gypsy life I've got, let's get this over with. | BA38: 3. Errors | BC38: NO | BF38: The Red Cross said they were going to report the police on my behalf, I don't know what for. Then the police apologized. Another weird move, man. Hell, I wish I had a gypsy life like this, let's go. | BG38: 3. Errors | BI38: NO | BL38: The Red Cross said they were going to file a complaint against the police on my behalf, I don’t know what for. Then the police apologized. Another weird move, man. Damn this gypsy life I’ve got, let’s go. | BM38: 3. Errors | BO38: NO | BR38: The Red Cross said they were going to report me to the police in my name, I don't know what. Then the police apologized. A weirder move, dude. Fuck me more with this gypsy life I have, come on. | BS38: 1. Reproduction | BT38: Direct Translation | BU38: NO | BX38: The Red Cross said that they were going to report the police in my name, which I don't know about. Then the police apologised. A very strange move, man. Fuck this gypsy life I have, come on. | BY38: 1. Reproduction | BZ38: Direct Translation | CA38: NO | CD38: The Red Cross said they were going to report me to the police in my name, which I don't know what. Then the police apologized. A weirder move, dude. Fuck me more with this gypsy life I have, come on. | CE38: 1. Reproduction | CF38: Direct Translation | CG38: NO | CJ38: The Red Cross said they were going to report me to the police in my name, who knows what. Then the police apologized. A weirder move, dude. Fuck me more with this gypsy life I have, come on. | CK38: 1. Reproduction | CL38: Direct Translation | CM38: NO | CP38: The Red Cross said they were going to report me to the police in my name, I don't know what. Then the police apologized. A weirder move, dude. Fuck me more with this gypsy life I have, come on. | CQ38: 1. Reproduction | CR38: Direct Translation | CS38: NO
A39: [empieza tema de conversación] | B39: La gente tiene mucho odio contra los franceses y lo entiendo, pero tengo que decir que yo en mi caso desarrollé un odio con la gente italiana. Es como un español, pero en nivel de cuñado como al máximo. | C39: Es así, o sea, les encanta montar un escándalo, les encanta hacerse notar borrachos. | D39: La gente tiene mucho odio contra los franceses y lo entiendo, pero tengo que decir que yo en mi caso desarrollé un odio con la gente italiana. Es como un español, pero en nivel de cuñado como al máximo. | E39: 1. Lexicon and Vocabulary | F39: 1.6 | G39: References to popular culture and memes | H39: busbybody / know-it-all | I39: WordReference | J39: People have a lot of animosity towards the French, and I understand that, but I have to say that, in my case, I developed a dislike for Italians. They're like Spaniards, but on the absolute highest level of being annoying. | K39: 4. Creative Shifts | L39: Abstraction – Paraphrase | M39: NO | P39: People have a lot of animosity towards the French, and I understand that, but I have to say that, in my case, I developed an aversion to Italians. They're like Spaniards, but on the absolute highest level of being annoying. | Q39: 4. Creative Shifts | R39: Abstraction – Paraphrase | S39: NO | V39: People have a lot of animosity towards the French, and I understand that, but I have to say that in my case, I developed a dislike for Italians. They're like Spaniards, but on the absolute maximum level of being annoying. | W39: 4. Creative Shifts | X39: Abstraction – Paraphrase | Y39: NO | AB39: People have a lot of animosity towards the French, and I understand that, but I have to say that, in my case, I developed a dislike for Italians. They're like Spaniards, but on the most irritating level possible. | AC39: 4. Creative Shifts | AD39: Abstraction – Paraphrase | AE39: NO | AH39: People have a lot of animosity towards the French, and I understand that, but I have to say that, in my case, I developed a dislike for Italians. They're like Spaniards, but on the absolute maximum level of being annoying. | AI39: 4. Creative Shifts | AJ39: Abstraction – Paraphrase | AK39: NO | AN39: People have a lot of hate for the French, and I get it, but I have to say that in my case I developed a hatred for Italians. It's like a Spaniard, but at the level of an in-law, like the worst possible one. | AO39: 1. Reproduction | AP39: Direct Translation | AQ39: NO | AT39: People have a lot of hate for the French, and I can understand that, but I have to say that in my case, I developed a hate for Italians. It's like a Spaniard, but at the level of a brother-in-law taken to the extreme. | AU39: 1. Reproduction | AV39: Direct Translation | AW39: NO | AZ39: People have a lot of hate for the French, and I get it, but I have to say that in my case I developed a hate for Italians. They're like a Spaniard, but at the level of an in-law, like the worst version. | BA39: 1. Reproduction | BB39: Direct Translation | BC39: NO | BF39: People have a lot of hate for the French, and I can understand that, but I have to say that in my case, I developed a hatred for Italians. It's like a Spaniard, but at the level of a brother-in-law taken to the extreme. | BG39: 1. Reproduction | BH39: Direct Translation | BI39: NO | BL39: People have a lot of hate for the French, and I get it, but I have to say that in my case, I developed a hate for the Italians. It's like a Spaniard, but at the level of a brother-in-law, like at maximum. | BM39: 1. Reproduction | BN39: Direct Translation | BO39: NO | BR39: People have a lot of hate against the French and I understand that, but I have to say that in my case I developed a hate with the Italian people. It's like a Spaniard, but at the level of a maximum cuñado. | BS39: 1. Reproduction | BT39: Retention | BU39: NO | BX39: People have so much hate against French people and I understand, but I have to say that in my case I developed hatred towards Italian people. It’s like a Spaniard, but at maximum level of cunny as when they make a scene drunk | BY39: 3. Errors | CA39: NO | CD39: People have a lot of hate against the French and I understand it, but I have to say that in my case I developed a hate with the Italian people. It's like a Spaniard, but at the level of a maximum cuñado. | CE39: 1. Reproduction | CF39: Retention | CG39: NO | CJ39: People have a lot of hate against the French and I understand that, but I have to say that in my case I developed a hate with the Italian people. It's like a Spaniard, but at the level of a brother-in-law as at the maximum. | CK39: 1. Reproduction | CL39: Direct Translation | CM39: NO | CP39: People have a lot of hate against the French and I understand that, but I have to say that in my case I developed a hate with the Italian people. It's like a Spaniard, but at the level of a brother-in-law as at maximum. | CQ39: 1. Reproduction | CR39: Direct Translation | CS39: NO
A40: [empieza tema de conversación] | B40: Vamos a abrir ese melón. En el anterior vídeo hablamos de sitios menos pudientes, ahora estamos hablando de sitios pudientes. Hablamos de colegios privados ultracatólicos en el centro de Madrid, en los cuales yo me he cruzado con la mayor chusma que te puedes imaginar. | C40: Era un campamento urbano en el que yo tenía niños de segundo de primaria, en el cual había un niño que su madre trabajaba en el colegio. Pues a ese niño, como la madre trabajaba en el colegio, no se querían juntar con él jugar con él, luego además en ese colegio yo tenía por contrato que yo no podía ni rezañar ni castigar ni quejarme a los padres | D40: Vamos a abrir ese melón. En el anterior vídeo hablamos de sitios menos pudientes, ahora estamos hablando de sitios pudientes. Hablamos de colegios privados ultracatólicos en el centro de Madrid, en los cuales yo me he cruzado con la mayor chusma que te puedes imaginar. | E40: 1. Lexicon and Vocabulary | F40: 1.4 | G40: Idiomatic expressions and colloquial phraseology | H40: riffraff / riff-raff | I40: Cambrdige / WordDictionary | J40: Okay, let's get into this. In the previous video, we talked about less affluent areas, but now we're talking about affluent areas. We're talking about ultra-Catholic private schools in the centre of Madrid, where I've encountered the most pretentious people you can imagine. | K40: 4. Creative Shifts | L40: Abstraction – Superordinate Term | M40: NO | P40: Okay, let's get into this. We're going to open up this can of worms. In the previous video, we talked about less affluent areas, but now we're talking about affluent areas. We're talking about ultra-Catholic private schools in the centre of Madrid, where I've encountered the most ridiculous people you can imagine. | Q40: 4. Creative Shifts | R40: Abstraction – Superordinate Term | S40: NO | V40: Right, let's tackle this topic. In the previous video, we talked about less affluent areas, now we're talking about affluent ones. We're talking about ultra-Catholic private schools in the centre of Madrid, where I've come across some of the most pretentious people you can imagine. | W40: 4. Creative Shifts | X40: Abstraction – Superordinate Term | Y40: NO | AB40: Right, let's tackle this topic. In the previous video, we talked about less affluent areas, but now we're talking about affluent areas. We're talking about ultra-Catholic private schools in the centre of Madrid, where I've encountered some of the most pretentious people you can imagine. | AC40: 4. Creative Shifts | AD40: Abstraction – Superordinate Term | AE40: NO | AH40: Right, let's get into this. In the previous video, we talked about less affluent areas. Now, we're talking about affluent areas. We're talking about ultra-Catholic private schools in the centre of Madrid, where I've encountered the most awful people you could possibly imagine. | AI40: 4. Creative Shifts | AJ40: Abstraction – Superordinate Term | AK40: NO | AN40: Let's open up that melon. In the previous video we talked about less posh places, now we're talking about more posh places. We're talking about ultra-Catholic private schools in the center of Madrid, where I've come across the worst bunch of kids you can imagine. | AO40: 4. Creative Shifts | AP40: Abstraction – Superordinate Term | AQ40: NO | AT40: Let's open that watermelon. In the previous video we talked about less posh places, now we're talking about more posh places. We're talking about ultra-Catholic private schools in the center of Madrid, where I've come across the worst bunch of kids you can imagine. | AU40: 4. Creative Shifts | AV40: Abstraction – Superordinate Term | AW40: NO | AZ40: Let's open up that watermelon. In the previous video we talked about less posh places, now we're talking about more posh places. We're talking about ultra-Catholic private schools in the center of Madrid, where I've run into the worst bunch of kids you can imagine. | BA40: 4. Creative Shifts | BB40: Abstraction – Superordinate Term | BC40: NO | BF40: Let’s get into it. In the previous video, we talked about less affluent places, now we’re talking about affluent ones. We’re talking about ultra-Catholic private schools in the center of Madrid, in which I’ve encountered the worst kind of riffraff you can imagine. | BG40: 1. Reproduction | BH40: Direct Translation | BI40: YES | BL40: Let's open that watermelon. In the previous video we talked about less affluent areas, now we're talking about more affluent ones. We're talking about ultra-Catholic private schools in the center of Madrid, where I've come across the worst kind of riff-raff you can imagine. | BM40: 1. Reproduction | BN40: Direct Translation | BO40: YES | BR40: Let's open that can of worms. In the previous video we talked about less affluent places, now we're talking about affluent places. We're talking about ultra-Catholic private schools in the center of Madrid, where I've run into the biggest riff-raff you can imagine. | BS40: 1. Reproduction | BT40: Direct Translation | BU40: YES | BX40: Let's talk about this issue now. In the previous video we talked about less affluent places, now we're talking about exclusive Catholic schools in downtown Madrid where I ran into some real trash you can imagine | BY40: 4. Creative Shifts | BZ40: Abstraction – Superordinate Term | CA40: NO | CD40: Let's open that can of worms. In the previous video we talked about less affluent places, now we're talking about affluent places. We're talking about ultra-Catholic private schools in the center of Madrid, where I've crossed paths with the biggest riff-raff you can imagine. | CE40: 1. Reproduction | CF40: Direct Translation | CG40: YES | CJ40: Let's open that can of worms. In the previous video we talked about less affluent places, now we're talking about affluent places. We're talking about ultra-Catholic private schools in the centre of Madrid, where I've crossed paths with the biggest riff-raff you can imagine. | CK40: 1. Reproduction | CL40: Direct Translation | CM40: YES | CP40: Let's open that can of worms. In the previous video we talked about less well-off places, now we're talking about well-off places. We're talking about ultra-Catholic private schools in the centre of Madrid, where I've crossed paths with the biggest riff-raff you can imagine | CQ40: 1. Reproduction | CR40: Direct Translation | CS40: YES
A41: [empieza tema de conversación] | B41: Una vez, creo que fue el mes de julio más o menos, había un cliente francés. Típico cliente francés de unos 50, 60 años, ¿vale? Que se le abrió el coche y tuvo que contactar con el seguro de Francia. A esto el señor no hablaba ni pipa de español, ¿sabes? | C41: Me pidió ayuda para traducirle, para contactar con el taller, para saber dónde tiene que llevarlo, a qué hora podía llevarlo, etcétera, ¿vale? | D41: Una vez, creo que fue el mes de julio más o menos, había un cliente francés. Típico cliente francés de unos 50, 60 años, ¿vale? Que se le abrió el coche y tuvo que contactar con el seguro de Francia. A esto el señor no hablaba ni pipa de español, ¿sabes? | E41: 3. Pragmatics and Discourse | F41: 3.1 | G41: Discourse markers | H41: you know? | I41: WordReference | J41: Once, I think it was sometime in July, we had a French customer. The typical French customer, around 50 or 60 years old, you know? His car had broken down, and he had to contact his insurance company in France. The thing is, the gentleman didn't speak a word of Spanish, you see? | K41: 4. Creative Shifts | L41: Modification – Situational | M41: YES | P41: Once, I think it was sometime in July, we had a French customer. The typical French customer, about 50 or 60 years old, you know? His car had broken down and he had to contact his insurance company in France. The thing is, the gentleman didn't speak a word of Spanish, you know | Q41: 1. Reproduction | R41: Direct Translation | S41: YES | V41: "Once, I think it was around July, we had a French client. The typical French client, about 50 or 60 years old, you know? His car had broken down and he had to contact his insurance company in France. The thing is, this guy didn't speak a word of Spanish, you know? | W41: 1. Reproduction | X41: Direct Translation | Y41: YES | AB41: "Once, I think it was around July, we had a French customer. The typical French customer, around 50 or 60 years old, you know? His car broke down, and he had to contact his insurance company in France. The thing is, the gentleman didn't speak a word of Spanish, you see?" | AC41: 4. Creative Shifts | AD41: Modification – Situational | AE41: YES | AH41: Once, I think it was sometime in July, we had a French customer. A typical French customer, around 50 or 60 years old, you know? His car had broken down, and he had to contact his insurance company in France. The thing is, the gentleman didn't speak a word of Spanish, you see? | AI41: 4. Creative Shifts | AJ41: Modification – Situational | AK41: YES | AN41: Once, I think it was around July, there was a French customer. Typical French customer, around 50 or 60 years old, right? His car broke down and he had to contact his insurance in France. And this guy didn't know a word of Spanish, you know? | AO41: 1. Reproduction | AP41: Direct Translation | AQ41: YES | AT41: Once, I think it was around July, there was a French client. Typical French client, around 50 or 60 years old, you know? His car broke down and he had to contact his French insurance company. And this guy didn’t speak a word of Spanish, you know? | AU41: 1. Reproduction | AV41: Direct Translation | AW41: YES | AZ41: Once, I think it was around July, there was a French client. Typical French client, around 50 or 60 years old, right? His car broke down and he had to get in touch with his French insurance company. And this guy didn't speak a word of Spanish, you know? | BA41: 1. Reproduction | BB41: Direct Translation | BC41: YES | BF41: Once, I think it was around July, there was a French customer. Typical French customer, about 50 or 60 years old, right? His car broke down and he had to contact the insurance in France. And this gentleman didn't speak a word of Spanish, do you know? | BG41: 1. Reproduction | BH41: Direct Translation | BI41: NO | BL41: Once, I think it was around July, there was a French client. Typical French client, around 50 or 60 years old, right? His car broke down, and he had to contact his insurance in France. And this guy didn’t know a single word of Spanish, you know? | BM41: 1. Reproduction | BN41: Direct Translation | BO41: YES | BR41: Once, I think it was in July, there was a French client. Typical French client of about 50 or 60 years old, right? Who had his car open and had to contact the French insurance company. The gentleman didn't speak a word of Spanish, do you know? | BS41: 1. Reproduction | BT41: Direct Translation | BU41: NO | BX41: Once, I think it was around July last year, there was a French client. Typical French customer aged about 50-60 years old who had his car opened and needed to contact the French insurance company. Now this gentleman didn’t speak so much Spanish did he now? | BY41: 3. Errors | CA41: NO | CD41: Once, I think it was in July, there was a French client. Typical French client of about 50 or 60 years old, right? Who had his car open and had to contact the French insurance. The gentleman didn't speak a word of Spanish, do you know? | CE41: 1. Reproduction | CF41: Direct Translation | CG41: NO | CJ41: Once, I think it was in July, there was a French client. Typical French client of about 50 or 60 years old, right? Who had his car open and had to contact the French insurance company. The gentleman didn't speak a word of Spanish, do you know? | CK41: 1. Reproduction | CL41: Direct Translation | CM41: NO | CP41: Once, I think it was in July, there was a French client. Typical French client of about 50 or 60 years old, right? Who had his car open and had to contact the French insurance company. The gentleman didn't speak a word of Spanish, do you know? | CQ41: 1. Reproduction | CR41: Direct Translation | CS41: NO
A42: [empieza tema de conversación] | B42: Siempre que he grabado algún vídeo en Inglaterra y he pillado a un irlandés o una irlandesa, el comentario estrella que siempre me han soltado en todos los vídeos que he grabado allí ha sido cagarse los muertos de Inglaterra de arriba abajo. | C42: Eso es una cosa que tenemos en común los españoles y los irlandeses, odiar a los ingleses. | D42: Siempre que he grabado algún vídeo en Inglaterra y he pillado a un irlandés o una irlandesa, el comentario estrella que siempre me han soltado en todos los vídeos que he grabado allí ha sido cagarse los muertos de Inglaterra de arriba abajo. | E42: 1. Lexicon and Vocabulary | F42: 1.4 | G42: Idiomatic expressions and colloquial phraseology | H42: to hell with sb | I42: WordReference | J42: Whenever I've filmed a video in England and happened to interview an Irish person, the most common comment I've received in all the videos I've made there is something along the lines of "let's criticise the English from top to bottom." | K42: 4. Creative Shifts | L42: Abstraction – Paraphrase | M42: NO | P42: Whenever I've filmed a video in England and encountered an Irish person, the most common comment I've received in all the videos I've filmed there is something along the lines of "screwing over the English." | Q42: 4. Creative Shifts | R42: Abstraction – Paraphrase | S42: YES | V42: Whenever I've filmed a video in England and caught sight of an Irishman or Irish woman, the most common comment I've received in all the videos I've filmed there is something along the lines of "screwing over the English." | W42: 4. Creative Shifts | X42: Abstraction – Paraphrase | Y42: YES | AB42: Whenever I've filmed a video in England and encountered an Irish person, the most common comment I've received in all the videos I've filmed there is something along the lines of "telling the English off" – essentially, criticising everything about England. | AC42: 4. Creative Shifts | AD42: Abstraction – Paraphrase | AE42: NO | AH42: "Whenever I've filmed a video in England and happened to encounter an Irish person, the most common comment I've received in all the videos I've shot there is something along the lines of 'blasting the English' – really going after them. | AI42: 4. Creative Shifts | AJ42: Abstraction – Paraphrase | AK42: NO | AN42: Whenever I've filmed any videos in England and come across an Irish person—either male or female—the top comment that's always been thrown at me in every video I've filmed there has been "f*** the English to hell." | AO42: 4. Creative Shifts | AP42: Modification – Cultural | AQ42: YES | AT42: Whenever I've filmed any videos in England and come across an Irish person, the top comment that's always been left on all my videos from there is "f*** the English from top to bottom." | AU42: 4. Creative Shifts | AV42: Modification – Cultural | AW42: YES | AZ42: Whenever I've filmed any videos in England and come across an Irish person—either male or female—the top comment that's always been left on every video I've filmed there has been something like "f*** the English from top to bottom." | BA42: 4. Creative Shifts | BB42: Modification – Cultural | BC42: YES | BF42: Whenever I've filmed any videos in England and come across an Irish person, male or female, the top comment I've always gotten on every video I've filmed there has been "to shit all over England from top to bottom." | BG42: 1. Reproduction | BH42: Direct Translation | BI42: NO | BL42: Every time I’ve filmed a video in England and run into an Irishman or an Irishwoman, the star comment that they’ve always given me in all the videos I’ve filmed there has been to shit all over the dead of England from top to bottom. | BM42: 1. Reproduction | BN42: Direct Translation | BO42: NO | BR42: Whenever I've recorded any video in England and I've caught an Irishman or Irishwoman, the star comment that they've always let me off in all the videos I've recorded there has been to curse the English from top to bottom. | BS42: 4. Creative Shifts | BT42: Abstraction – Superordinate Term | BU42: NO | BX42: Whenever I've recorded any video in England and I've caught an Irishman or Irishwoman, the star comment that they've always let me off in all the videos I've recorded there has been to curse the English from top to bottom. | BY42: 4. Creative Shifts | BZ42: Abstraction – Superordinate Term | CA42: NO | CD42: Whenever I've filmed any videos in England and I've caught an Irish person, the star comment that they've always let slip in all the videos I've filmed there has been to curse the English from top to bottom. | CE42: 4. Creative Shifts | CF42: Abstraction – Superordinate Term | CG42: NO | CJ42: Whenever I've recorded any video in England and I've caught an Irishman or Irishwoman, the star comment that they've always let me off in all the videos I've recorded there has been to curse the English from top to bottom. | CK42: 4. Creative Shifts | CL42: Abstraction – Superordinate Term | CM42: NO | CP42: Whenever I've recorded any video in England and I've caught an Irishman or Irishwoman, the star comment that they've always let me off in all the videos I've recorded there has been to curse the English from top to bottom. | CQ42: 4. Creative Shifts | CR42: Abstraction – Superordinate Term | CS42: NO
