Workbook
Name CreativeShifts: Lists!$E$1:$E$7
Name Errors: Lists!$D$1
Name Omissions: Lists!$C$1:$C$2
Name Reproduction: Lists!$B$1:$B$4

Sheet Lists
A1: 1. Reproduction | B1: Retention | C1: Creative Omission | D1: Error | E1: Abstraction – Superordinate Term | G1: 1. Reproduction | H1: Reproduction
A2: 2. Omissions | B2: Specification | C2: Shortcut Solution | E2: Abstraction – Paraphrase | G2: 2. Omissions | H2: Omissions
A3: 3. Errors | B3: Direct Translation | E3: Concretisation – Addition | G3: 3. Errors | H3: Errors
A4: 4. Creative Shifts | B4: Official Translation | E4: Concretisation – Completion | G4: 4. Creative Shifts | H4: CreativeShifts
E5: Modification – Cultural
E6: Modification – Situational
E7: Modification – Historical

Sheet Dashboard
B1: EVALUATION DASHBOARD — Category Distribution (4 Models × 5 Prompts)
B3: ℹ Fill dropdowns in the Evaluation sheet — counts update here automatically.
B5: Model A - Translategemma
B6: Prompt | C6: Reproduction | D6: Omissions | E6: Errors | F6: Creative Shifts | G6: Total | H6: % Done
B7: Baseline | C7: =COUNTIF(Evaluation!I3:I202,"1. Reproduction") -> 82 | D7: =COUNTIF(Evaluation!I3:I202,"2. Omissions") -> 16 | E7: =COUNTIF(Evaluation!I3:I202,"3. Errors") -> 22 | F7: =COUNTIF(Evaluation!I3:I202,"4. Creative Shifts") -> 80 | G7: =COUNTIF(Evaluation!I3:I202,"<>") -> 200 | H7: =IFERROR(G7/200,"") -> 1
B8: Few-shot 1 | C8: =COUNTIF(Evaluation!O3:O202,"1. Reproduction") -> 101 | D8: =COUNTIF(Evaluation!O3:O202,"2. Omissions") -> 14 | E8: =COUNTIF(Evaluation!O3:O202,"3. Errors") -> 24 | F8: =COUNTIF(Evaluation!O3:O202,"4. Creative Shifts") -> 61 | G8: =COUNTIF(Evaluation!O3:O202,"<>") -> 200 | H8: =IFERROR(G8/200,"") -> 1
B9: Few-shot 2 | C9: =COUNTIF(Evaluation!U3:U202,"1. Reproduction") -> 112 | D9: =COUNTIF(Evaluation!U3:U202,"2. Omissions") -> 11 | E9: =COUNTIF(Evaluation!U3:U202,"3. Errors") -> 23 | F9: =COUNTIF(Evaluation!U3:U202,"4. Creative Shifts") -> 54 | G9: =COUNTIF(Evaluation!U3:U202,"<>") -> 200 | H9: =IFERROR(G9/200,"") -> 1
B10: CoT 1 | C10: =COUNTIF(Evaluation!AA3:AA202,"1. Reproduction") -> 83 | D10: =COUNTIF(Evaluation!AA3:AA202,"2. Omissions") -> 13 | E10: =COUNTIF(Evaluation!AA3:AA202,"3. Errors") -> 26 | F10: =COUNTIF(Evaluation!AA3:AA202,"4. Creative Shifts") -> 78 | G10: =COUNTIF(Evaluation!AA3:AA202,"<>") -> 200 | H10: =IFERROR(G10/200,"") -> 1
B11: CoT 2 | C11: =COUNTIF(Evaluation!AG3:AG202,"1. Reproduction") -> 82 | D11: =COUNTIF(Evaluation!AG3:AG202,"2. Omissions") -> 19 | E11: =COUNTIF(Evaluation!AG3:AG202,"3. Errors") -> 29 | F11: =COUNTIF(Evaluation!AG3:AG202,"4. Creative Shifts") -> 70 | G11: =COUNTIF(Evaluation!AG3:AG202,"<>") -> 200 | H11: =IFERROR(G11/200,"") -> 1
B14: Model B - Qwen
B15: Prompt | C15: Reproduction | D15: Omissions | E15: Errors | F15: Creative Shifts | G15: Total | H15: % Done
B16: Baseline | C16: =COUNTIF(Evaluation!AM3:AM202,"1. Reproduction") -> 149 | D16: =COUNTIF(Evaluation!AM3:AM202,"2. Omissions") -> 1 | E16: =COUNTIF(Evaluation!AM3:AM202,"3. Errors") -> 29 | F16: =COUNTIF(Evaluation!AM3:AM202,"4. Creative Shifts") -> 21 | G16: =COUNTIF(Evaluation!AM3:AM202,"<>") -> 200 | H16: =IFERROR(G16/200,"") -> 1
B17: Few-shot 1 | C17: =COUNTIF(Evaluation!AS3:AS202,"1. Reproduction") -> 161 | D17: =COUNTIF(Evaluation!AS3:AS202,"2. Omissions") -> 0 | E17: =COUNTIF(Evaluation!AS3:AS202,"3. Errors") -> 23 | F17: =COUNTIF(Evaluation!AS3:AS202,"4. Creative Shifts") -> 16 | G17: =COUNTIF(Evaluation!AS3:AS202,"<>") -> 200 | H17: =IFERROR(G17/200,"") -> 1
B18: Few-shot 2 | C18: =COUNTIF(Evaluation!AY3:AY202,"1. Reproduction") -> 161 | D18: =COUNTIF(Evaluation!AY3:AY202,"2. Omissions") -> 1 | E18: =COUNTIF(Evaluation!AY3:AY202,"3. Errors") -> 23 | F18: =COUNTIF(Evaluation!AY3:AY202,"4. Creative Shifts") -> 15 | G18: =COUNTIF(Evaluation!AY3:AY202,"<>") -> 200 | H18: =IFERROR(G18/200,"") -> 1
B19: CoT 1 | C19: =COUNTIF(Evaluation!BE3:BE202,"1. Reproduction") -> 160 | D19: =COUNTIF(Evaluation!BE3:BE202,"2. Omissions") -> 0 | E19: =COUNTIF(Evaluation!BE3:BE202,"3. Errors") -> 25 | F19: =COUNTIF(Evaluation!BE3:BE202,"4. Creative Shifts") -> 15 | G19: =COUNTIF(Evaluation!BE3:BE202,"<>") -> 200 | H19: =IFERROR(G19/200,"") -> 1
B20: CoT 2 | C20: =COUNTIF(Evaluation!BK3:BK202,"1. Reproduction") -> 150 | D20: =COUNTIF(Evaluation!BK3:BK202,"2. Omissions") -> 0 | E20: =COUNTIF(Evaluation!BK3:BK202,"3. Errors") -> 34 | F20: =COUNTIF(Evaluation!BK3:BK202,"4. Creative Shifts") -> 16 | G20: =COUNTIF(Evaluation!BK3:BK202,"<>") -> 200 | H20: =IFERROR(G20/200,"") -> 1
B23: Model C - Salamandra
B24: Prompt | C24: Reproduction | D24: Omissions | E24: Errors | F24: Creative Shifts | G24: Total | H24: % Done
B25: Baseline | C25: =COUNTIF(Evaluation!BQ3:BQ202,"1. Reproduction") -> 162 | D25: =COUNTIF(Evaluation!BQ3:BQ202,"2. Omissions") -> 2 | E25: =COUNTIF(Evaluation!BQ3:BQ202,"3. Errors") -> 12 | F25: =COUNTIF(Evaluation!BQ3:BQ202,"4. Creative Shifts") -> 24 | G25: =COUNTIF(Evaluation!BQ3:BQ202,"<>") -> 200 | H25: =IFERROR(G25/200,"") -> 1
B26: Few-shot 1 | C26: =COUNTIF(Evaluation!BW3:BW202,"1. Reproduction") -> 164 | D26: =COUNTIF(Evaluation!BW3:BW202,"2. Omissions") -> 2 | E26: =COUNTIF(Evaluation!BW3:BW202,"3. Errors") -> 14 | F26: =COUNTIF(Evaluation!BW3:BW202,"4. Creative Shifts") -> 20 | G26: =COUNTIF(Evaluation!BW3:BW202,"<>") -> 200 | H26: =IFERROR(G26/200,"") -> 1
B27: Few-shot 2 | C27: =COUNTIF(Evaluation!CC3:CC202,"1. Reproduction") -> 163 | D27: =COUNTIF(Evaluation!CC3:CC202,"2. Omissions") -> 1 | E27: =COUNTIF(Evaluation!CC3:CC202,"3. Errors") -> 17 | F27: =COUNTIF(Evaluation!CC3:CC202,"4. Creative Shifts") -> 19 | G27: =COUNTIF(Evaluation!CC3:CC202,"<>") -> 200 | H27: =IFERROR(G27/200,"") -> 1
B28: CoT 1 | C28: =COUNTIF(Evaluation!CI3:CI202,"1. Reproduction") -> 159 | D28: =COUNTIF(Evaluation!CI3:CI202,"2. Omissions") -> 3 | E28: =COUNTIF(Evaluation!CI3:CI202,"3. Errors") -> 15 | F28: =COUNTIF(Evaluation!CI3:CI202,"4. Creative Shifts") -> 23 | G28: =COUNTIF(Evaluation!CI3:CI202,"<>") -> 200 | H28: =IFERROR(G28/200,"") -> 1
B29: CoT 2 | C29: =COUNTIF(Evaluation!CO3:CO202,"1. Reproduction") -> 162 | D29: =COUNTIF(Evaluation!CO3:CO202,"2. Omissions") -> 1 | E29: =COUNTIF(Evaluation!CO3:CO202,"3. Errors") -> 17 | F29: =COUNTIF(Evaluation!CO3:CO202,"4. Creative Shifts") -> 20 | G29: =COUNTIF(Evaluation!CO3:CO202,"<>") -> 200 | H29: =IFERROR(G29/200,"") -> 1
B32: Model D
B33: Prompt | C33: Reproduction | D33: Omissions | E33: Errors | F33: Creative Shifts | G33: Total | H33: % Done
B34: Baseline | C34: =COUNTIF(Evaluation!#REF!,"1. Reproduction") -> #REF! | D34: =COUNTIF(Evaluation!#REF!,"2. Omissions") -> #REF! | E34: =COUNTIF(Evaluation!#REF!,"3. Errors") -> #REF! | F34: =COUNTIF(Evaluation!#REF!,"4. Creative Shifts") -> #REF! | G34: =COUNTIF(Evaluation!#REF!,"<>") -> #REF! | H34: =IFERROR(G34/200,"")
B35: Few-shot 1 | C35: =COUNTIF(Evaluation!#REF!,"1. Reproduction") -> #REF! | D35: =COUNTIF(Evaluation!#REF!,"2. Omissions") -> #REF! | E35: =COUNTIF(Evaluation!#REF!,"3. Errors") -> #REF! | F35: =COUNTIF(Evaluation!#REF!,"4. Creative Shifts") -> #REF! | G35: =COUNTIF(Evaluation!#REF!,"<>") -> #REF! | H35: =IFERROR(G35/200,"")
B36: Few-shot 2 | C36: =COUNTIF(Evaluation!#REF!,"1. Reproduction") -> #REF! | D36: =COUNTIF(Evaluation!#REF!,"2. Omissions") -> #REF! | E36: =COUNTIF(Evaluation!#REF!,"3. Errors") -> #REF! | F36: =COUNTIF(Evaluation!#REF!,"4. Creative Shifts") -> #REF! | G36: =COUNTIF(Evaluation!#REF!,"<>") -> #REF! | H36: =IFERROR(G36/200,"")
B37: CoT 1 | C37: =COUNTIF(Evaluation!#REF!,"1. Reproduction") -> #REF! | D37: =COUNTIF(Evaluation!#REF!,"2. Omissions") -> #REF! | E37: =COUNTIF(Evaluation!#REF!,"3. Errors") -> #REF! | F37: =COUNTIF(Evaluation!#REF!,"4. Creative Shifts") -> #REF! | G37: =COUNTIF(Evaluation!#REF!,"<>") -> #REF! | H37: =IFERROR(G37/200,"")
B38: CoT 2 | C38: =COUNTIF(Evaluation!#REF!,"1. Reproduction") -> #REF! | D38: =COUNTIF(Evaluation!#REF!,"2. Omissions") -> #REF! | E38: =COUNTIF(Evaluation!#REF!,"3. Errors") -> #REF! | F38: =COUNTIF(Evaluation!#REF!,"4. Creative Shifts") -> #REF! | G38: =COUNTIF(Evaluation!#REF!,"<>") -> #REF! | H38: =IFERROR(G38/200,"")

Sheet Evaluation
H1: Model A - TranslateGemma | AL1: Model B - Qwen | BP1: Model C - Salamandra
A2: text_previous | B2: text_analyzed | C2: text_after | D2: text_analyzed | E2: macrocategory | F2: subcategory_num | G2: subcategory | H2: translation_translategemma_baseline | I2: Baseline ▼ Category | J2: Baseline ▼ Subcategory | K2: Mantains informal register? | L2: Intensity of informality | M2: Baseline Comments | N2: translation_translategemma_fewshot1 | O2: Few-shot 1 ▼ Category | P2: Few-shot 1 ▼ Subcategory | Q2: Mantains informal register? | R2: Intensity of informality | S2: Few-shot 1 Comments | T2: translation_translategemma_fewshot2 | U2: Few-shot 2 ▼ Category | V2: Few-shot 2 ▼ Subcategory | W2: Mantains informal register? | X2: Intensity of informality | Y2: Few-shot 2 Comments | Z2: translation_translategemma_CoT1 | AA2: CoT 1 ▼ Category | AB2: CoT 1 ▼ Subcategory | AC2: Mantains informal register? | AD2: Intensity of informality | AE2: CoT 1 Comments | AF2: translation_translategemma_CoT2 | AG2: CoT 2 ▼ Category | AH2: CoT 2 ▼ Subcategory | AI2: Mantains informal register? | AJ2: Intensity of informality | AK2: CoT 2 Comments | AL2: translation_qwen_baseline | AM2: Baseline ▼ Category | AN2: Baseline ▼ Subcategory | AO2: Mantains informal register? | AP2: Intensity of informality | AQ2: Baseline Comments | AR2: translation_qwen_fewshot1 | AS2: Few-shot 1 ▼ Category | AT2: Few-shot 1 ▼ Subcategory | AU2: Mantains informal register? | AV2: Intensity of informality | AW2: Few-shot 1 Comments | AX2: translation_qwen_fewshot2 | AY2: Few-shot 2 ▼ Category | AZ2: Few-shot 2 ▼ Subcategory | BA2: Mantains informal register? | BB2: Intensity of informality | BC2: Few-shot 2 Comments | BD2: translation_qwen_CoT1 | BE2: CoT 1 ▼ Category | BF2: CoT 1 ▼ Subcategory | BG2: Mantains informal register? | BH2: Intensity of informality | BI2: CoT 1 Comments | BJ2: translation_qwen_CoT2 | BK2: CoT 2 ▼ Category | BL2: CoT 2 ▼ Subcategory | BM2: Mantains informal register? | BN2: Intensity of informality | BO2: CoT 2 Comments | BP2: translation_salam_baseline | BQ2: Baseline ▼ Category | BR2: Baseline ▼ Subcategory | BS2: Mantains informal register? | BT2: Intensity of informality | BU2: Baseline Comments | BV2: translation_salam_fewshot1 | BW2: Few-shot 1 ▼ Category | BX2: Few-shot 1 ▼ Subcategory | BY2: Mantains informal register? | BZ2: Intensity of informality | CA2: Few-shot 1 Comments | CB2: translation_salam_fewshot2 | CC2: Few-shot 2 ▼ Category | CD2: Few-shot 2 ▼ Subcategory | CE2: Mantains informal register? | CF2: Intensity of informality | CG2: Few-shot 2 Comments | CH2: translation_salam_CoT1 | CI2: CoT 1 ▼ Category | CJ2: CoT 1 ▼ Subcategory | CK2: Mantains informal register? | CL2: Intensity of informality | CM2: CoT 1 Comments | CN2: translation_salam_CoT2 | CO2: CoT 2 ▼ Category | CP2: CoT 2 ▼ Subcategory | CQ2: Mantains informal register? | CR2: Intensity of informality | CS2: CoT 2 Comments
A3: [empieza tema de conversación] | B3: O sigui, jo hi ha gent també i de vegades ja penso, hòstia, gordi, i si calles la putíssima boca. En plan, ostres, nano, per què no calles, loca? | C3: És que també té moltes parts negatives d'això i té una cosa, en plan, jo tampoc considero que sigui superpolèmica, en plan, jo, per exemple, soc molt cordial, no em mullo, així com tu sí que sento que dius opinions com molt polèmiques, jo amb això, gens. | D3: O sigui, jo hi ha gent també i de vegades ja penso, hòstia, gordi, i si calles la putíssima boca. En plan, ostres, nano, per què no calles, loca? | E3: 3. Pragmatics and Discourse | F3: 3.2 | G3: Familiar address or vocatives | H3: Mira, a veces hay gente que me saca de quicio, y pienso, "¡hostia!, ¡qué pesado!, ¿por qué no te callas?". En serio, a veces pienso, "chico/chica, ¿por qué no te puedes quedar callado/a?". | I3: 4. Creative Shifts | J3: Abstraction – Superordinate Term | K3: NO | N3: O sea, hay gente que también opina así, y a veces pienso, joder, ¿y si callaras de una vez? En plan, oye, ¿por qué no te callas, loca? | O3: 2. Omissions | P3: Shortcut Solution | Q3: NO | T3: O sea, también hay gente que opina, y a veces pienso, ¡hostia, si pudieras callarte la boca! O sea, ¿pero por qué no te callas, loca? | U3: 2. Omissions | V3: Shortcut Solution | W3: NO | Z3: O sea, hay gente que también opina así, y a veces pienso, ¡madre mía!, ¿por qué no te callas de una vez? En plan, ¡ostras!, ¿por qué no te callas, loca? | AA3: 2. Omissions | AB3: Shortcut Solution | AC3: NO | AF3: O sea, hay gente que también opina así, y a veces pienso, ¡madre mía!, ¿por qué no te callas de una vez? En plan, ¿pero qué dices, tonto? ¿Por qué no te callas, loca? | AG3: 2. Omissions | AH3: Shortcut Solution | AI3: NO | AL3: O sigui, hay gente también, y a veces ya pienso, joder, gordo, y si callaras la puta boca. En plan, mierda, chaval, ¿por qué no callas, loca? | AM3: 4. Creative Shifts | AN3: Abstraction – Superordinate Term | AO3: YES | AP3: LESS | AR3: O sea, hay gente también y a veces ya pienso, hóstia, gordo, y si callas la puta boca. En plan, ostras, nano, por qué no callas, loca? | AS3: 1. Reproduction | AT3: Direct Translation | AU3: YES | AV3: SAME | AX3: O sea, yo también hay gente y de vez en cuando ya pienso, joder, gordo, y si callas la puta boca. En plan, mierda, tío, por qué no callas, loca? | AY3: 4. Creative Shifts | AZ3: Modification – Cultural | BA3: YES | BB3: LESS | BD3: O sea, yo también hay gente, y a veces ya pienso, joder, gordo, y si callaras la puta boca. En plan, mierda, tío, ¿por qué no callas, loca? | BE3: 4. Creative Shifts | BF3: Modification – Cultural | BG3: YES | BH3: LESS | BJ3: Bueno, también hay gente, y a veces ya pienso, mierda, gordo, y si callaras la puta boca. En plan, joder, tío, ¿por qué no te callas, loca? | BK3: 4. Creative Shifts | BL3: Modification – Cultural | BM3: YES | BN3: LESS | BP3: O sea, yo también hay gente y a veces ya pienso, hostia, gordi, y si callas la puta boca. En plan, ¡ostras, tío, por qué no callas, loca? | BQ3: 4. Creative Shifts | BR3: Modification – Cultural | BS3: YES | BT3: LESS | BV3: O sea, yo también hay gente y a veces ya pienso, hostia, gordi, y si callas la puta boca. En plan, joder, tío, por qué no callas, loca? | BW3: 4. Creative Shifts | BX3: Modification – Cultural | BY3: YES | BZ3: LESS | CB3: O sea, yo también hay gente y a veces ya pienso, hostia, gordi, y si callas la puta boca. En plan, joder, tío, por qué no callas, loca? | CC3: 4. Creative Shifts | CD3: Modification – Cultural | CE3: YES | CF3: LESS | CH3: O sea, yo también hay gente y a veces ya pienso, hostia, gordi, y si callas la puta boca. En plan, ¡ostras, tío, por qué no callas, loca? | CI3: 4. Creative Shifts | CJ3: Modification – Cultural | CK3: YES | CL3: LESS | CN3: O sea, yo hay gente también y a veces ya pienso, hostia, gordi, y si callas la putísima boca. En plan, ostras, nano, ¿por qué no callas, loca? | CO3: 1. Reproduction | CP3: Direct Translation | CQ3: YES | CR3: SAME
A4: [empieza tema de conversación] | B4: A tot això, a tu realment te la suda molt el que pensi la resta? És que no ho sé, perquè jo et diria que no, que no m'importa gens el que pensi la resta, i de fet crec que és una cosa que m'ha caracteritzat des de sempre, i en èpoques molt difícils com l'adolescència, etcètera, jo també m'he mantingut molt ferma amb qui soc jo | C4: Sempre he fet una mica el que m'ha vingut de gust, encara que fos una bogeria, però després penso que és mentida, que segur que penso tot el rato en realitat, perquè al final és que vivim en societat, és que si realment no penses en els altres, llavors ets un d'aquests bojos que va descalços i despullat i cridant pel carrer. | D4: A tot això, a tu realment te la suda molt el que pensi la resta? És que no ho sé, perquè jo et diria que no, que no m'importa gens el que pensi la resta, i de fet crec que és una cosa que m'ha caracteritzat des de sempre, i en èpoques molt difícils com l'adolescència, etcètera, jo també m'he mantingut molt ferma amb qui soc jo | E4: 1. Lexicon and Vocabulary | F4: 1.2 | G4: Colloquial lexicon and slang | H4: En todo esto, ¿a ti realmente te importa mucho lo que piense el resto? Es que no lo sé, porque yo te diría que no, que no me importa en absoluto lo que piense la gente, y de hecho creo que es algo que me ha caracterizado siempre, y en épocas muy difíciles como la adolescencia, etc., yo también me he mantenido muy firme con lo que soy. | I4: 4. Creative Shifts | J4: Abstraction – Paraphrase | K4: NO | N4: "Dicho esto, ¿a ti realmente te importa mucho lo que piense el resto? Es que no lo sé, porque yo te diría que no, que no me importa nada lo que piense la gente, y de hecho creo que es algo que me ha caracterizado siempre, y en épocas muy difíciles como la adolescencia, etcétera, yo también me he mantenido muy firme con quien soy." | O4: 4. Creative Shifts | P4: Abstraction – Paraphrase | Q4: NO | T4: A todo esto, ¿a ti realmente te importa mucho lo que piense el resto? Es que no lo sé, porque yo te diría que no, que no me importa nada lo que piense el resto, y de hecho creo que es algo que me ha caracterizado desde siempre, y en épocas muy difíciles como la adolescencia, etc., yo también me he mantenido muy firme con quien soy. | U4: 4. Creative Shifts | V4: Abstraction – Paraphrase | W4: NO | Z4: De todo esto, ¿a ti realmente te importa mucho lo que piense el resto? Es que no lo sé, porque yo te diría que no, que no me importa en absoluto lo que piense la gente, y de hecho, creo que es algo que me ha caracterizado siempre, y en épocas muy difíciles como la adolescencia, etcétera, yo también me he mantenido muy firme con lo que soy. | AA4: 4. Creative Shifts | AB4: Abstraction – Paraphrase | AC4: NO | AF4: A todo esto, ¿realmente te da igual lo que piense el resto? Es que no lo sé, porque yo te diría que no, que no me importa en absoluto lo que piense la gente, y de hecho creo que es algo que me ha caracterizado siempre, y en épocas muy difíciles como la adolescencia, etcétera, yo también me he mantenido muy firme con quien soy. | AG4: 4. Creative Shifts | AH4: Abstraction – Paraphrase | AI4: NO | AL4: A todo esto, ¿a ti realmente te importa mucho lo que piensen los demás? Es que no lo sé, porque yo te diría que no, que no me importa nada lo que piensen los demás, y de hecho creo que es algo que me ha caracterizado siempre, y en épocas muy difíciles como la adolescencia, etcétera, yo también me he mantenido muy firme con quién soy. | AM4: 4. Creative Shifts | AN4: Abstraction – Paraphrase | AO4: NO | AR4: A todo esto, a ti realmente te importa mucho lo que piense el resto? Es que no lo sé, porque yo te diría que no, que no me importa nada lo que piense el resto, y de hecho creo que es algo que me ha caracterizado siempre, y en épocas muy difíciles como la adolescencia, etcétera, yo también me he mantenido muy firme con quién soy. | AS4: 4. Creative Shifts | AT4: Abstraction – Paraphrase | AU4: NO | AX4: A todo esto, a ti realmente te importa mucho lo que piense el resto? Es que no lo sé, porque yo te diría que no, que no me importa nada lo que piense el resto, y de hecho creo que es algo que me ha caracterizado siempre, y en épocas muy difíciles como la adolescencia, etcétera, yo también me he mantenido muy firme con quién soy. | AY4: 4. Creative Shifts | AZ4: Abstraction – Paraphrase | BA4: NO | BD4: A todo esto, ¿a ti realmente te importa mucho lo que piense el resto? Es que no lo sé, porque yo te diría que no, que no me importa nada lo que piense el resto, y de hecho creo que es algo que me ha caracterizado siempre, y en épocas muy difíciles como la adolescencia, etcétera, yo también me he mantenido muy firme con quién soy. | BE4: 4. Creative Shifts | BF4: Abstraction – Paraphrase | BG4: NO | BJ4: A todo esto, ¿a ti realmente te importa mucho lo que piensen los demás? La verdad es que no lo sé, porque yo te diría que no, que no me importa nada lo que piensen los demás, y de hecho creo que es algo que me ha caracterizado siempre, y en épocas muy difíciles como la adolescencia, etcétera, también he estado muy firme con respecto a quién soy yo. | BK4: 4. Creative Shifts | BL4: Abstraction – Paraphrase | BM4: NO | BP4: A todo esto, ¿a ti realmente te la suda mucho lo que piensen los demás? Porque yo te diría que no, que no me importa nada lo que piensen los demás, y de hecho creo que es algo que me ha caracterizado desde siempre, y en épocas muy difíciles como la adolescencia, etcétera, yo también me he mantenido muy firme con quien soy | BQ4: 1. Reproduction | BR4: Direct Translation | BS4: YES | BT4: SAME | BV4: A todo esto, ¿a ti realmente te la suda mucho lo que piense el resto? Es que no sé, porque yo te diría que no, que no me importa nada lo que piense el resto, y de hecho creo que es algo que me ha caracterizado desde siempre, y en épocas muy difíciles como la adolescencia, etcétera, yo también me he mantenido muy firme con quien soy yo | BW4: 1. Reproduction | BX4: Direct Translation | BY4: YES | BZ4: SAME | CB4: A todo esto, ¿a ti realmente te la suda mucho lo que piense el resto? Es que no sé, porque yo te diría que no, que no me importa nada lo que piense el resto, y de hecho creo que es algo que me ha caracterizado desde siempre, y en épocas muy difíciles como la adolescencia, etcétera, yo también me he mantenido muy firme con quien soy yo | CC4: 1. Reproduction | CD4: Direct Translation | CE4: YES | CF4: SAME | CH4: A todo esto, ¿a ti realmente te la suda mucho lo que piensen los demás? Porque yo te diría que no, que no me importa nada lo que piensen los demás, y de hecho creo que es algo que me ha caracterizado desde siempre, y en épocas muy difíciles como la adolescencia, etcétera, yo también me he mantenido muy firme con quien soy Siempre he hecho un poco lo que me ha venido en gana, aunque fuera una locura, pero luego pienso que es mentira, que seguro que pienso todo el rato en realidad, porque al final es que vivimos en sociedad, es que si realmente no piensas en los demás, entonces eres uno de esos locos que va descalzo y desnudo gritando por la calle. | CI4: 1. Reproduction | CJ4: Direct Translation | CK4: YES | CL4: SAME | CN4: A todo esto, ¿a ti realmente te la suda mucho lo que piensen los demás? Es que no sé, porque yo te diría que no, que no me importa nada lo que piensen los demás, y de hecho creo que es algo que me ha caracterizado desde siempre, y en épocas muy difíciles como la adolescencia, etcétera, yo también me he mantenido muy firme con quien soy. | CO4: 1. Reproduction | CP4: Direct Translation | CQ4: YES | CR4: SAME
A5: [empieza tema de conversación] | B5: Jo sóc molt desconfiada, però molt desconfiada. Jo pense que te me l'estan a punt de fotre per l'esquena. Tot el rato. | C5: Mira, per exemple, el Marc Andreu, jo encara no critico amb ell per WhatsApp, hem de quedar presencialment per criticar, perquè no vull que quedi constància la meva criticada. Imagina la desconfiada que soc. | D5: Jo sóc molt desconfiada, però molt desconfiada. Jo pense que te me l'estan a punt de fotre per l'esquena. Tot el rato. | E5: 1. Lexicon and Vocabulary | F5: 1.2 | G5: Colloquial lexicon and slang | H5: Soy muy desconfiada, pero muchísimo. Creo que me están a punto de apuñalar por la espalda. Todo el rato. | I5: 4. Creative Shifts | J5: Modification – Situational | K5: YES | L5: LESS | N5: Soy muy desconfiada, la verdad. Creo que me están preparando una jugada por la espalda. Todo el rato. | O5: 4. Creative Shifts | P5: Modification – Situational | Q5: YES | R5: LESS | T5: Yo soy muy desconfiada, pero muchísimo. Yo pienso que te están a punto de clavar una puñalada por la espalda. Todo el rato. | U5: 4. Creative Shifts | V5: Modification – Situational | W5: YES | X5: SAME | Z5: Soy muy desconfiada, la verdad. Creo que me están tendiendo una trampa constantemente. | AA5: 4. Creative Shifts | AB5: Abstraction – Paraphrase | AC5: NO | AF5: Yo soy muy desconfiada, pero muchísimo. Yo pienso que me están intentando engañar a mis espaldas. Todo el rato. | AG5: 4. Creative Shifts | AH5: Abstraction – Paraphrase | AI5: NO | AL5: Estoy muy desconfiada, pero muy desconfiada. Creo que me van a pillar por la espalda. Todo el rato. | AM5: 4. Creative Shifts | AN5: Modification – Situational | AO5: NO | AR5: Yo soy muy desconfiada, pero muy desconfiada. Yo pienso que me van a hacer una trampa por la espalda. Todo el rato. | AS5: 4. Creative Shifts | AT5: Abstraction – Paraphrase | AU5: NO | AX5: Yo soy muy desconfiada, pero muy desconfiada. Yo pienso que te me lo están a punto de liar por la espalda. Todo el rato. | AY5: 4. Creative Shifts | AZ5: Modification – Situational | BA5: YES | BB5: LESS | BD5: Yo soy muy desconfiada, pero muy desconfiada. Yo pienso que te me lo están a punto de liar por la espalda. Todo el rato. | BE5: 4. Creative Shifts | BF5: Modification – Situational | BG5: YES | BH5: LESS | BJ5: Soy muy desconfiada, pero muy desconfiada. Creo que me están a punto de liar por la espalda todo el rato. | BK5: 4. Creative Shifts | BL5: Modification – Situational | BM5: YES | BN5: LESS | BP5: Yo soy muy desconfiada, pero muy desconfiada. Yo pienso que te la están a punto de meter por la espalda todo el rato. | BQ5: 4. Creative Shifts | BR5: Modification – Situational | BS5: YES | BT5: LESS | BV5: Yo soy muy desconfiada, pero muy desconfiada. Yo pienso que te me la están a punto de meter por la espalda. Todo el rato. | BW5: 4. Creative Shifts | BX5: Modification – Situational | BY5: YES | BZ5: LESS | CB5: Yo soy muy desconfiada, pero muy desconfiada. Yo pienso que te me la están a punto de meter por la espalda. Todo el rato. | CC5: 4. Creative Shifts | CD5: Modification – Situational | CE5: YES | CF5: LESS | CH5: Yo soy muy desconfiada, pero muy desconfiada. Yo pienso que te la están a punto de meter por la espalda. Todo el rato. | CI5: 4. Creative Shifts | CJ5: Modification – Situational | CK5: YES | CL5: LESS | CN5: Yo soy muy desconfiada, pero muy desconfiada. Yo pienso que te la están a punto de meter por la espalda. Todo el rato. | CO5: 4. Creative Shifts | CP5: Modification – Situational | CQ5: YES | CR5: LESS
A6: [empieza tema de conversación] | B6: O sigui, és que realment me vaig començar a fer coneguda perquè ho vaig deixar amb la meva parella i em vaig tornar loca. En plan, uau, he perdut O sigui, clar, és que jo en aquell moment se m'acabava el puto món, t'ho juro. I ara ho veig en perspectiva i dic, amor, relaxat. | C6: Però és normal, és que hi ha moment quan ho deixes Hi ha gent que diu, és que em torno boja. O sigui, una ruptura sempre és un moment de loca. | D6: O sigui, és que realment me vaig començar a fer coneguda perquè ho vaig deixar amb la meva parella i em vaig tornar loca. En plan, uau, he perdut O sigui, clar, és que jo en aquell moment se m'acabava el puto món, t'ho juro. I ara ho veig en perspectiva i dic, amor, relaxat. | E6: 4. Register and Tone | F6: 4.1 | G6: Hyperbole and exaggeration | H6: O sea, la verdad es que empecé a darme a conocer cuando rompí con mi pareja y me volví loca. En plan, ¡uf!, lo perdí todo. O sea, claro, en ese momento, mi mundo se estaba viniendo abajo, te lo juro. Y ahora lo veo con perspectiva y digo, cariño, relájate. | I6: 4. Creative Shifts | J6: Abstraction – Paraphrase | K6: NO | N6: O sea, es que realmente empecé a darme a conocer porque rompí con mi pareja y me volví loca. En plan, ¡guau!, me vino todo encima. O sea, claro, es que yo en ese momento se me acababa el mundo, te lo juro. Y ahora lo veo con perspectiva y digo, "amor, relájate". | O6: 4. Creative Shifts | P6: Abstraction – Paraphrase | Q6: NO | T6: O sea, es que realmente empecé a darme a conocer porque rompí con mi pareja y me volví loca. En plan, vaya, me perdí... O sea, claro, es que en ese momento se me acababa el mundo, te lo juro. Y ahora lo veo en perspectiva y digo, amor, relájate. | U6: 4. Creative Shifts | V6: Abstraction – Paraphrase | W6: NO | Z6: O sea, en realidad empecé a darme a conocer cuando rompí con mi pareja y me volví loca. En plan, ¡guau!, me vino el mundo encima. O sea, claro, en ese momento, te juro, mi vida se estaba desmoronando. Y ahora lo veo con perspectiva y digo, cariño, relájate. | AA6: 4. Creative Shifts | AB6: Abstraction – Paraphrase | AC6: NO | AF6: O sea, en realidad empecé a darme a conocer porque rompí con mi pareja y me volví loca. En plan, ¡guau!, lo perdí todo. O sea, claro, en ese momento, mi mundo se estaba desmoronando, te lo juro. Y ahora lo veo con perspectiva y digo, "tranquilo, todo va a estar bien". | AG6: 4. Creative Shifts | AH6: Abstraction – Paraphrase | AI6: NO | AL6: O sigui, es que realmente me empecé a hacer famosa porque dejé a mi pareja y me volví loca. En plan, uau, perdí el culo, ¿sabes? O sea, claro, en ese momento me acababa el mundo, te lo juro. Y ahora lo veo en perspectiva y digo, amor, relájate. | AM6: 4. Creative Shifts | AN6: Abstraction – Superordinate Term | AO6: NO | AR6: O sea, es que realmente me empecé a hacer famosa porque lo dejé con mi pareja y me volví loca. En plan, uau, he perdido, o sea, claro, es que en aquel momento se me acababa el puto mundo, te lo juro. Y ahora lo veo en perspectiva y digo, amor, relájate. | AS6: 1. Reproduction | AT6: Direct Translation | AU6: YES | AV6: SAME | AX6: O sea, es que realmente me empecé a hacer conocida porque lo dejé con mi pareja y me volví loca. En plan, uau, he perdido O sea, claro, es que en ese momento se me acababa el puto mundo, te lo juro. Y ahora lo veo en perspectiva y digo, amor, relájate. | AY6: 1. Reproduction | AZ6: Direct Translation | BA6: YES | BB6: SAME | BD6: O sea, es que realmente me empecé a hacer conocida porque lo dejé con mi pareja y me volví loca. En plan, uau, he perdido O sea, claro, es que en ese momento se me acababa el puto mundo, te lo juro. Y ahora lo veo en perspectiva y digo, amor, relájate. | BE6: 1. Reproduction | BF6: Direct Translation | BG6: YES | BH6: SAME | BJ6: O sea, es que realmente me empecé a hacer famosa porque lo dejé con mi pareja y me volví loca. En plan, uau, he perdido, o sea, claro, es que en ese momento se me acababa el puto mundo, te lo juro. Y ahora lo veo en perspectiva y digo, amor, relájate. | BK6: 1. Reproduction | BL6: Direct Translation | BM6: YES | BN6: SAME | BP6: O sea, es que realmente me hice conocida porque lo dejé con mi pareja y me volví loca. En plan, uau, he perdido O sea, claro, es que yo en ese momento se me acababa el puto mundo, te lo juro. Y ahora lo veo en perspectiva y digo, amor, relájate. | BQ6: 1. Reproduction | BR6: Direct Translation | BS6: YES | BT6: SAME | BV6: O sea, es que realmente me hice conocida porque lo dejé con mi pareja y me volví loca. En plan, uau, he perdido O sea, claro, es que yo en ese momento se me acababa el puto mundo, te lo juro. Y ahora lo veo en perspectiva y digo, amor, relájate. | BW6: 1. Reproduction | BX6: Direct Translation | BY6: YES | BZ6: SAME | CB6: O sea, es que realmente me hice conocida porque lo dejé con mi pareja y me volví loca. En plan, uau, he perdido O sea, claro, es que yo en ese momento se me acababa el puto mundo, te lo juro. Y ahora lo veo en perspectiva y digo, amor, relájate. | CC6: 1. Reproduction | CD6: Direct Translation | CE6: YES | CF6: SAME | CH6: O sea, que realmente me hice conocida porque dejé a mi pareja y me volví loca. En plan, wow, he perdido O sea, claro, es que yo en ese momento se me acababa el puto mundo, te lo juro. Y ahora lo veo en perspectiva y digo, amor, relájate. | CI6: 1. Reproduction | CJ6: Direct Translation | CK6: YES | CL6: SAME | CN6: O sea, es que realmente me hice conocida porque lo dejé con mi pareja y me volví loca. En plan, uau, he perdido O sea, claro, es que yo en ese momento se me acababa el puto mundo, te lo juro. Y ahora lo veo en perspectiva y digo, amor, relájate. | CO6: 1. Reproduction | CP6: Direct Translation | CQ6: YES | CR6: SAME
A7: [empieza tema de conversación] | B7: És que, de fet, aquest és el primer meló que volia obrir de la solteria, que, clar, sembla que quan ets un home i estàs solter, és una solteria escollida, en plan, estic solter perquè vull, i si ets un lligón, a sobre ets el puto amo, però quan ets una noia i estàs soltera, ja és perquè ningú et vol, mai és soltera per voluntat pròpia, sempre la idea és estar soltera perquè algú té alguna tara i no la volen, i si a sobre ets una lligona, estàs desesperada. | C7: Llavors, clar, és que són 2 maneres de viure la solteria super diferent. | D7: És que, de fet, aquest és el primer meló que volia obrir de la solteria, que, clar, sembla que quan ets un home i estàs solter, és una solteria escollida, en plan, estic solter perquè vull, i si ets un lligón, a sobre ets el puto amo, però quan ets una noia i estàs soltera, ja és perquè ningú et vol, mai és soltera per voluntat pròpia, sempre la idea és estar soltera perquè algú té alguna tara i no la volen, i si a sobre ets una lligona, estàs desesperada. | E7: 1. Lexicon and Vocabulary | F7: 1.4 | G7: Idiomatic expressions and colloquial phraseology | H7: Es que, de hecho, este es el primer tema que quería tratar sobre la soltería, y claro, parece que cuando eres hombre y estás soltero, es una soltería elegida, o sea, estoy soltero porque quiero, y si eres atractivo, aún más, eres el dueño de tu vida. Pero cuando eres mujer y estás soltera, ya es porque nadie la quiere, nunca es soltera por propia voluntad, siempre la idea es que está soltera porque alguien tiene algún problema y no la quiere, y si encima eres atractiva, estás desesperada. | I7: 4. Creative Shifts | J7: Abstraction – Paraphrase | K7: NO | N7: Pues, de hecho, este es el primer tema que quería tratar sobre la soltería, que, claro, parece que cuando eres hombre y estás soltero, es una soltería elegida, como que estoy soltero porque quiero, y si además eres atractivo, eres el puto amo, pero cuando eres mujer y estás soltera, ya es porque nadie te quiere, nunca es soltería por voluntad propia, siempre la idea es estar soltera porque alguien tiene algún problema y no te quiere, y si además eres atractiva, estás desesperada. | O7: 4. Creative Shifts | P7: Abstraction – Paraphrase | Q7: NO | T7: Pues, de hecho, este es el primer melón que quería abrir sobre la soltería, que, claro, parece que cuando eres hombre y estás soltero, es una soltería elegida, vamos, estoy soltero porque quiero, y si eres un "ligón", encima eres el puto amo, pero cuando eres una chica y estás soltera, ya es porque nadie la quiere, nunca es soltera por voluntad propia, siempre la idea es estar soltera porque alguien tiene alguna tara y no la quieren, y si encima eres una "ligona", estás desesperada. | U7: 1. Reproduction | V7: Direct Translation | W7: YES | X7: SAME | Z7: Es que, de hecho, este es el primer tema que quería tratar sobre la soltería, y claro, parece que cuando eres hombre y estás soltero, es una soltería elegida, en plan, estoy soltero porque quiero, y si eres atractivo, encima eres el dueño de ti mismo, pero cuando eres mujer y estás soltera, ya es porque nadie te quiere, nunca es soltería por voluntad propia, siempre la idea es estar soltera porque alguien tiene algún problema y no la quiere, y si encima eres atractiva, estás desesperada. | AA7: 4. Creative Shifts | AB7: Abstraction – Paraphrase | AC7: NO | AF7: En realidad, este es el primer tema que quería abordar sobre la soltería, y es que, claro, parece que cuando eres hombre y estás soltero, es una soltería elegida, es decir, estás soltero porque quieres, y si eres atractivo, encima eres el dueño de tu vida. Pero cuando eres mujer y estás soltera, ya es porque nadie te quiere, nunca es soltería por voluntad propia, siempre la idea es que estás soltera porque alguien tiene algún problema y no te quiere, y si encima eres atractiva, estás desesperada. | AG7: 4. Creative Shifts | AH7: Abstraction – Paraphrase | AI7: NO | AL7: Pues, de hecho, este es el primer melo que quería abrir sobre la soltería, que, claro, parece que cuando eres un hombre y estás soltero, es una soltería elegida, en plan, estoy soltero porque quiero, y si además eres un ligue, encima eres el puto amo. Pero cuando eres una chica y estás soltera, ya es porque nadie te quiere, nunca es soltera por voluntad propia, siempre la idea es estar soltera porque alguien tiene alguna tara y no la quiere, y si encima eres una ligueona, estás desesperada. | AM7: 3. Errors | AO7: NO | AR7: Pues, de hecho, este es el primer meló que quería abrir de la soltería, que, claro, parece que cuando eres un hombre y estás soltero, es una soltería elegida, en plan, estoy soltero porque quiero, y si eres un ligue, a más es el puto amo, pero cuando eres una chica y estás soltera, ya es porque nadie te quiere, nunca es soltera por voluntad propia, siempre la idea es estar soltera porque alguien tiene alguna tara y no la quiere, y si a más eres una ligueona, estás desesperada. | AS7: 3. Errors | AU7: NO | AX7: Es que, de hecho, este es el primer melo que quería abrir de la soltería, que, claro, parece que cuando eres un hombre y estás soltero, es una soltería elegida, en plan, estoy soltero porque quiero, y si eres un ligón, a más, eres el puto amo, pero cuando eres una chica y estás soltera, ya es porque nadie te quiere, nunca es soltera por voluntad propia, siempre la idea es estar soltera porque alguien tiene alguna tara y no la quieren, y si a más eres una ligona, estás desesperada. | AY7: 3. Errors | BA7: NO | BD7: Claro, de hecho, este es el primer melo que quería abrir sobre la soltería, que, claro, parece que cuando eres un hombre y estás soltero, es una soltería elegida, en plan, estoy soltero porque quiero, y si eres un ligue, a más, eres el puto amo, pero cuando eres una chica y estás soltera, ya es porque nadie te quiere, nunca es soltera por voluntad propia, siempre la idea es estar soltera porque alguien tiene alguna tara y no la quiere, y si a más eres una ligueona, estás desesperada. | BE7: 3. Errors | BG7: NO | BJ7: Es que, de hecho, este es el primer melo que quería abrir de la soltería, que, claro, parece que cuando eres un hombre y estás soltero, es una soltería elegida, en plan, estoy soltero porque quiero, y si eres un ligón, a más, eres el puto amo, pero cuando eres una chica y estás soltera, ya es porque nadie te quiere, nunca es soltera por voluntad propia, siempre la idea es estar soltera porque alguien tiene alguna tara y no la quiere, y si a más eres una ligona, estás desesperada. | BK7: 3. Errors | BM7: NO | BP7: Es que, de hecho, este es el primer melón que quería abrir de la soltería, que, claro, parece que cuando eres un hombre y estás soltero, es una soltería elegida, en plan, estoy soltero porque quiero, y si eres un ligón, encima eres el puto amo, pero cuando eres una chica y estás soltera, ya es porque nadie te quiere, nunca es soltera por voluntad propia, siempre la idea es estar soltera porque alguien tiene algún defecto y no la quieren, y si encima eres una ligona, estás desesperada. | BQ7: 1. Reproduction | BR7: Direct Translation | BS7: YES | BT7: SAME | BV7: Es que, de hecho, este es el primer melón que quería abrir de la soltería, que, claro, parece que cuando eres un hombre y estás soltero, es una soltería elegida, en plan, estoy soltero porque quiero, y si eres un ligón, a sobre eres el puto amo, pero cuando eres una chica y estás soltera, ya es porque nadie te quiere, nunca es soltera por voluntad propia, siempre la idea es estar soltera porque alguien tiene algún defecto y no la quieren, y si encima eres una ligona, estás desesperada. | BW7: 1. Reproduction | BX7: Direct Translation | BY7: YES | BZ7: SAME | CB7: Es que, de hecho, este es el primer melón que quería abrir de la soltería, que, claro, parece que cuando eres un hombre y estás soltero, es una soltería elegida, en plan, estoy soltero porque quiero, y si eres un ligón, a sobre eres el puto amo, pero cuando eres una chica y estás soltera, ya es porque nadie te quiere, nunca es soltera por voluntad propia, siempre la idea es estar soltera porque alguien tiene algún defecto y no la quieren, y si encima eres una ligona, estás desesperada. | CC7: 1. Reproduction | CD7: Direct Translation | CE7: YES | CF7: SAME | CH7: Es que, de hecho, este es el primer melón que quería abrir de la soltería, que, claro, parece que cuando eres un hombre y estás soltero, es una soltería elegida, en plan, estoy soltero porque quiero, y si eres un ligón, encima eres el puto amo, pero cuando eres una chica y estás soltera, ya es porque nadie te quiere, nunca es soltera por voluntad propia, siempre la idea es estar soltera porque alguien tiene algún defecto y no la quieren, y si encima eres una ligona, estás desesperada. | CI7: 1. Reproduction | CJ7: Direct Translation | CK7: YES | CL7: SAME | CN7: Es que, de hecho, este es el primer melón que quería abrir de la soltería, que, claro, parece que cuando eres un hombre y estás soltero, es una soltería elegida, en plan, estoy soltero porque quiero, y si eres un ligón, a sobre eres el puto amo, pero cuando eres una chica y estás soltera, ya es porque nadie te quiere, nunca es soltera por voluntad propia, siempre la idea es estar soltera porque alguien tiene algún defecto y no la quieren, y si encima eres una ligona, estás desesperada. | CO7: 1. Reproduction | CP7: Direct Translation | CQ7: YES | CR7: SAME
A8: [empieza tema de conversación] | B8: Clar, però alhora és que vull dir, perdó, però ja no vull pas obrir una bandera lila, però a vegades com a tia és impossible fer-ho bé. Perquè si estàs soltera i no lligues, per a alguns ets d'autovalor, però per a alguns, quin és el teu fallo? Per què no estàs follant? En canvi, si estàs soltera i lligues molt, ets una guarra. Què faig? Mira, jo lo que trobo que hem de fer és lo que mos surti del xotxo, del cony, saps? | C8: Totalment. | D8: Clar, però alhora és que vull dir, perdó, però ja no vull pas obrir una bandera lila, però a vegades com a tia és impossible fer-ho bé. Perquè si estàs soltera i no lligues, per a alguns ets d'autovalor, però per a alguns, quin és el teu fallo? Per què no estàs follant? En canvi, si estàs soltera i lligues molt, ets una guarra. Què faig? Mira, jo lo que trobo que hem de fer és lo que mos surti del xotxo, del cony, saps? | E8: 4. Register and Tone | F8: 4.1 | G8: Hyperbole and exaggeration | H8: Mira, a ver, quiero decir, perdona, pero no quiero empezar una discusión, pero a veces, como mujer, es imposible hacerlo bien. Porque si estás soltera y no tienes pareja, para algunos tienes una autoestima altísima, pero para otros, ¿cuál es tu problema? ¿Por qué no tienes novio? En cambio, si estás soltera y tienes muchas citas, eres una aprovechada. ¿Qué hago? Mira, yo creo que lo que tenemos que hacer es lo que nos salga del corazón, lo que nos apetezca, ¿sabes? | I8: 4. Creative Shifts | J8: Abstraction – Paraphrase | K8: NO | N8: Claro, pero a la vez, quiero decir, perdón, pero no quiero abrir un debate feminista, pero a veces, como mujer, es imposible hacerlo bien. Porque si estás soltera y no ligas, para algunos tienes baja autoestima, pero para otros, ¿cuál es tu problema? ¿Por qué no estás teniendo relaciones? En cambio, si estás soltera y ligas mucho, eres una guarra. ¿Qué hago? Mira, yo creo que tenemos que hacer lo que nos salga de las pelotas, lo que nos dé la gana, ¿sabes? | O8: 4. Creative Shifts | P8: Abstraction – Paraphrase | Q8: YES | R8: LESS | T8: Claro, pero a la vez, quiero decir, perdona, pero ya no quiero abrir una "bandera lila", pero a veces, como mujer, es imposible hacerlo bien. Porque si estás soltera y no ligas, para algunos tienes baja autoestima, pero para otros, ¿cuál es tu problema? ¿Por qué no estás "liando"? En cambio, si estás soltera y ligas mucho, eres una "guarra". ¿Qué hago? Mira, yo creo que lo que tenemos que hacer es lo que nos salga de las pelotas, lo que nos plazca, ¿sabes? | U8: 4. Creative Shifts | V8: Abstraction – Paraphrase | W8: YES | X8: LESS | Z8: Claro, pero a la vez, quiero decir, disculpa, pero no quiero abrir un debate sobre esto, pero a veces, como mujer, es imposible hacerlo bien. Porque si estás soltera y no tienes pareja, para algunos eres una persona con baja autoestima, pero para otros, ¿cuál es tu problema? ¿Por qué no tienes novio? En cambio, si estás soltera y tienes muchas citas, eres una aprovechada. ¿Qué hago? Mira, yo creo que debemos hacer lo que nos salga del corazón, lo que nos apetezca, ¿sabes? | AA8: 4. Creative Shifts | AB8: Abstraction – Paraphrase | AC8: NO | AF8: Mira, claro, pero a la vez, a ver, perdón, pero no quiero precisamente levantar una polvareda, pero a veces, como mujer, es imposible hacerlo bien. Porque si estás soltera y no tienes pareja, para algunos eres de "autovalor", pero para otros, ¿cuál es tu problema? ¿Por qué no tienes novio? En cambio, si estás soltera y tienes muchas citas, eres una "guarra". ¿Qué hago? Mira, yo creo que lo que tenemos que hacer es lo que nos salga del corazón, del estómago, ¿sabes? | AG8: 3. Errors | AI8: NO | AL8: Clar, pero a la vez es que quiero decir, perdón, pero ya no quiero pas abrir una bandera lila, pero a veces como tía es imposible hacerlo bien. Porque si estás soltera y no estás liada, para algunos eres de autovalor, pero para otros, ¿cuál es tu fallo? ¿Por qué no estás follando? En cambio, si estás soltera y estás liada mucho, eres una guarra. ¿Qué hago? Mira, yo lo que encuentro que debemos hacer es lo que nos salga del churro, del cony, ¿sabes? | AM8: 3. Errors | AO8: NO | AR8: Claro, pero a la vez quiero decir, perdón, pero ya no quiero pasarlo a una bandera lila, pero a veces como tía es imposible hacerlo bien. Porque si estás soltera y no estás liada, para algunos eres de autovalor, pero para otros, ¿cuál es tu fallo? ¿Por qué no estás follando? En cambio, si estás soltera y estás liada mucho, eres una guarra. ¿Qué hago? Mira, lo que yo encuentro que debemos hacer es lo que nos salga del coño, del chocho, ¿sabes? | AS8: 1. Reproduction | AT8: Direct Translation | AU8: YES | AV8: SAME | AX8: Claro, pero a la vez es que quiero decir, perdón, pero ya no quiero pasar por una bandera lila, pero a veces, como tía, es imposible hacerlo bien. Porque si estás soltera y no estás liada, para algunos eres de autovalor, pero para otros, ¿cuál es tu fallo? ¿Por qué no estás follando? Por el contrario, si estás soltera y estás liada mucho, eres una guarra. ¿Qué hago? Mira, yo lo que encuentro que debemos hacer es lo que nos salga del churro, del cony, ¿sabes? | AY8: 3. Errors | BA8: NO | BD8: Claro, pero a la vez quiero decir, perdón, pero ya no quiero abrir una bandera lila, pero a veces, como mujer, es imposible hacerlo bien. Porque si estás soltera y no estás ligando, para algunos eres de autovalor, pero para otros, ¿cuál es tu fallo? ¿Por qué no estás follando? Por otro lado, si estás soltera y ligas mucho, eres una guarra. ¿Qué hago? Mira, lo que yo encuentro que debemos hacer es lo que nos salga del churro, del cony, ¿sabes? | BE8: 3. Errors | BG8: NO | BJ8: Claro, pero a la vez quiero decir, perdón, pero ya no quiero abrir una bandera lila, pero a veces, como tía, es imposible hacerlo bien. Porque si estás soltera y no estás ligando, para algunos eres de autovalor, pero para otros, ¿cuál es tu fallo? ¿Por qué no estás follando? En cambio, si estás soltera y ligas mucho, eres una guarra. ¿Qué hago? Mira, yo lo que encuentro que debemos hacer es lo que nos salga del churro, del cony, ¿sabes? | BK8: 3. Errors | BM8: NO | BP8: Claro, pero al mismo tiempo es que quiero decir, perdón, pero ya no quiero abrir una bandera lila, pero a veces como tía es imposible hacerlo bien. Porque si estás soltera y no ligas, para algunos eres de autovalor, pero para algunos, ¿cuál es tu fallo? ¿Por qué no follas? En cambio, si estás soltera y ligas mucho, eres una guarra. ¿Qué hago? Mira, lo que creo que debemos hacer es lo que nos salga de los cojones, del coño, ¿sabes? | BQ8: 4. Creative Shifts | BR8: Modification – Cultural | BS8: YES | BT8: SAME | BV8: Claro, pero a la vez quiero decir, perdona, pero ya no quiero abrir una bandera lila, pero a veces como tía es imposible hacerlo bien. Porque si estás soltera y no ligas, para algunos eres de autovalor, pero para algunos, ¿cuál es tu fallo? ¿Por qué no follas? En cambio, si estás soltera y ligas mucho, eres una guarra. ¿Qué hago? Mira, lo que creo que debemos hacer es lo que nos salga de los cojones, del coño, ¿sabes?" | BW8: 4. Creative Shifts | BX8: Modification – Cultural | BY8: YES | BZ8: SAME | CB8: Claro, pero a la vez es que quiero decir, perdón, pero ya no quiero abrir una bandera lila, pero a veces como tía es imposible hacerlo bien. Porque si estás soltera y no ligas, para algunos eres de autovalor, pero para algunos, ¿cuál es tu fallo? ¿Por qué no estás follando? En cambio, si estás soltera y atas mucho, eres una guarra. ¿Qué hago? Mira, yo lo que creo que tenemos que hacer es lo que nos salga del chocho, del coño, ¿sabes? | CC8: 1. Reproduction | CD8: Direct Translation | CE8: YES | CF8: SAME | CH8: Claro, pero al mismo tiempo es que quiero decir, perdón, pero ya no quiero abrir una bandera lila, pero a veces como tía es imposible hacerlo bien. Porque si estás soltera y no ligas, para algunos eres de autovalor, pero para algunos, ¿cuál es tu fallo? ¿Por qué no follas? En cambio, si estás soltera y ligas mucho, eres una guarra. ¿Qué hago? Mira, lo que creo que debemos hacer es lo que nos salga de los cojones, del coño, ¿sabes? | CI8: 4. Creative Shifts | CJ8: Modification – Cultural | CK8: YES | CL8: SAME | CN8: Claro, pero al mismo tiempo es que quiero decir, perdona, pero ya no quiero abrir una bandera lila, pero a veces como tía es imposible hacerlo bien. Porque si estás soltera y no ligas, para algunos eres de autovalor, pero para algunos, ¿cuál es tu fallo? ¿Por qué no follas? En cambio, si estás soltera y ligas mucho, eres una guarra. ¿Qué hago? Mira, lo que creo que debemos hacer es lo que nos salga de los cojones, del coño, ¿sabes? | CO8: 4. Creative Shifts | CP8: Modification – Cultural | CQ8: YES | CR8: SAME
A9: [empieza tema de conversación] | B9: Mira, jo, és a dir, jo realment me'n recordo etapes de la meva vida que estava soltera, que era una soltera infeliç, pel que dèiem de tot el rato estar pendent de dir, bueno, vale, molt bé, tinc amigues i família, però A veure quan ve el puto nòvio, saps? | C9: I com vius amb aquella impaciència, i també allò de no saber-ho si estàs fent bé, rotllo, si lligava, em sentia una guarra per lligar, i si no lligava pensava, per què ningú m'està tirant la canya? | D9: Mira, jo, és a dir, jo realment me'n recordo etapes de la meva vida que estava soltera, que era una soltera infeliç, pel que dèiem de tot el rato estar pendent de dir, bueno, vale, molt bé, tinc amigues i família, però A veure quan ve el puto nòvio, saps? | E9: 1. Lexicon and Vocabulary | F9: 1.1 | G9: Lexicon of insult | H9: Mira, yo, es decir, yo realmente recuerdo etapas de mi vida en las que estaba soltera, y era una soltera infeliz, por eso siempre estaba pendiente de pensar, bueno, vale, tengo amigas y familia, pero... a ver, ¿cuándo aparece el puto novio, sabes? | I9: 1. Reproduction | J9: Direct Translation | K9: YES | L9: SAME | N9: Mira, yo, o sea, yo realmente recuerdo etapas de mi vida en las que estaba soltera, y era una soltera infeliz, como decíamos, siempre pendiente de pensar: bueno, vale, tengo amigas y familia, pero a ver, ¿cuándo aparece el puto novio?, ¿sabes? | O9: 1. Reproduction | P9: Direct Translation | Q9: YES | R9: SAME | T9: Mira, yo, o sea, yo realmente recuerdo etapas de mi vida en las que estaba soltera, y era una soltera infeliz, como decíamos, siempre pendiente de pensar: bueno, vale, tengo amigas y familia, pero, a ver, ¿cuándo aparece el puto novio?, ¿sabes? | U9: 1. Reproduction | V9: Direct Translation | W9: YES | X9: SAME | Z9: Mira, yo, o sea, yo realmente recuerdo etapas de mi vida en las que estaba soltera, y era una soltera infeliz, por lo que siempre estaba pendiente de pensar: bueno, vale, tengo amigas y familia, pero... a ver, ¿cuándo aparece el condenado novio, sabes? | AA9: 4. Creative Shifts | AB9: Abstraction – Superordinate Term | AC9: NO | AF9: Mira, yo, es decir, yo realmente recuerdo etapas de mi vida en las que estaba soltera, y era una soltera infeliz, porque, como decíamos constantemente, estaba pendiente de pensar: "Vale, bien, tengo amigas y familia, pero... ¿cuándo aparecerá el condenado novio, sabes?". | AG9: 4. Creative Shifts | AH9: Abstraction – Superordinate Term | AI9: NO | AL9: Mira, yo, es decir, yo realmente me acuerdo de etapas de mi vida en las que estaba soltera, que era una soltera infeliz, y de todo el rato estar pendiente de decir, bueno, vale, muy bien, tengo amigas y familia, pero a ver cuándo llega el puto novio, ¿sabes? | AM9: 1. Reproduction | AN9: Direct Translation | AO9: YES | AP9: SAME | AR9: Mira, yo, es decir, yo realmente me acuerdo de etapas de mi vida en las que estaba soltera, que era una soltera infeliz, de lo que siempre decíamos de estar pendientes de decir, bueno, vale, muy bien, tengo amigas y familia, pero a ver cuando llega el puto novio, ¿sabes? | AS9: 1. Reproduction | AT9: Direct Translation | AU9: YES | AV9: SAME | AX9: Mira, yo, es decir, yo realmente me acuerdo de etapas de mi vida en las que estaba soltera, que era una soltera infeliz, y de lo que siempre decíamos, bueno, vale, muy bien, tengo amigas y familia, pero a ver cuando llega el puto novio, ¿sabes? | AY9: 1. Reproduction | AZ9: Direct Translation | BA9: YES | BB9: SAME | BD9: Mira, yo, quiero decir, realmente me acuerdo de etapas de mi vida en las que estaba soltera, que era una soltera infeliz, porque siempre estábamos pendientes de decir, bueno, vale, muy bien, tengo amigas y familia, pero ¿cuándo llega ese maldito novio, sabes? | BE9: 4. Creative Shifts | BF9: Abstraction – Superordinate Term | BG9: NO | BJ9: Mira, yo, es decir, yo realmente me acuerdo de etapas de mi vida en las que estaba soltera, que era una soltera infeliz, y siempre decíamos que estábamos pendientes de decir, bueno, vale, muy bien, tengo amigas y familia, pero a ver cuándo llega ese puto novio, ¿sabes? | BK9: 1. Reproduction | BL9: Direct Translation | BM9: YES | BN9: SAME | BP9: Mira, yo, es decir, yo realmente me acuerdo etapas de mi vida que estaba soltera, que era una soltera infeliz, por lo que decíamos de todo el rato estar pendiente de decir, bueno, vale, muy bien, tengo amigas y familia, pero A ver cuando viene el puto novio, ¿sabes? | BQ9: 1. Reproduction | BR9: Direct Translation | BS9: YES | BT9: SAME | BV9: Oye, mira, yo, o sea, yo realmente recuerdo etapas de mi vida que estaba soltera, que era una soltera infeliz, por lo que decíamos todo el rato de "bueno, vale, muy bien, tengo amigas y familia", pero ¿a ver cuándo viene el put* novio?, sabes? | BW9: 1. Reproduction | BX9: Direct Translation | BY9: YES | BZ9: SAME | CB9: Oye, mira, yo, o sea, yo realmente recuerdo etapas de mi vida que estaba soltera, que era una soltera infeliz, por lo que decíamos todo el rato de "bueno, vale, muy bien, tengo amigas y familia", pero ¿a ver cuándo viene el puto novio?, sabes? | CC9: 1. Reproduction | CD9: Direct Translation | CE9: YES | CF9: SAME | CH9: Mira, yo, es decir, yo realmente me acuerdo etapas de mi vida que estaba soltera, que era una soltera infeliz, por lo que decíamos de todo el rato estar pendiente de decir, bueno, vale, muy bien, tengo amigas y familia, pero A ver cuándo viene el puto novio, ¿sabes? | CI9: 1. Reproduction | CJ9: Direct Translation | CK9: YES | CL9: SAME | CN9: Mira, yo, es decir, yo realmente me acuerdo etapas de mi vida que estaba soltera, que era una soltera infeliz, por lo que decíamos de todo el rato estar pendiente de decir, bueno, vale, muy bien, tengo amigas y familia, pero A ver cuándo viene el puto novio, ¿sabes? | CO9: 1. Reproduction | CP9: Direct Translation | CQ9: YES | CR9: SAME
A10: [empieza tema de conversación] | B10: Mira, lligar jo penso que és com anar a fer la compra al súper, que diuen que no hi pots anar mai amb gana. Perquè llavors compres moltes coses que no necessites. I quan vas a comprar al súper, que ja no tens gana, fas una compra amb seny. | C10: [acaba tema de conversación] | D10: Mira, lligar jo penso que és com anar a fer la compra al súper, que diuen que no hi pots anar mai amb gana. Perquè llavors compres moltes coses que no necessites. I quan vas a comprar al super, que ja no tens gana, fas una compra amb seny. | E10: 1. Lexicon and Vocabulary | F10: 1.1 | G10: Lexicon of insult | H10: Mira, en lo que respecta a las relaciones, yo pienso que es como ir a hacer la compra al supermercado, que dicen que nunca se debe ir con hambre. Porque entonces compras muchas cosas que no necesitas. Y cuando vas a comprar al supermercado sin hambre, haces una compra con sensatez. | I10: 1. Reproduction | J10: Specification | K10: NO | N10: Mira, en lo que respecta a ligar, yo creo que es como ir a hacer la compra al supermercado, que dicen que nunca se debe ir con hambre. Porque entonces compras muchas cosas que no necesitas. Y cuando vas a comprar al supermercado y ya no tienes hambre, haces una compra con sensatez. | O10: 1. Reproduction | P10: Specification | Q10: NO | T10: Mira, en lo que a mí respecta, ligar es como ir a hacer la compra al supermercado, que dicen que nunca se debe ir con hambre. Porque entonces compras muchas cosas que no necesitas. Y cuando vas a comprar al supermercado y ya no tienes hambre, haces una compra con sensatez. | U10: 1. Reproduction | V10: Specification | W10: NO | Z10: Mira, en lo que respecta a las relaciones, yo creo que es como ir a hacer la compra al supermercado, que dicen que nunca se debe ir con hambre. Porque entonces compras muchas cosas que no necesitas. Y cuando vas a comprar al supermercado y ya no tienes hambre, haces una compra con sensatez. | AA10: 1. Reproduction | AB10: Specification | AC10: NO | AF10: Mira, yo creo que ligar es como ir a hacer la compra al supermercado, que dicen que nunca se debe ir con hambre. Porque entonces compras muchas cosas que no necesitas. Y cuando vas a comprar al supermercado y ya no tienes hambre, haces una compra con sensatez. | AG10: 1. Reproduction | AH10: Specification | AI10: NO | AL10: Mira, ligar yo pienso que es como ir a hacer la compra al supermercado, que dicen que no puedes ir nunca con hambre. Porque entonces compras muchas cosas que no necesitas. Y cuando vas a comprar al supermercado, que ya no tienes hambre, haces una compra con sentido común. | AM10: 1. Reproduction | AN10: Specification | AO10: NO | AR10: Mira, ligar yo penso que es como ir a hacer la compra al super, que dicen que no puedes ir nunca con hambre. Porque entonces compras muchas cosas que no necesitas. Y cuando vas a comprar al super, que ya no tienes hambre, haces una compra con sentido común. | AS10: 1. Reproduction | AT10: Retention | AU10: YES | AV10: SAME | AX10: Mira, ligar yo pienso que es como ir a hacer la compra al super, que dicen que no puedes ir nunca con hambre. Porque entonces compras muchas cosas que no necesitas. Y cuando vas a comprar al super, que ya no tienes hambre, haces una compra con sentido común. | AY10: 1. Reproduction | AZ10: Retention | BA10: YES | BB10: SAME | BD10: Mira, hacer una compra, yo pienso que es como ir al supermercado, que dicen que no puedes ir nunca con hambre. Porque entonces compras muchas cosas que no necesitas. Y cuando vas al supermercado, que ya no tienes hambre, haces una compra con sentido común. | BE10: 1. Reproduction | BF10: Retention | BG10: NO | BJ10: Mira, ligar yo pienso que es como ir a hacer la compra al supermercado, que dicen que no puedes ir nunca con hambre. Porque entonces compras muchas cosas que no necesitas. Y cuando vas a comprar al supermercado, que ya no tienes hambre, haces una compra con sentido común. | BK10: 1. Reproduction | BL10: Retention | BM10: NO | BP10: Mira, ligar yo pienso que es como ir a hacer la compra al súper, que dicen que no se puede ir nunca con hambre. Porque entonces se compran muchas cosas que no se necesitan. Y cuando se va a comprar al súper, que ya no se tiene hambre, se hace una compra con cabeza. | BQ10: 3. Errors | BS10: NO | BV10: Mira, ligar yo pienso que es como ir a hacer la compra al súper, que dicen que no puedes ir nunca con hambre. Porque entonces compras muchas cosas que no necesitas. Y cuando vas a comprar al súper, que ya no tienes hambre, haces una compra con cabeza. | BW10: 3. Errors | BY10: NO | CB10: Mira, ligar yo pienso que es como ir a hacer la compra al súper, que dicen que no puedes ir nunca con hambre. Porque entonces compras muchas cosas que no necesitas. Y cuando vas a comprar al súper, que ya no tienes hambre, haces una compra con cabeza. | CC10: 3. Errors | CE10: NO | CH10: Mira, ligar yo pienso que es como ir a hacer la compra al súper, que dicen que no se puede ir nunca con hambre. Porque entonces se compran muchas cosas que no se necesitan. Y cuando se va a comprar al súper, que ya no se tiene hambre, se hace una compra con cabeza. | CI10: 3. Errors | CK10: NO | CN10: Mira, ligar yo pienso que es como ir a hacer la compra al súper, que dicen que no puedes ir nunca con hambre. Porque entonces compras muchas cosas que no necesitas. Y cuando vas a comprar al súper, que ya no tienes hambre, haces una compra con cabeza. | CO10: 3. Errors | CQ10: NO
A11: [empieza tema de conversación] | B11: I llavors quan vaig començar a anar a la platja amb les amigues com a pla de platja, o sigui, que ja implicava una socialització i que ja implicava totes les normes amb les que ens hem socialitzat les noies, era com, hòstia, necessito looks per anar a la platja. Com que looks per anar a la platja? | C11: A mi encara ara em segueix fent mal gastar-me diners en roba maca per anar a la platja, perquè penso, és que és total, és per anar a la platja. | D11: I llavors quan vaig començar a anar a la platja amb les amigues com a pla de platja, o sigui, que ja implicava una socialització i que ja implicava totes les normes amb les que ens hem socialitzat les noies, era com, hòstia, necessito looks per anar a la platja. Com que looks per anar a la platja? | E11: 1. Lexicon and Vocabulary | F11: 1.8 | G11: Neologisms | H11: Y entonces, cuando empecé a ir a la playa con mis amigas, como parte del plan, o sea, ya implicaba socializar y también implicaba todas esas normas con las que nos han educado a las mujeres, era como, "madre mía, necesito looks para ir a la playa". ¿Looks para ir a la playa? | I11: 1. Reproduction | J11: Retention | K11: YES | L11: SAME | N11: "Y entonces, cuando empecé a ir a la playa con mis amigas como plan de verano, o sea, ya implicaba socializar y ya implicaba todas las normas con las que nos han socializado a las mujeres, era como, ¡madre mía!, necesito looks para ir a la playa. ¿Looks para ir a la playa? | O11: 1. Reproduction | P11: Retention | Q11: YES | R11: SAME | T11: Y entonces, cuando empecé a ir a la playa con mis amigas como parte del plan, es decir, ya implicaba socializar y ya implicaba todas las normas con las que nos hemos socializado las chicas, era como, ¡madre mía!, necesito looks para ir a la playa. ¿Looks para ir a la playa? | U11: 1. Reproduction | V11: Retention | W11: YES | X11: SAME | Z11: Entonces, cuando empecé a ir a la playa con mis amigas, como parte de un plan, es decir, ya implicaba socializar y ya implicaba todas las normas con las que nos han socializado a las mujeres, era como: "¡Madre mía, necesito ropa para ir a la playa!". ¿Ropa para ir a la playa? | AA11: 1. Reproduction | AB11: Direct Translation | AC11: NO | AF11: Y entonces, cuando empecé a ir a la playa con mis amigas como parte de un plan, es decir, ya implicaba socializar y también todas las normas con las que nos hemos criado las chicas, pensaba: "¡Uf, necesito looks para ir a la playa!". ¿Looks para ir a la playa? | AG11: 1. Reproduction | AH11: Retention | AI11: YES | AJ11: SAME | AL11: Y entonces, cuando empecé a ir a la playa con las amigas como plan de playa, es decir, que ya implicaba una socialización y que ya implicaba todas las normas con las que nos hemos socializado las chicas, era como, joder, necesito looks para ir a la playa. ¿Qué quiere decir, looks para ir a la playa? | AM11: 1. Reproduction | AN11: Retention | AO11: YES | AP11: SAME | AR11: Y entonces, cuando empecé a ir a la playa con las amigas como plan de playa, o sea, que ya implicaba una socialización y que ya implicaba todas las normas con las que nos hemos socializado las chicas, era como, hostia, necesito looks para ir a la playa. ¿Cómo que looks para ir a la playa? | AS11: 1. Reproduction | AT11: Retention | AU11: YES | AV11: SAME | AX11: Y entonces cuando empecé a ir a la playa con las amigas como plan de playa, o sea, que ya implicaba una socialización y que ya implicaba todas las normas con las que nos hemos socializado las chicas, era como, joder, necesito looks para ir a la playa. ¿Como que looks para ir a la playa? | AY11: 1. Reproduction | AZ11: Retention | BA11: YES | BB11: SAME | BD11: Y entonces, cuando empecé a ir a la playa con las amigas como plan de playa, es decir, que ya implicaba una socialización y que ya implicaba todas las normas con las que nos hemos socializado las chicas, era como, joder, necesito looks para ir a la playa. ¿Cómo que looks para ir a la playa? | BE11: 1. Reproduction | BF11: Retention | BG11: YES | BH11: SAME | BJ11: Y entonces, cuando empecé a ir a la playa con las amigas como plan de playa, es decir, que ya implicaba una socialización y que ya implicaba todas las normas con las que nos hemos socializado las chicas, era como, joder, necesito looks para ir a la playa. ¿Cómo que looks para ir a la playa? | BK11: 1. Reproduction | BL11: Retention | BM11: YES | BN11: SAME | BP11: Y entonces, cuando empecé a ir a la playa con mis amigas como plan de playa, es decir, que ya implicaba una socialización y que ya implicaba todas las normas con las que nos hemos socializado las chicas, era como, joder, necesito looks para ir a la playa. ¿Cómo que looks para ir a la playa? | BQ11: 1. Reproduction | BR11: Retention | BS11: YES | BT11: SAME | BV11: Y entonces cuando empecé a ir a la playa con las amigas como plan de playa, o sea, que ya implicaba una socialización y que ya implicaba todas las normas con las que nos hemos socializado las chicas, era como, hostia, necesito looks para ir a la playa. ¿Cómo looks para ir a la playa? | BW11: 1. Reproduction | BX11: Retention | BY11: YES | BZ11: SAME | CB11: Y entonces cuando empecé a ir a la playa con las amigas como plan de playa, o sea, que ya implicaba una socialización y que ya implicaba todas las normas con las que nos hemos socializado las chicas, era como, hostia, necesito looks para ir a la playa. ¿Cómo looks para ir a la playa? | CC11: 1. Reproduction | CD11: Retention | CE11: YES | CF11: SAME | CH11: Y entonces, cuando empecé a ir a la playa con mis amigas como plan de playa, es decir, que ya implicaba una socialización y que ya implicaba todas las normas con las que nos hemos socializado las chicas, era como, joder, necesito looks para ir a la playa. ¿Cómo que looks para ir a la playa? | CI11: 1. Reproduction | CJ11: Retention | CK11: YES | CL11: SAME | CN11: Entonces, cuando empecé a ir a la playa con mis amigas como plan de playa, es decir, que ya implicaba una socialización y que ya implicaba todas las normas con las que nos hemos socializado las chicas, era como, ¡mierda, necesito looks para ir a la playa! ¿Por qué looks para ir a la playa? | CO11: 1. Reproduction | CP11: Retention | CQ11: YES | CR11: SAME
A12: [empieza tema de conversación] | B12: Jo moltes vegades em noto com superfrenada del que estic fent perquè ja me dono cringe a la mínima, saps? O sigui, me fa cringe fins i tot anar al metro, qualsevol puta merda, en plan obrir la porta, me fa vergonya. | C12: Això és de teràpia, eh? Hashtag salut mental, ens hem de cuidar. | D12: Jo moltes vegades em noto com superfrenada del que estic fent perquè ja me dono cringe a la mínima, saps? O sigui, me fa cringe fins i tot anar al metro, qualsevol puta merda, en plan obrir la porta, me fa vergonya. | E12: 1. Lexicon and Vocabulary | F12: 1.5 | G12: Informal intensifiers and quantifiers | H12: A mí, muchas veces, me siento muy avergonzada de lo que estoy haciendo, porque me da vergüenza incluso la cosa más mínima, ¿entiendes? Es decir, me da vergüenza hasta ir en el metro, cualquier cosa, incluso abrir la puerta, me da vergüenza. | I12: 4. Creative Shifts | J12: Abstraction – Paraphrase | K12: NO | N12: Yo muchas veces me doy cuenta de que soy demasiado sensible a lo que hago, porque me da vergüenza con facilidad, ¿sabes? O sea, me da vergüenza incluso ir al metro, cualquier cosa, en plan abrir la puerta, me da vergüenza. | O12: 3. Errors | Q12: NO | T12: A veces me doy cuenta de que soy superinhibida con lo que estoy haciendo, porque me da vergüenza con facilidad, ¿sabes? Es decir, me da vergüenza incluso ir en el metro, cualquier cosa, incluso abrir la puerta, me da vergüenza. | U12: 4. Creative Shifts | V12: Abstraction – Paraphrase | W12: NO | Z12: A mí, muchas veces me doy cuenta de que soy demasiado sensible a lo que hago, porque me da vergüenza con facilidad, ¿sabes? O sea, me da vergüenza incluso ir en el metro, cualquier cosa, por ejemplo, abrir la puerta, me da vergüenza. | AA12: 3. Errors | AC12: NO | AF12: A mí, muchas veces, me noto demasiado sensible con lo que hago, porque me da vergüenza con facilidad, ¿sabes? Es decir, me da vergüenza incluso ir en el metro, cualquier cosa, por ejemplo, abrir la puerta, me da vergüenza. | AG12: 3. Errors | AI12: NO | AL12: También me siento muchas veces como super frenada de lo que estoy haciendo porque ya me doy cringe a la mínima, ¿sabes? O sea, me da cringe incluso ir al metro, cualquier puta mierda, como abrir la puerta, me da vergüenza. | AM12: 3. Errors | AO12: NO | AR12: Jo muchas veces me siento como superfrenada del que estoy haciendo porque ya me doy cringe a la mínima, saps? O sea, me hace cringe incluso ir al metro, cualquier puta mierda, en plan abrir la puerta, me da vergüenza. | AS12: 1. Reproduction | AT12: Direct Translation | AU12: YES | AV12: SAME | AX12: Muchas veces me siento superfrenada con lo que estoy haciendo porque ya me doy cringe a la mínima, ¿sabes? O sea, me da cringe incluso ir al metro, cualquier puta mierda, en plan abrir la puerta, me da vergüenza. | AY12: 1. Reproduction | AZ12: Direct Translation | BA12: YES | BB12: SAME | BD12: "Muchas veces me siento como super frenada de lo que estoy haciendo porque ya me da cringe a la mínima, sabes? O sea, me da cringe incluso ir al metro, cualquier mierda, a la hora de abrir la puerta, me da vergüenza." | BE12: 3. Errors | BG12: NO | BJ12: A veces me siento como si estuviera super frenada con lo que estoy haciendo, porque ya me doy vergüenza incluso a la mínima, ¿sabes? O sea, me da vergüenza hasta ir al metro, cualquier mierda, incluso abrir la puerta, me da vergüenza. | BK12: 3. Errors | BM12: NO | BP12: Yo muchas veces me noto como superfrenada del que estoy haciendo porque ya me doy cringe a la mínima, sabes? O sea, me da cringe incluso ir al metro, cualquier puta mierda, en plan abrir la puerta, me da vergüenza. | BQ12: 1. Reproduction | BR12: Direct Translation | BS12: YES | BT12: SAME | BV12: Yo muchas veces me noto como superfrenada del que estoy haciendo porque ya me doy cringe a la mínima, sabes? O sea, me da cringe incluso ir al metro, cualquier puta mierda, en plan abrir la puerta, me da vergüenza. | BW12: 1. Reproduction | BX12: Direct Translation | BY12: YES | BZ12: SAME | CB12: Yo muchas veces me noto como superfrenada del que estoy haciendo porque ya me doy cringe a la mínima, sabes? O sea, me da cringe hasta ir al metro, cualquier puta mierda, en plan abrir la puerta, me da vergüenza. | CC12: 1. Reproduction | CD12: Direct Translation | CE12: YES | CF12: SAME | CH12: Yo muchas veces me noto como superfrenada del que estoy haciendo porque ya me doy cringe a la mínima, sabes? O sea, me da cringe hasta ir al metro, cualquier cosa, en plan abrir la puerta, me da vergüenza. | CI12: 1. Reproduction | CJ12: Direct Translation | CK12: YES | CL12: SAME | CN12: Jo muchas veces me noto como superfrenada de lo que estoy haciendo porque ya me da cringe a la mínima, ¿sabes? O sea, me da cringe hasta ir al metro, cualquier puta mierda, en plan abrir la puerta, me da vergüenza. | CO12: 1. Reproduction | CP12: Direct Translation | CQ12: YES | CR12: SAME
A13: [empieza tema de conversación] | B13: Ja, jo soc molt tocona, perdoneu-me. De fet, moltes vegades, a molta gent ficava comentaris de "aquesta presentadora és una tiracanyes". | C13: Sí que és veritat. Quan hi vaig anar em vaig sentir supertocada, m'encanta. | D13: Ja, jo soc molt tocona, perdoneu-me. De fet, moltes vegades, a molta gent ficava comentaris de "aquesta presentadora és una tiracanyes". | E13: 1. Lexicon and Vocabulary | F13: 1.2 | G13: Colloquial lexicon and slang | H13: Sí, soy muy despistada, discúlpenme. De hecho, muchas veces, le dejaba comentarios a mucha gente como "esta presentadora es una insensata". | I13: 3. Errors | K13: NO | N13: Sí, yo soy muy presumida, perdónenme. De hecho, muchas veces, a mucha gente les sacaba comentarios de "esta presentadora es una engreída". | O13: 3. Errors | Q13: NO | T13: Sí, yo soy muy sensible, perdónenme. De hecho, muchas veces, le dejaba comentarios a mucha gente como "esta presentadora es una tirana". | U13: 3. Errors | W13: NO | Z13: Sí, soy muy atrevida, disculpadme. De hecho, muchas veces, le dejaba comentarios a mucha gente como "esta presentadora es una bocaza". | AA13: 3. Errors | AC13: NO | AF13: Sí, yo soy muy susceptible, discúlpenme. De hecho, muchas veces, le decía a mucha gente cosas como "esta presentadora es una insensata". | AG13: 3. Errors | AI13: NO | AL13: Sí, soy muy tocona, perdónenme. De hecho, muchas veces le ponía comentarios a mucha gente diciendo "esta presentadora es una tiracaníes". | AM13: 3. Errors | AO13: NO | AR13: Sí, yo soy muy tocona, perdónenme. De hecho, muchas veces le ponía comentarios a mucha gente de "esta presentadora es una tiracanyas". | AS13: 3. Errors | AU13: NO | AX13: Bueno, yo soy muy tocona, perdónenme. De hecho, muchas veces le ponía comentarios a mucha gente de "esta presentadora es una tiracanyas". | AY13: 3. Errors | BA13: NO | BD13: Claro, soy muy tocona, perdónenme. De hecho, muchas veces le dejaba comentarios a mucha gente diciendo "esta presentadora es una tiracanyas". | BE13: 3. Errors | BG13: NO | BJ13: Claro, soy muy tocona, perdónenme. De hecho, muchas veces le dejaba comentarios a mucha gente diciendo "esta presentadora es una tiracanyas". | BK13: 3. Errors | BM13: NO | BP13: Sí, yo soy muy tocona, perdónenme. De hecho, muchas veces, a mucha gente le hacía comentarios de "esta presentadora es una tiracanyes". | BQ13: 1. Reproduction | BR13: Retention | BS13: NO | BV13: Sí, yo soy muy tocona, perdónenme. De hecho, muchas veces, a mucha gente le hacía comentarios de "esta presentadora es una tiracanyes". | BW13: 1. Reproduction | BX13: Retention | BY13: NO | CB13: Sí, yo soy muy tocona, perdónenme. De hecho, muchas veces, a mucha gente le hacía comentarios de "esta presentadora es una tiracanyes". | CC13: 1. Reproduction | CD13: Retention | CE13: NO | CH13: Sí, yo soy muy tocona, perdónenme. De hecho, muchas veces, a mucha gente le hacía comentarios de "esta presentadora es una tiracanyes". | CI13: 1. Reproduction | CJ13: Retention | CK13: NO | CN13: Sí, yo soy muy tocona, perdónenme. De hecho, muchas veces, a mucha gente le hacía comentarios de "esta presentadora es una tiracanyes". | CO13: 1. Reproduction | CP13: Retention | CQ13: NO
A14: [empieza tema de conversación] | B14: De fet, jo quan anava a l'insti tenia superdepressió perquè estava com molt de moda, en plan, com més plans feies, més xula eres. Llavors era, faig un pla, ni que sigui fer un cafè de 5 minuts amb una amiga i he de penjar un instastory per deixar constància que he fet aquest pla. Era una cosa de madness molt bèstia. | C14: I a dia d'avui, com més privat ets, en plan, la penya que ara està a l'institut, és com poden fer un pla superguai, per exemple, se'n van a Nova York un puto més, pensaran potser un Instastory I els hi pela. | D14: De fet, jo quan anava a l'insti tenia superdepressió perquè estava com molt de moda, en plan, com més plans feies, més xula eres. Llavors era, faig un pla, ni que sigui fer un cafè de 5 minuts amb una amiga i he de penjar un instastory per deixar constància que he fet aquest pla. Era una cosa de madness molt bèstia. | E14: 4. Register and Tone | F14: 4.1 | G14: Hyperbole and exaggeration | H14: De hecho, cuando iba al instituto, estaba superdeprimida porque era muy de moda, como que cuanto más planes hacías, más "cool" eras. Entonces, era así: hacía un plan, aunque fuera tomar un café de 5 minutos con una amiga, y tenía que publicar un "instastory" para dejar constancia de que había hecho ese plan. Era una locura. | I14: 4. Creative Shifts | J14: Modification – Situational | K14: YES | L14: LESS | N14: De hecho, cuando iba al instituto, tenía una depresión terrible porque estaba muy de moda esa cosa, como que cuanto más planes hacías, más "guay" eras. Entonces, hacía un plan, aunque fuera tomar un café de cinco minutos con una amiga, y tenía que subirlo a un Instastory para dejar constancia de que había hecho ese plan. Era una locura. | O14: 4. Creative Shifts | P14: Abstraction – Superordinate Term | Q14: NO | T14: De hecho, cuando iba al instituto tenía superdepresión porque estaba muy de moda, en plan, cuanto más planes hacías, más guapa eras. Entonces era, hago un plan, aunque sea tomar un café de 5 minutos con una amiga, y tengo que subir un story de Instagram para dejar constancia de que he hecho ese plan. Era una locura. | U14: 1. Reproduction | V14: Direct Translation | W14: YES | X14: SAME | Z14: De hecho, cuando iba al instituto, sufría de una depresión muy fuerte porque estaba muy de moda esa cosa, como que cuanto más planes hacías, más "guapa" eras. Entonces, hacía un plan, aunque fuera tomar un café de 5 minutos con una amiga, y tenía que subir un "instastory" para dejar constancia de que había hecho ese plan. Era una locura. | AA14: 4. Creative Shifts | AB14: Abstraction – Superordinate Term | AC14: NO | AF14: De hecho, cuando iba al instituto, tenía mucha depresión porque estaba muy de moda esa cosa, como que cuanto más planes hacías, más "cool" eras. Entonces, era así: hacía un plan, aunque fuera tomar un café de 5 minutos con una amiga, y tenía que subirlo a un "instastory" para dejar constancia de que había hecho ese plan. Era una locura total. | AG14: 4. Creative Shifts | AH14: Abstraction – Superordinate Term | AI14: NO | AL14: De hecho, yo cuando iba al instituto tenía superdepresión porque estaba como muy de moda, en plan, cuanto más planes haces, más guay eres. Entonces era, hacía un plan, ni que fuera hacer un café de cinco minutos con una amiga y tenía que subir un instastory para dejar constancia de que había hecho ese plan. Era una cosa de locura muy bestia. | AM14: 1. Reproduction | AN14: Direct Translation | AO14: YES | AP14: SAME | AR14: De hecho, yo cuando iba al instituto tenía superdepresión porque estaba como muy de moda, en plan, cuanto más planes hacías, más guay eras. Entonces era, hacía un plan, ni que fuera hacer un café de 5 minutos con una amiga y tenía que colgar un instastory para dejar constancia de que había hecho ese plan. Era una cosa de madness muy bestia. | AS14: 1. Reproduction | AT14: Direct Translation | AU14: YES | AV14: SAME | AX14: De hecho, yo cuando iba al instituto tenía superdepresión porque estaba como muy de moda, en plan, cuanto más planes hacías, más guapa eras. Entonces era, hacía un plan, ni que fuera hacer un café de 5 minutos con una amiga y tenía que subir un instastory para dejar constancia de que había hecho ese plan. Era una cosa de madness muy bestia. | AY14: 1. Reproduction | AZ14: Direct Translation | BA14: YES | BB14: SAME | BD14: De fet, yo cuando iba al instituto tenía superdepresión porque estaba como muy de moda, en plan, cuanto más planes hacías, más guapa eras. Entonces era, hacía un plan, ni que fuera hacer un café de 5 minutos con una amiga y tenía que subir un instastory para dejar constancia de que había hecho ese plan. Era una cosa de madness muy bestia. | BE14: 1. Reproduction | BF14: Direct Translation | BG14: YES | BH14: SAME | BJ14: De hecho, yo cuando iba al instituto tenía superdepresión porque estaba como muy de moda, en plan, cuanto más planes hacías, más guay eras. Entonces era, hacías un plan, ni que fuera hacer un café de 5 minutos con una amiga y tenías que subir un instastory para dejar constancia de que habías hecho ese plan. Era una cosa de locura muy bestia. | BK14: 1. Reproduction | BL14: Direct Translation | BM14: YES | BN14: SAME | BP14: De hecho, cuando iba al instituto tenía superdepresión porque estaba como muy de moda, en plan, cuanto más planes hacías, más guay eras. Entonces era, hago un plan, aunque sea ir a tomar un café de 5 minutos con una amiga y tenía que colgar una historia de Instagram para dejar constancia de que había hecho ese plan. Era una cosa de locos muy bestia. | BQ14: 1. Reproduction | BR14: Direct Translation | BS14: YES | BT14: SAME | BV14: De hecho, yo cuando iba al instituto tenía superdepresión porque estaba como muy de moda, en plan, cuanto más planes hacías, más guay eras. Entonces era, hago un plan, ni que sea ir a tomar un café de 5 minutos con una amiga y tenía que colgar un instastory para dejar constancia de que he hecho ese plan. Era una cosa de locos muy bestia. | BW14: 1. Reproduction | BX14: Direct Translation | BY14: YES | BZ14: SAME | CB14: De hecho, yo cuando iba al instituto tenía superdepresión porque estaba como muy de moda, en plan, cuanto más planes hacías, más guay eras. Entonces era, hago un plan, ni que sea ir a tomar un café de 5 minutos con una amiga y tengo que colgar una historia de Instagram para dejar constancia de que he hecho ese plan. Era una cosa de locos muy bestia. | CC14: 1. Reproduction | CD14: Direct Translation | CE14: YES | CF14: SAME | CH14: De hecho, cuando iba al instituto tenía superdepresión porque estaba como muy de moda, en plan, cuanto más planes hacías, más guay eras. Entonces era, hago un plan, aunque sea ir a tomar un café de 5 minutos con una amiga y tenía que colgar una historia de Instagram para dejar constancia de que había hecho ese plan. Era una cosa de locos muy bestia. | CI14: 1. Reproduction | CJ14: Direct Translation | CK14: YES | CL14: SAME | CN14: De hecho, yo cuando iba al instituto tenía superdepresión porque estaba como muy de moda, en plan, cuanto más planes hacías, más chula eras. Entonces era, hago un plan, ni que sea tomar un café de 5 minutos con una amiga y tengo que colgar un instastory para dejar constancia de que he hecho ese plan. Era una cosa de madness muy bestia. | CO14: 1. Reproduction | CP14: Direct Translation | CQ14: YES | CR14: SAME
A15: [empieza tema de conversación] | B15: Estic tenint un recuerdo de Vietnam, nenes. Vaig estar a una discoteca molt gay, que no diré nom, i un tio de 50 anys va intentar lligar amb mi 50 hores seguides, jo intentant fer-li veure que no, i m'ha dit, jo soc bailarín, no sé què, bailamos, i jo així, que no, que no, que no, i jo que no, i ell, que sí, que sí, que sí, que sí, per demostrar-m'ho, de cop i volta, obre les cames fent el puto espagat i rebotant el cul contra el terra fent l'espagat. | C15: Jo em vaig quedar... | D15: Estic tenint un recuerdo de Vietnam, nenes. Vaig estar a una discoteca molt gay, que no diré nom, i un tio de 50 anys va intentar lligar amb mi 50 hores seguides, jo intentant fer-li veure que no, i m'ha dit, jo soc bailarín, no sé què, bailamos, i jo així, que no, que no, que no, i jo que no, i ell, que sí, que sí, que sí, que sí, per demostrar-m'ho, de cop i volta, obre les cames fent el puto espagat i rebotant el cul contra el terra fent l'espagat. | E15: 1. Lexicon and Vocabulary | F15: 1.6 | G15: References to popular culture and memes | H15: Estoy recordando Vietnam, chicas. Estuve en una discoteca muy gay, que no voy a decir el nombre, y un tipo de 50 años intentó ligar conmigo durante 50 horas seguidas, yo intentando hacerle ver que no, y me dijo, "soy bailarín, no sé qué", "bailamos", y yo, "no, no, no", y él, "sí, sí, sí, sí", y para demostrármelo, de repente, abrió las piernas haciendo el puto estiramiento y rebotando el trasero contra el suelo haciendo el estiramiento. | I15: 4. Creative Shifts | J15: Modification – Situational | K15: NO | N15: Estoy teniendo un recuerdo de Vietnam, chicas. Estuve en una discoteca muy gay, que no voy a decir el nombre, y un tío de 50 años intentó ligar conmigo durante 50 horas seguidas, yo intentando hacerle ver que no, y me dijo: "Soy bailarín, no sé qué...", "bailamos", y yo, "no, no, no", y él, "sí, sí, sí, sí", para demostrármelo, de repente, abre las piernas haciendo el puto estiramiento y rebotando el culo contra el suelo mientras hace el estiramiento. | O15: 1. Reproduction | P15: Direct Translation | Q15: YES | R15: SAME | T15: Estoy teniendo un recuerdo de Vietnam, chicas. Estuve en una discoteca muy gay, que no voy a decir el nombre, y un tío de 50 años intentó ligar conmigo durante 50 horas seguidas, yo intentando hacerle ver que no, y me dijo, "yo soy bailarín, no sé qué", "bailamos", y yo así, que no, que no, que no, y yo que no, y él, que sí, que sí, que sí, que sí, para demostrarmelo, de repente, abre las piernas haciendo el puto estiramiento y rebotando el culo contra el suelo haciendo el estiramiento. | U15: 1. Reproduction | V15: Direct Translation | W15: YES | X15: SAME | Z15: Estoy recordando Vietnam, chicas. Estuve en una discoteca muy gay, que no voy a nombrar, y un tipo de 50 años intentó ligar conmigo durante 50 horas seguidas, yo intentando hacerle ver que no, y me dijo, "soy bailarín, no sé qué", "bailamos", y yo, "no, no, no", y él, "sí, sí, sí, sí", para demostrarlo, de repente, abrió las piernas haciendo el puto estiramiento y rebotando el trasero contra el suelo mientras hacía el estiramiento. | AA15: 4. Creative Shifts | AB15: Modification – Situational | AC15: NO | AF15: Estoy recordando Vietnam, chicas. Estuve en una discoteca muy gay, que no voy a mencionar, y un tipo de unos 50 años intentó ligar conmigo sin parar, yo intentando hacerle entender que no, y me dijo, "soy bailarín, no sé qué", "bailamos", y yo, "no, no, no", y yo, "no", y él, "sí, sí, sí, sí", y para demostrarlo, de repente, abrió las piernas haciendo una postura de estiramiento y rebotando el trasero contra el suelo. | AG15: 4. Creative Shifts | AH15: Modification – Situational | AI15: NO | AL15: También tengo un recuerdo de Vietnam, chicas. Estuve en una discoteca muy gay, que no diré el nombre, y un tío de 50 años intentó ligarme durante 50 horas seguidas, yo intentando hacerle entender que no, y me dijo, "yo soy bailarín, no sé qué, bailamos", y yo así, "que no, que no, que no, yo que no", y él, "sí, sí, sí, sí", para demostrármelo, de repente, se abre las piernas haciendo el puto espagueti y rebota el culo contra el suelo haciendo el espagueti. | AM15: 1. Reproduction | AN15: Direct Translation | AO15: YES | AP15: SAME | AR15: Tengo un recuerdo de Vietnam, nenas. Estuve en una discoteca muy gay, que no diré el nombre, y un tío de 50 años intentó ligar conmigo durante 50 horas seguidas, yo intentando hacerle ver que no, y me dijo, \"yo soy bailarín, no sé qué, bailamos\", y yo así, que no, que no, que no, y yo que no, y él, que sí, que sí, que sí, que sí, para demostrármelo, de repente, abre las piernas haciendo el puto espagueti y rebota el culo contra el suelo haciendo el espagueti. | AS15: 1. Reproduction | AT15: Direct Translation | AU15: YES | AV15: SAME | AX15: Estoy teniendo un recuerdo de Vietnam, chicas. Estuve en una discoteca muy gay, que no diré el nombre, y un tío de 50 años intentó ligar conmigo durante 50 horas seguidas, yo intentando hacerle ver que no, y me dijo, "yo soy bailarín, no sé qué, bailamos", y yo así, que no, que no, que no, y yo que no, y él, que sí, que sí, que sí, que sí, para demostrármelo, de repente, abre las piernas haciendo el puto espagueti y rebota el culo contra el suelo haciendo el espagueti. | AY15: 1. Reproduction | AZ15: Direct Translation | BA15: YES | BB15: SAME | BD15: Estoy teniendo un recuerdo de Vietnam, chicas. Estuve en una discoteca muy gay, que no diré el nombre, y un tío de 50 años intentó ligar conmigo durante 50 horas seguidas, yo intentando hacerle ver que no, y me dijo, "yo soy bailarín, no sé qué, bailamos", y yo así, que no, que no, que no, y yo que no, y él, que sí, que sí, que sí, que sí, para demostrármelo, de repente, abre las piernas haciendo el puto espagueti y rebota el culo contra el suelo haciendo el espagueti. | BE15: 1. Reproduction | BF15: Direct Translation | BG15: YES | BH15: SAME | BJ15: Estoy teniendo un recuerdo de Vietnam, chicas. Estuve en una discoteca muy gay, que no diré el nombre, y un tío de 50 años intentó ligarme durante 50 horas seguidas, yo intentando hacerle entender que no, y me dijo, "yo soy bailarín, no sé qué, bailamos", y yo así, que no, que no, que no, y yo que no, y él, que sí, que sí, que sí, que sí, para demostrármelo, de repente, abre las piernas haciendo el puto espagueti y rebota el culo contra el suelo haciendo el espagueti. | BK15: 1. Reproduction | BL15: Direct Translation | BM15: YES | BN15: SAME | BP15: Estoy teniendo un recuerdo de Vietnam, niñas. Estuve en una discoteca muy gay, que no voy a nombrar, y un tío de 50 años intentó ligar conmigo 50 horas seguidas, yo intentando hacerle ver que no, y me dijo, yo soy bailarín, no sé qué, bailemos, y yo así, que no, que no, que no, y yo que no, y él, que sí, que sí, que sí, que sí, de repente, abre las piernas haciendo el puto split y rebotando el culo contra el suelo haciendo el split. | BQ15: 1. Reproduction | BR15: Direct Translation | BS15: YES | BT15: SAME | BV15: Estoy teniendo un recuerdo de Vietnam, niñas. Estuve en una discoteca muy gay, que no voy a decir el nombre, y un tío de 50 años intentó ligar conmigo 50 horas seguidas, yo intentando hacerle ver que no, y me ha dicho, yo soy bailarín, no sé qué, bailemos, y yo así, que no, que no, que no, y yo que no, y él, que sí, que sí, que sí, que sí, para demostrarmelo, de repente, abre las piernas haciendo el puto espagat y rebotando el culo contra el suelo haciendo el espagat. | BW15: 1. Reproduction | BX15: Direct Translation | BY15: YES | BZ15: SAME | CB15: Estoy teniendo un recuerdo de Vietnam, niñas. Estuve en una discoteca muy gay, que no diré el nombre, y un tío de 50 años intentó ligar conmigo 50 horas seguidas, yo intentando hacerle ver que no, y me ha dicho, yo soy bailarín, no sé qué, bailemos, y yo así, que no, que no, que no, y yo que no, y él, que sí, que sí, que sí, que sí, de repente, abre las piernas haciendo el puto split y rebotando el culo contra el suelo haciendo el split. | CC15: 1. Reproduction | CD15: Direct Translation | CE15: YES | CF15: SAME | CH15: Estoy teniendo un recuerdo de Vietnam, chicas. Estuve en una discoteca muy gay, que no voy a nombrar, y un tío de 50 años intentó ligar conmigo durante 50 horas seguidas, yo tratando de hacerle ver que no, y me dijo, yo soy bailarín, no sé qué, bailemos, y yo así, que no, que no, que no, y yo que no, y él, que sí, que sí, que sí, que sí, de repente, abre las piernas haciendo el puto split y rebotando el culo contra el suelo haciendo el split. | CI15: 1. Reproduction | CJ15: Direct Translation | CK15: YES | CL15: SAME | CN15: Estaba recordando Vietnam, chicas. Estuve en una discoteca muy gay, que no voy a nombrar, y un tío de 50 años intentó ligar conmigo durante 50 horas seguidas, yo intentando hacerle ver que no, y me dijo, yo soy bailarín, no sé qué, bailemos, y yo así, que no, que no, que no, y yo que no, y él, que sí, que sí, que sí, que sí, de repente, abre las piernas haciendo el puto split y rebotando el culo contra el suelo haciendo el split. | CO15: 4. Creative Shifts | CP15: Abstraction – Superordinate Term | CQ15: NO
A16: [empieza tema de conversación] | B16: La meva conclusió és que no fer cringe també fa cringe, perquè vol dir que ets una persona amb molt NPC, amb una personalitat 0 definida. Jo crec que quan tu te la jugues a la vida i ets tu mateixa, en alguns moments fas cringe, ja està, victòries i derrotes, la vida consisteix en això. | C16: I no fer cringe mai, no fer cringe mai, és fer cringe. Perquè vol dir que ets una persona que se senta en un bar, simplement escolta i no té pors d'Instagram, sinó que té destacadors. | D16: La meva conclusió és que no fer cringe també fa cringe, perquè vol dir que ets una persona amb molt NPC, amb una personalitat 0 definida. Jo crec que quan tu te la jugues a la vida i ets tu mateixa, en alguns moments fas cringe, ja està, victòries i derrotes, la vida consisteix en això. | E16: 1. Lexicon and Vocabulary | F16: 1.6 | G16: References to popular culture and memes | H16: Mi conclusión es que no sentir vergüenza a veces también da vergüenza, porque significa que eres una persona muy "NPC", con una personalidad prácticamente inexistente. Creo que cuando te arriesgas en la vida y eres tú misma, a veces puedes sentir vergüenza, y eso está bien, son victorias y derrotas, la vida consiste en eso. | I16: 1. Reproduction | J16: Direct Translation | K16: YES | L16: SAME | N16: Mi conclusión es que no ser "cringe" también puede ser "cringe", porque significa que eres una persona muy "NPC", con una personalidad prácticamente inexistente. Yo creo que cuando te arriesgas en la vida y eres tú mismo, a veces puedes resultar "cringe", y eso está bien, son victorias y derrotas, la vida consiste en eso. | O16: 1. Reproduction | P16: Direct Translation | Q16: YES | R16: SAME | T16: Mi conclusión es que no "hacer cringe" también da "cringe", porque significa que eres una persona con mucho de "NPC", con una personalidad 0 definida. Yo creo que cuando te arriesgas en la vida y eres tú misma, a veces das "cringe", y eso está bien, victorias y derrotas, la vida consiste en eso. | U16: 3. Errors | W16: NO | Z16: Mi conclusión es que no sentir vergüenza a veces también da vergüenza, porque significa que eres una persona muy "NPC", con una personalidad prácticamente inexistente. Creo que cuando uno se arriesga en la vida y es auténtico, a veces uno hace cosas que dan vergüenza, y eso está bien. La vida consiste en eso, en victorias y derrotas. | AA16: 1. Reproduction | AB16: Direct Translation | AC16: YES | AD16: SAME | AF16: Mi conclusión es que no sentir vergüenza a veces también da vergüenza, porque significa que eres una persona muy "NPC", con una personalidad prácticamente inexistente. Creo que cuando uno se arriesga en la vida y es auténtico, a veces uno hace cosas que dan vergüenza, y eso está bien, son victorias y derrotas, la vida consiste en eso. | AG16: 1. Reproduction | AH16: Direct Translation | AI16: YES | AJ16: SAME | AL16: Mi conclusión es que no hacer cringe también es cringe, porque significa que eres una persona con mucho NPC, con una personalidad totalmente definida. Yo creo que cuando te juegas la vida y eres tú misma, en algunos momentos haces cringe, ya está, victorias y derrotas, la vida consiste en esto. | AM16: 3. Errors | AO16: NO | AR16: Mi conclusión es que no hacer cringe también hace cringe, porque significa que eres una persona con muy poca personalidad, con una personalidad totalmente indefinida. Yo creo que cuando te metes en la vida y eres tú misma, en algunos momentos haces cringe, ya está, victorias y derrotas, la vida consiste en esto. | AS16: 4. Creative Shifts | AT16: Abstraction – Paraphrase | AU16: NO | AX16: Mi conclusión es que no hacer cringe también da cringe, porque significa que eres una persona con mucho NPC, con una personalidad 0 definida. Yo creo que cuando tú te la juegas a la vida y eres tú misma, en algunos momentos haces cringe, ya está, victorias y derrotas, la vida consiste en esto. | AY16: 3. Errors | BA16: NO | BD16: Mi conclusión es que no hacer cringe también hace cringe, porque significa que eres una persona con muy poco NPC, con una personalidad sin definir. Yo creo que cuando te juegas la vida y eres tú misma, en algunos momentos haces cringe, ya está, victorias y derrotas, la vida consiste en esto. | BE16: 3. Errors | BG16: NO | BJ16: Mi conclusión es que no hacer cringe también hace cringe, porque significa que eres una persona con mucho NPC, con una personalidad totalmente indefinida. Yo creo que cuando te juegas la vida y eres tú misma, en algunos momentos haces cringe, ya está, hay victorias y derrotas, la vida consiste en esto. | BK16: 3. Errors | BM16: NO | BP16: Mi conclusión es que no hacer cringe también hace cringe, porque significa que eres una persona con mucha NPC, con una personalidad 0 definida. Yo creo que cuando tú te la juegas en la vida y eres tú misma, en algunos momentos haces cringe, ya está, victorias y derrotas, la vida consiste en eso. | BQ16: 3. Errors | BS16: NO | BV16: Mi conclusión es que no hacer cringe también hace cringe, porque significa que eres una persona con muy poca NPC, con una personalidad 0 definida. Yo creo que cuando tú te la juegas en la vida y eres tú misma, en algunos momentos haces cringe, ya está, victorias y derrotas, la vida consiste en eso. | BW16: 3. Errors | BY16: NO | CB16: Mi conclusión es que no hacer cringe también hace cringe, porque significa que eres una persona con mucha NPC, con una personalidad 0 definida. Yo creo que cuando tú te la juegas en la vida y eres tú misma, en algunos momentos haces cringe, ya está, victorias y derrotas, la vida consiste en eso. | CC16: 3. Errors | CE16: NO | CH16: Mi conclusión es que no hacer cringe también hace cringe, porque significa que eres una persona con mucha NPC, con una personalidad 0 definida. Yo creo que cuando tú te la juegas en la vida y eres tú misma, en algunos momentos haces cringe, ya está, victorias y derrotas, la vida consiste en eso. | CI16: 3. Errors | CK16: NO | CN16: Mi conclusión es que no hacer cringe también hace cringe, porque quiere decir que eres una persona con mucho NPC, con una personalidad 0 definida. Yo creo que cuando tú te la juegas en la vida y eres tú misma, en algunos momentos haces cringe, ya está, victorias y derrotas, la vida consiste en eso. | CO16: 3. Errors | CQ16: NO
A17: [empieza tema de conversación] | B17: A la vida hi ha d'haver una mica de salsa i de vegades, si no existeix, ja l'hi posem nosaltres. Què serien les converses amb amigues sense aquell punt d'exageració? Sense aquell detallet extra que afegeix una mica de suc a una xafarderia? | C17: Sense aquella emoció magnificada entremig de l'explicació sobre un ars de nivell totalment normal, l'exageració afegeix energia literaturesca a la vida i per això, depèn del context, podem gaudir-la molt o podem no gaudir-la gens. | D17: A la vida hi ha d'haver una mica de salsa i de vegades, si no existeix, ja l'hi posem nosaltres. Què serien les converses amb amigues sense aquell punt d'exageració? Sense aquell detallet extra que afegeix una mica de suc a una xafarderia? | E17: 1. Lexicon and Vocabulary | F17: 1.2 | G17: Colloquial lexicon and slang | H17: En la vida tiene que haber un poco de "sabor" y, a veces, si no existe, nosotros se lo añadimos. ¿Qué serían las conversaciones con amigas sin ese punto de exageración? ¿Sin ese pequeño detalle extra que le da un poco de "jugo" a un chisme? | I17: 4. Creative Shifts | J17: Abstraction – Superordinate Term | K17: NO | N17: En la vida tiene que haber un poco de "salsa", y a veces, si no existe, ya la añadimos nosotros. ¿Qué serían las conversaciones con amigas sin ese punto de exageración? ¿Sin ese detallito extra que añade un poco de sabor a un chismorreo? | O17: 1. Reproduction | P17: Direct Translation | Q17: YES | R17: SAME | T17: En la vida tiene que haber un poco de "salsa", y a veces, si no existe, ya se la ponemos nosotros. ¿Qué serían las conversaciones con amigas sin ese punto de exageración? ¿Sin ese detallito extra que añade un poco de "jugo" a un cotilleo? | U17: 4. Creative Shifts | V17: Abstraction – Superordinate Term | W17: YES | X17: LESS | Z17: En la vida, debe haber un poco de "sabor" y, a veces, si no existe, nosotros se lo añadimos. ¿Qué serían las conversaciones con amigas sin ese punto de exageración? ¿Sin ese detalle extra que le añade un poco de chispa a un chisme? | AA17: 4. Creative Shifts | AB17: Abstraction – Superordinate Term | AC17: YES | AD17: LESS | AF17: En la vida, tiene que haber un poco de "sabor" y, a veces, si no existe, nosotros se lo añadimos. ¿Qué serían las conversaciones con amigas sin ese punto de exageración? ¿Sin ese pequeño detalle extra que le da un poco de "jugo" a un chismorreo? | AG17: 1. Reproduction | AH17: Direct Translation | AI17: YES | AJ17: SAME | AL17: A la vida hay que tener un poco de salsa, y a veces, si no existe, ya la ponemos nosotros. ¿Qué serían las conversaciones con amigas sin ese toque de exageración? Sin ese detalle extra que le da un poco de sabor a una charla de cotilleos? | AM17: 4. Creative Shifts | AN17: Abstraction – Superordinate Term | AO17: YES | AP17: LESS | AR17: A la vida hay que haber un poco de salsa y a veces, si no existe, ya la ponemos nosotros. ¿Qué serían las conversaciones con amigas sin ese toque de exageración? Sin ese detalle extra que añade un poco de sabor a una chafarderia? | AS17: 1. Reproduction | AT17: Direct Translation | AU17: YES | AV17: SAME | AX17: A la vida hay que haber un poco de salsa y a veces, si no existe, ya la ponemos nosotros. ¿Qué serían las conversaciones con amigas sin ese toque de exageración? Sin ese detalle extra que añade un poco de sabor a una chafarderia? | AY17: 1. Reproduction | AZ17: Direct Translation | BA17: YES | BB17: SAME | BD17: A la vida hay que tener un poco de salsa, y a veces, si no existe, ya la ponemos nosotros. ¿Qué serían las conversas con amigas sin ese punto de exageración? Sin ese detalle extra que añade un poco de sabor a una chafarderia? | BE17: 1. Reproduction | BF17: Direct Translation | BG17: YES | BH17: SAME | BJ17: A la vida hay que tener un poco de salsa, y a veces, si no existe, ya la ponemos nosotros. ¿Qué serían las conversaciones con amigas sin ese toque de exageración? Sin ese detalle extra que añade un poco de sabor a una chisme? | BK17: 4. Creative Shifts | BL17: Abstraction – Superordinate Term | BM17: YES | BN17: LESS | BP17: En la vida debe haber un poco de picante y, a veces, si no existe, nosotros mismos se lo añadimos. ¿Qué serían las conversaciones con amigas sin ese punto de exageración? Sin ese detallito extra que añade un poco de sabor a un cotilleo? | BQ17: 4. Creative Shifts | BR17: Abstraction – Superordinate Term | BS17: YES | BT17: LESS | BV17: En la vida debe haber un poco de salsa y a veces, si no existe, nosotros mismos se la ponemos. ¿Qué serían las conversaciones con amigas sin ese punto de exageración? Sin ese detallito extra que añade un poco de jugo a una chismografía? | BW17: 1. Reproduction | BX17: Direct Translation | BY17: NO | CB17: En la vida tiene que haber un poco de salsa y a veces, si no existe, nosotros mismos se la ponemos. ¿Qué serían las conversaciones con amigas sin ese punto de exageración? Sin ese detallito extra que añade un poco de jugo a un cotilleo? | CC17: 4. Creative Shifts | CD17: Abstraction – Superordinate Term | CE17: YES | CF17: LESS | CH17: En la vida debe haber un poco de picante y, a veces, si no existe, nosotros mismos se lo añadimos. ¿Qué serían las conversaciones con amigas sin ese punto de exageración? Sin ese detallito extra que añade un poco de sabor a un chisme? | CI17: 4. Creative Shifts | CJ17: Abstraction – Superordinate Term | CK17: YES | CL17: LESS | CN17: A la vida hay que añadirle un poco de salsa y, a veces, si no existe, ya nos encargamos nosotros. ¿Qué serían las conversaciones con amigas sin ese punto de exageración? Sin ese detallito extra que añade un poco de jugo a una chismografía? | CO17: 1. Reproduction | CP17: Direct Translation | CQ17: NO
A18: [empieza tema de conversación] | B18: Després parlarem de ser businesswoman, que tu i jo en privat en parlem molt i en tinc moltes ganes. Abans, però, una cosa que a mi m'obsessiona de ser una girl és la intuïció femenina. Ull de sonada, mai falla la tirada. | C18: Expressió catalana. Un dia la volia dir en castellà a la ràdio, la vaig ficar al guió i la lingüista em va dir, mira, en català es diu així, i vaig dir: L'apuntem. | D18: Després parlarem de ser businesswoman, que tu i jo en privat en parlem molt i en tinc moltes ganes. Abans, però, una cosa que a mi m'obsessiona de ser una girl és la intuïció femenina. Ull de sonada, mai falla la tirada. | E18: 1. Lexicon and Vocabulary | F18: 1.4 | G18: Idiomatic expressions and colloquial phraseology | H18: Después hablaremos de ser empresaria, algo de lo que tú y yo hablamos mucho en privado y de lo que tengo muchas ganas. Pero antes, hay algo que me obsesiona de ser una mujer: la intuición femenina. "Ojo de cerradura", nunca falla. | I18: 3. Errors | K18: NO | N18: Después hablaremos de ser empresarias, que tú y yo lo hablamos mucho en privado y tengo muchas ganas de hablar de eso. Pero antes, hay algo que me obsesiona de ser una mujer: la intuición femenina. "Ull de sonada", nunca falla. | O18: 3. Errors | Q18: NO | T18: Después hablaremos de ser empresaria, que tú y yo en privado lo hablamos mucho y tengo muchas ganas. Pero antes, algo que a mí me obsesiona de ser una "girl" es la intuición femenina. "Ull de sonada", nunca falla. | U18: 3. Errors | W18: NO | Z18: Después hablaremos de ser empresaria, algo de lo que tú y yo hablamos mucho en privado y de lo que tengo muchas ganas. Pero antes, una cosa que me obsesiona de ser una mujer es la intuición femenina. "Ojo de buena", nunca falla. | AA18: 3. Errors | AC18: NO | AF18: Después hablaremos de ser empresaria, algo de lo que tú y yo hablamos mucho en privado y de lo que tengo muchas ganas. Pero antes, hay algo que me obsesiona de ser una "girl": la intuición femenina. "Ojo de halcón", nunca falla. | AG18: 3. Errors | AI18: NO | AL18: También hablaremos de ser emprendedora, algo que tú y yo hablamos mucho en privado y de lo que tengo mucha ganas. Pero antes, una cosa que me obsesiona de ser mujer es la intuición femenina. Ojo de sonada, nunca falla la tirada. | AM18: 1. Reproduction | AN18: Direct Translation | AO18: NO | AR18: Después hablaremos de ser businesswoman, que tú y yo en privado lo hablamos mucho y tengo muchas ganas. Antes, sin embargo, una cosa que a mí me obsesiona de ser una chica es la intuición femenina. Ull de sonada, nunca falla la tirada. | AS18: 1. Reproduction | AT18: Retention | AU18: NO | AX18: Después hablaremos de ser businesswoman, que tú y yo en privado lo hablamos mucho y tengo muchas ganas. Antes, sin embargo, una cosa que a mí me obsesiona de ser una chica es la intuición femenina. Ojo de sonada, nunca falla la tirada. | AY18: 1. Reproduction | AZ18: Direct Translation | BA18: NO | BD18: Después hablaremos de ser empresaria, que tú y yo en privado lo hablamos mucho y tengo muchas ganas de hacerlo. Pero antes, una cosa que me obsesiona de ser una chica es la intuición femenina. Ojo de sonada, nunca falla la tirada. | BE18: 1. Reproduction | BF18: Direct Translation | BG18: NO | BJ18: Después hablaremos de ser businesswoman, que tú y yo en privado lo hablamos mucho y me encantaría hacerlo. Antes, sin embargo, hay algo que me obsesiona sobre ser una chica: la intuición femenina. Ull de sonada, nunca falla la tirada. | BK18: 1. Reproduction | BL18: Retention | BM18: NO | BP18: Después hablaremos de ser mujer de negocios, que tú y yo hablamos mucho de eso en privado y tengo muchas ganas. Antes, sin embargo, algo que me obsesiona de ser una chica es la intuición femenina. Ojo de la bruja, nunca falla la tirada. | BQ18: 1. Reproduction | BR18: Direct Translation | BS18: NO | BV18: Después hablaremos de ser businesswoman, que tú y yo en privado hablamos mucho de ello y tengo muchas ganas. Antes, sin embargo, una cosa que a mí me obsesiona de ser una chica es la intuición femenina. Ojo de sonada, nunca falla la tirada. | BW18: 1. Reproduction | BX18: Direct Translation | BY18: NO | CB18: Después hablaremos de ser businesswoman, que tú y yo en privado hablamos mucho de ello y tengo muchas ganas. Antes, sin embargo, una cosa que a mí me obsesiona de ser una chica es la intuición femenina. Ojo de sonada, nunca falla la tirada. | CC18: 1. Reproduction | CD18: Direct Translation | CE18: NO | CH18: Después hablaremos de ser mujer de negocios, que tú y yo en privado hablamos mucho de ello y tengo muchas ganas. Antes, sin embargo, algo que me obsesiona de ser una chica es la intuición femenina. ¡Ojo de bruja, nunca falla la tirada! | CI18: 1. Reproduction | CJ18: Direct Translation | CK18: NO | CN18: Después hablaremos de ser businesswoman, que tú y yo en privado hablamos mucho y tengo muchas ganas. Antes, pero, una cosa que a mí me obsesiona de ser una chica es la intuición femenina. Ojo de sonada, nunca falla la tirada. | CO18: 1. Reproduction | CP18: Direct Translation | CQ18: NO
A19: [empieza tema de conversación] | B19: També és molt important per a l'amistat, i jo pensava que no, i no ho entenia, l'admiració. Perquè jo sempre havia escoltat allò de, és molt important admirar la gent del teu entorn, i jo pensava, xd, jo a la meva amiga Laura, no l'admiro, amb la meva puta mare fent viures, però no l'admiro. | C19: Però ara, que et vas fent gran i cada cop tens menys amigues, el cercle es redueix, que a mi m'encanta, és la millor sensació del món, o sigui, fer lligams més forts i no tants | D19: També és molt important per a l'amistat, i jo pensava que no, i no ho entenia, l'admiració. Perquè jo sempre havia escoltat allò de, és molt important admirar la gent del teu entorn, i jo pensava, xd, jo a la meva amiga Laura, no l'admiro, amb la meva puta mare fent viures, però no l'admiro. | E19: 1. Lexicon and Vocabulary | F19: 1.6 | G19: References to popular culture and memes | H19: También es muy importante para la amistad, y yo pensaba que no, y no lo entendía, la admiración. Porque yo siempre había escuchado eso de que es muy importante admirar a la gente de tu entorno, y yo pensaba, ¿en serio?, a mi amiga Laura, no la admiro, con mi propia madre luchando por sobrevivir, pero no la admiro. | I19: 4. Creative Shifts | J19: Abstraction – Paraphrase | K19: NO | N19: También es muy importante para la amistad, y yo pensaba que no, y no lo entendía, la admiración. Porque yo siempre había escuchado eso de que es muy importante admirar a la gente de tu entorno, y yo pensaba, ¿en serio?, a mi amiga Laura, no la admiro, con mi puta madre trabajando, pero no la admiro. | O19: 4. Creative Shifts | P19: Abstraction – Paraphrase | Q19: NO | T19: También es muy importante para la amistad, y yo pensaba que no, y no lo entendía, la admiración. Porque yo siempre había escuchado eso de, es muy importante admirar a la gente de tu entorno, y yo pensaba, ¿en serio?, a mi amiga Laura, no la admiro, con mi puta madre trabajando, pero no la admiro. | U19: 4. Creative Shifts | V19: Abstraction – Paraphrase | W19: NO | Z19: También es muy importante para la amistad, y yo pensaba que no, y no lo entendía, la admiración. Porque siempre había escuchado eso de que es muy importante admirar a la gente de tu entorno, y yo pensaba, ja, a mi amiga Laura, no la admiro, con mi puta madre trabajando, pero no la admiro. | AA19: 4. Creative Shifts | AB19: Abstraction – Paraphrase | AC19: NO | AF19: También es muy importante para la amistad, y yo pensaba que no, y no lo entendía, la admiración. Porque yo siempre había escuchado eso de que es muy importante admirar a la gente de tu entorno, y yo pensaba, ¿en serio?, a mi amiga Laura, no la admiro, con mi puta madre trabajando, pero no la admiro. | AG19: 4. Creative Shifts | AH19: Abstraction – Paraphrase | AI19: NO | AL19: También es muy importante para la amistad, y yo pensaba que no, y no lo entendía, la admiración. Porque siempre había escuchado eso de que es muy importante admirar a la gente de tu entorno, y yo pensaba, xd, yo con mi amiga Laura, no la admiro, con mi puta madre haciendo vida, pero no la admiro. | AM19: 1. Reproduction | AN19: Direct Translation | AO19: YES | AP19: SAME | AR19: También es muy importante para la amistad, y yo pensaba que no, y no lo entendía, la admiración. Porque yo siempre había escuchado aquello de, es muy importante admirar a la gente de tu entorno, y yo pensaba, xd, yo con mi amiga Laura, no la admiro, con mi puta madre haciendo vidas, pero no la admiro. | AS19: 1. Reproduction | AT19: Direct Translation | AU19: YES | AV19: SAME | AX19: También es muy importante para la amistad, y yo pensaba que no, y no lo entendía, la admiración. Porque yo siempre había oído aquello de, es muy importante admirar a la gente de tu entorno, y yo pensaba, xd, yo con mi amiga Laura, no la admiro, con mi puta madre haciendo vida, pero no la admiro. | AY19: 1. Reproduction | AZ19: Direct Translation | BA19: YES | BB19: SAME | BD19: También es muy importante para la amistad, y yo pensaba que no, y no lo entendía, la admiración. Porque yo siempre había escuchado eso de, es muy importante admirar a la gente de tu entorno, y yo pensaba, xd, yo a mi amiga Laura, no la admiro, con mi puta madre haciendo vidas, pero no la admiro. | BE19: 1. Reproduction | BF19: Direct Translation | BG19: YES | BH19: SAME | BJ19: También es muy importante para la amistad, y yo pensaba que no, y no lo entendía, la admiración. Porque siempre había oído eso de que es muy importante admirar a la gente de tu entorno, y yo pensaba, xd, yo con mi amiga Laura, no la admiro, con mi puta madre haciendo viernes, pero no la admiro. | BK19: 1. Reproduction | BL19: Direct Translation | BM19: YES | BN19: SAME | BP19: También es muy importante para la amistad, y yo pensaba que no, y no lo entendía, la admiración. Porque yo siempre había escuchado aquello de, es muy importante admirar a la gente de tu entorno, y yo pensaba, xd, yo a mi amiga Laura, no la admiro, con mi puta madre haciendo viures, pero no la admiro. | BQ19: 1. Reproduction | BR19: Direct Translation | BS19: YES | BT19: SAME | BV19: También es muy importante para la amistad, y yo pensaba que no, y no lo entendía, la admiración. Porque yo siempre había escuchado aquello de, es muy importante admirar a la gente de tu entorno, y yo pensaba, xd, yo a mi amiga Laura, no la admiro, con mi puta madre haciendo viures, pero no la admiro. | BW19: 1. Reproduction | BX19: Direct Translation | BY19: YES | BZ19: SAME | CB19: También es muy importante para la amistad, y yo pensaba que no, y no lo entendía, la admiración. Porque yo siempre había escuchado aquello de, es muy importante admirar a la gente de tu entorno, y yo pensaba, xd, yo a mi amiga Laura, no la admiro, con mi puta madre haciendo viures, pero no la admiro. | CC19: 1. Reproduction | CD19: Direct Translation | CE19: YES | CF19: SAME | CH19: También es muy importante para la amistad, y yo pensaba que no, y no lo entendía, la admiración. Porque yo siempre había escuchado aquello de, es muy importante admirar a la gente de tu entorno, y yo pensaba, xd, yo a mi amiga Laura, no la admiro, con mi puta madre haciendo viures, pero no la admiro. | CI19: 1. Reproduction | CJ19: Direct Translation | CK19: YES | CL19: SAME | CN19: También es muy importante para la amistad, y yo pensaba que no, y no lo entendía, la admiración. Porque yo siempre había escuchado aquello de, es muy importante admirar a la gente de tu entorno, y yo pensaba, xd, yo a mi amiga Laura, no la admiro, con mi puta madre haciendo viures, pero no la admiro. | CO19: 1. Reproduction | CP19: Direct Translation | CQ19: YES | CR19: SAME
A20: [empieza tema de conversación] | B20: És tan difícil ser un tio. La corba d'aprenentatge sexualment i afectivament és, primer, és tot molt jajajiji i després 0. En plan, no saps ni el que li agrada al teu amic, ni el que sent el teu amic, ni res. En plan, ets un adolescent, passes a ser un home o passes a ser un projecte d'home i després ja, ningú parla de sentiments. | C20: És com que si fóssiu, o sigui, socialment se us obliga a ser pedres. Perquè a més, jo, amics tios em diuen, és que jo amb el meu amic no hem parlat mai dels nostres problemes, en plan, hi ha molts homes que utilitzen l'amistat femenina per desafogar-se. | D20: És tan difícil ser un tio. La corba d'aprenentatge sexualment i afectivament és, primer, és tot molt jajajiji i després 0. En plan, no saps ni el que li agrada al teu amic, ni el que sent el teu amic, ni res. En plan, ets un adolescent, passes a ser un home o passes a ser un projecte d'home i després ja, ningú parla de sentiments. | E20: 1. Lexicon and Vocabulary | F20: 1.7 | G20: Onomatopoeia and sound representation | H20: Es tan difícil ser hombre. La curva de aprendizaje, tanto sexual como afectivamente, es así: al principio, todo es muy "jajajiji" y luego, cero. En serio, ni siquiera sabes qué le gusta a tu amigo, ni lo que siente, nada. Estás en la adolescencia, luego pasas a ser un hombre, o pasas a ser un "proyecto de hombre", y después ya, nadie habla de sentimientos. | I20: 1. Reproduction | J20: Direct Translation | K20: YES | L20: SAME | N20: Es tan difícil ser un tío. La curva de aprendizaje, tanto sexual como afectivamente, es esta: al principio, todo es muy fácil, jajajaja, y luego, cero. Es decir, ni siquiera sabes qué le gusta a tu amigo, ni qué siente, ni nada. Estás en la adolescencia, de repente te conviertes en un hombre, o en un "proyecto de hombre", y luego, ya, nadie habla de sentimientos. | O20: 4. Creative Shifts | P20: Abstraction – Superordinate Term | Q20: YES | R20: SAME | T20: Es tan difícil ser hombre. La curva de aprendizaje, tanto sexual como afectivamente, es esta: al principio, todo es "jajajaja", y luego, cero. En plan, ni siquiera sabes qué le gusta a tu amigo, ni qué siente tu amigo, ni nada. Es que eres un adolescente, pasas a ser un hombre o pasas a ser un proyecto de hombre, y luego, ya, nadie habla de sentimientos. | U20: 4. Creative Shifts | V20: Abstraction – Superordinate Term | W20: YES | X20: SAME | Z20: Es muy difícil ser hombre. La curva de aprendizaje, tanto sexual como afectivamente, es así: al principio, todo es muy gracioso, jajajiji, y luego, cero. En serio, ni siquiera sabes qué le gusta a tu amigo, ni qué siente tu amigo, nada. Estás en la adolescencia, luego te conviertes en un hombre, o en un "proyecto de hombre", y después ya nadie habla de sentimientos. Es como si, socialmente, se os obligara a ser insensibles. Además, amigos míos, otros hombres, me dicen que nunca han hablado con sus amigos de sus | AA20: 1. Reproduction | AB20: Direct Translation | AC20: YES | AD20: SAME | AF20: Es tan difícil ser hombre. La curva de aprendizaje, tanto sexual como afectivamente, es así: al principio, todo es muy "jajajiji" y luego, cero. En plan, ni siquiera sabes qué le gusta a tu amigo, ni qué siente, nada. Estás en la adolescencia, pasas a ser un hombre, o pasas a ser un "proyecto de hombre", y luego, ya, nadie habla de sentimientos. | AG20: 1. Reproduction | AH20: Direct Translation | AI20: YES | AJ20: SAME | AL20: Es tan difícil ser un tío. La curva de aprendizaje sexual y afectivamente es, primero, todo jajajiji y después 0. En plan, no sabes ni lo que le gusta a tu amigo, ni lo que siente tu amigo, ni nada. En plan, eres un adolescente, pasas a ser un hombre o pasas a ser un proyecto de hombre y después ya, nadie habla de sentimientos. | AM20: 1. Reproduction | AN20: Direct Translation | AO20: YES | AP20: SAME | AR20: Es tan difícil ser un tío. La curva de aprendizaje sexual y afectivamente es, primero, todo jajajiji y después 0. En plan, no sabes ni lo que le gusta a tu amigo, ni lo que siente tu amigo, ni nada. En plan, eres un adolescente, pasas a ser un hombre o pasas a ser un proyecto de hombre y después ya, nadie habla de sentimientos. | AS20: 1. Reproduction | AT20: Direct Translation | AU20: YES | AV20: SAME | AX20: Es tan difícil ser un tío. La curva de aprendizaje sexual y afectivamente es, primero, es todo muy jajajiji y después 0. En plan, no sabes ni lo que le gusta a tu amigo, ni lo que siente tu amigo, ni nada. En plan, eres un adolescente, pasas a ser un hombre o pasas a ser un proyecto de hombre y después ya, nadie habla de sentimientos. | AY20: 1. Reproduction | AZ20: Direct Translation | BA20: YES | BB20: SAME | BD20: Es tan difícil ser un tío. La curva de aprendizaje sexual y afectivamente es, primero, todo jajajiji y después 0. En plan, no sabes ni lo que le gusta a tu amigo, ni lo que siente tu amigo, ni nada. En plan, eres un adolescente, pasas a ser un hombre o pasas a ser un proyecto de hombre y después ya, nadie habla de sentimientos. | BE20: 1. Reproduction | BF20: Direct Translation | BG20: YES | BH20: SAME | BJ20: Es tan difícil ser un tío. La curva de aprendizaje sexual y afectivamente es, primero, todo jajajiji y después 0. En plan, no sabes ni lo que le gusta a tu amigo, ni lo que siente tu amigo, ni nada. En plan, eres un adolescente, pasas a ser un hombre o pasas a ser un proyecto de hombre y después ya, nadie habla de sentimientos. | BK20: 1. Reproduction | BL20: Direct Translation | BM20: YES | BN20: SAME | BP20: Es tan difícil ser un hombre. La curva de aprendizaje sexual y emocional es, primero, es todo muy jajajiji y después 0. En plan, no sabes ni lo que le gusta a tu amigo, ni lo que siente tu amigo, ni nada. En plan, eres un adolescente, pasas a ser un hombre o pasas a ser un proyecto de hombre y después ya, nadie habla de sentimientos. | BQ20: 1. Reproduction | BR20: Direct Translation | BS20: YES | BT20: SAME | BV20: Es tan difícil ser un tío. La curva de aprendizaje sexual y emocional es, primero, es todo muy jajajiji y después 0. En plan, no sabes ni lo que le gusta a tu amigo, ni lo que siente tu amigo, ni nada. En plan, eres un adolescente, pasas a ser un hombre o pasas a ser un proyecto de hombre y después ya, nadie habla de sentimientos. | BW20: 1. Reproduction | BX20: Direct Translation | BY20: YES | BZ20: SAME | CB20: Es tan difícil ser un tío. La curva de aprendizaje sexual y emocional es, primero, todo muy jajajiji y después 0. En plan, no sabes ni lo que le gusta a tu amigo, ni lo que siente tu amigo, ni nada. En plan, eres un adolescente, pasas a ser un hombre o pasas a ser un proyecto de hombre y después ya, nadie habla de sentimientos. | CC20: 1. Reproduction | CD20: Direct Translation | CE20: YES | CF20: SAME | CH20: Es tan difícil ser un hombre. La curva de aprendizaje sexual y emocional es, primero, es todo muy jajajiji y después 0. En plan, no sabes ni lo que le gusta a tu amigo, ni lo que siente tu amigo, ni nada. En plan, eres un adolescente, pasas a ser un hombre o pasas a ser un proyecto de hombre y después ya, nadie habla de sentimientos. | CI20: 1. Reproduction | CJ20: Direct Translation | CK20: YES | CL20: SAME | CN20: Es tan difícil ser un tío. La curva de aprendizaje sexual y emocional es, primero, es todo muy jajajiji y después 0. En plan, no sabes ni lo que le gusta a tu amigo, ni lo que siente tu amigo, ni nada. En plan, eres un adolescente, pasas a ser un hombre o pasas a ser un proyecto de hombre y después ya, nadie habla de sentimientos. | CO20: 1. Reproduction | CP20: Direct Translation | CQ20: YES | CR20: SAME
A21: [empieza tema de conversación] | B21: Tot i que l'amistat femenina té hàndicaps. Té molts hàndicaps. Com per exemple, i ara obrim el gran meló que tenia moltes ganes d'obrir, la competència entre dones. | C21: Les ties som les més maques, les més simpàtiques, però per culpa, en cap cas per culpa nostra, no vull treure pelotes fora, però vull dir, a nivell social, evidentment encara hi ha molta misogínia, llavors hi ha una competència molt bèstia, i jo me'n recordo que jo de petita era superenvejosa. | D21: Tot i que l'amistat femenina té hàndicaps. Té molts hàndicaps. Com per exemple, i ara obrim el gran meló que tenia moltes ganes d'obrir, la competència entre dones. | E21: 1. Lexicon and Vocabulary | F21: 1.4 | G21: Idiomatic expressions and colloquial phraseology | H21: Aunque la amistad entre mujeres tiene sus dificultades. Tiene muchas dificultades. Por ejemplo, y ahora vamos a abordar un tema del que tenía muchas ganas de hablar, la competencia entre mujeres. | I21: 4. Creative Shifts | J21: Abstraction – Paraphrase | K21: NO | N21: Aunque la amistad femenina tiene sus dificultades. Tiene muchos obstáculos. Por ejemplo, y ahora voy a tocar un tema del que tenía muchas ganas de hablar, la competencia entre mujeres. | O21: 4. Creative Shifts | P21: Abstraction – Paraphrase | Q21: NO | T21: Aunque la amistad femenina tiene sus dificultades. Tiene muchos inconvenientes. Por ejemplo, y ahora abro ese tema del que tenía muchas ganas de hablar, la competencia entre mujeres. | U21: 4. Creative Shifts | V21: Abstraction – Paraphrase | W21: NO | Z21: Aunque la amistad femenina tiene sus dificultades. Tiene muchas dificultades. Por ejemplo, y ahora abrimos ese tema del que tenía muchas ganas de hablar, la competencia entre mujeres. | AA21: 4. Creative Shifts | AB21: Abstraction – Paraphrase | AC21: NO | AF21: Aunque la amistad femenina tiene sus desafíos. Tiene muchos desafíos. Por ejemplo, y ahora vamos a abordar un tema del que tenía muchas ganas de hablar, la competencia entre mujeres. | AG21: 4. Creative Shifts | AH21: Abstraction – Paraphrase | AI21: NO | AL21: Aunque la amistad femenina tiene sus problemas. Tiene muchos problemas. Por ejemplo, ahora abrimos el gran tema que llevaba mucho tiempo queriendo abrir, la competencia entre mujeres. | AM21: 4. Creative Shifts | AN21: Abstraction – Paraphrase | AO21: NO | AR21: Aunque la amistad femenina tiene muchos problemas. Tiene muchos problemas. Por ejemplo, y ahora abrimos el gran tema que tenía muchas ganas de abrir, la competencia entre mujeres. | AS21: 4. Creative Shifts | AT21: Abstraction – Paraphrase | AU21: NO | AX21: Aunque la amistad femenina tiene muchos problemas. Tiene muchos problemas. Por ejemplo, y ahora abrimos el gran tema que tenía muchas ganas de abrir, la competencia entre mujeres. | AY21: 4. Creative Shifts | AZ21: Abstraction – Paraphrase | BA21: NO | BD21: Aunque la amistad entre mujeres tiene problemas. Tiene muchos problemas. Por ejemplo, ahora abrimos el gran tema que llevábamos tiempo queriendo abordar, la competencia entre mujeres. | BE21: 4. Creative Shifts | BF21: Abstraction – Paraphrase | BG21: NO | BJ21: Aunque la amistad entre chicas tiene sus problemas. Tiene muchos problemas. Por ejemplo, ahora abrimos el gran tema que llevaba mucho tiempo queriendo abordar, la competencia entre mujeres. | BK21: 4. Creative Shifts | BL21: Abstraction – Paraphrase | BM21: NO | BP21: A pesar de que la amistad femenina tiene desventajas. Tiene muchas desventajas. Como por ejemplo, y ahora abrimos el gran melón que tenía muchas ganas de abrir, la competencia entre mujeres. | BQ21: 1. Reproduction | BR21: Direct Translation | BS21: YES | BT21: SAME | BV21: Aunque la amistad femenina tiene desventajas. Tiene muchas desventajas. Como, por ejemplo, y ahora abrimos el gran melón que tenía muchas ganas de abrir, la competencia entre mujeres. | BW21: 1. Reproduction | BX21: Direct Translation | BY21: YES | BZ21: SAME | CB21: A pesar de que la amistad femenina tiene desventajas. Tiene muchas desventajas. Como por ejemplo, y ahora abrimos el gran melón que tenía muchas ganas de abrir, la competencia entre mujeres. | CC21: 1. Reproduction | CD21: Direct Translation | CE21: YES | CF21: SAME | CH21: A pesar de que la amistad femenina tiene desventajas. Tiene muchas desventajas. Como por ejemplo, y ahora abrimos el gran melón que tenía muchas ganas de abrir, la competencia entre mujeres. | CI21: 1. Reproduction | CJ21: Direct Translation | CK21: YES | CL21: SAME | CN21: A pesar de que la amistad femenina tiene desventajas. Tiene muchas desventajas. Como por ejemplo, y ahora abrimos el gran melón que tenía muchas ganas de abrir, la competencia entre mujeres. | CO21: 1. Reproduction | CP21: Direct Translation | CQ21: YES | CR21: SAME
A22: [empieza tema de conversación] | B22: Creus que seràs milionària? Tens una intuïció dintre que dius, podria passar? O te la suda totalment i ni hi penses? | C22: No hi penso tant, he de dir. O sigui, jo, mentre tingui una casa, estigui tranquil·la, i visqui, doncs, això, tranquil·la, no que m'hagi de preocupar, no soc gaire més ambiciós amb els diners, crec, en aquest sentit. Crec que amb això, tenint un pis així assegurat i més tranquil·la, ja estic bé. | D22: Creus que seràs milionària? Tens una intuïció dintre que dius, podria passar? O te la suda totalment i ni hi penses? | E22: 1. Lexicon and Vocabulary | F22: 1.2 | G22: Colloquial lexicon and slang | H22: ¿Crees que serás millonaria? ¿Tienes alguna intuición, como diciendo, que podría pasar? ¿O te da igual por completo y ni siquiera lo piensas? | I22: 4. Creative Shifts | J22: Abstraction – Paraphrase | K22: NO | N22: ¿Crees que serás millonaria? ¿Tienes una intuición, o sea, crees que podría pasar? ¿O te da igual por completo y ni siquiera lo piensas? | O22: 4. Creative Shifts | P22: Abstraction – Paraphrase | Q22: NO | T22: ¿Crees que serás millonaria? ¿Tienes alguna intuición, digo, podría pasar? ¿O te da igual por completo y ni siquiera lo piensas? | U22: 4. Creative Shifts | V22: Abstraction – Paraphrase | W22: NO | Z22: ¿Crees que serás millonaria? ¿Tienes esa intuición, esa corazonada, que te dice que podría pasar? ¿O te da igual por completo y ni siquiera lo piensas? | AA22: 4. Creative Shifts | AB22: Abstraction – Paraphrase | AC22: NO | AF22: ¿Crees que te harás millonaria? ¿Tienes esa intuición, esa corazonada, que te dice que podría pasar? ¿O te da igual por completo y ni siquiera lo piensas? | AG22: 4. Creative Shifts | AH22: Abstraction – Paraphrase | AI22: NO | AL22: ¿Crees que serás millonaria? ¿Tienes una intuición dentro que te dice que podría pasar, o te lo sudas totalmente y ni siquiera lo piensas? | AM22: 3. Errors | AO22: NO | AR22: ¿Crees que serás millonaria? Tienes una intuición dentro que digas, podría pasar? O te la sudas totalmente y ni siquiera piensas en ello? | AS22: 3. Errors | AU22: NO | AX22: Crees que serás millonaria? Tienes una intuición dentro que dices, podría pasar? O te la suda totalmente y ni piensas en ello? | AY22: 1. Reproduction | AZ22: Direct Translation | BA22: YES | BB22: SAME | BD22: ¿Crees que serás millonaria? Tienes una intuición dentro que dices, ¿podría pasar? O te la sudas totalmente y ni siquiera piensas en ello? | BE22: 3. Errors | BG22: NO | BJ22: Crees que llegarás a ser millonaria? Tienes una intuición dentro que te dice, podría pasar? O te lo sudas totalmente y ni siquiera lo piensas? | BK22: 3. Errors | BM22: NO | BP22: ¿Crees que serás millonaria? ¿Tienes una corazonada que dice, podría pasar? ¿O te suda totalmente y ni piensas en ello? | BQ22: 3. Errors | BS22: NO | BV22: Crees que serás millonaria? Tienes una intuición dentro que dices, podría pasar? O te la suda totalmente y ni piensas en ello? | BW22: 1. Reproduction | BX22: Direct Translation | BY22: YES | BZ22: SAME | CB22: ¿Crees que serás millonaria? ¿Tienes una corazonada que te dice que podría pasar? ¿O te suda totalmente y ni piensas en ello? | CC22: 3. Errors | CE22: NO | CH22: ¿Crees que serás millonaria? ¿Tienes una corazonada que te dice que podría pasar? ¿O te suda totalmente y ni piensas en ello? | CI22: 3. Errors | CK22: NO | CN22: Crees que serás millonaria? Tienes una intuición dentro que dices, podría pasar? O te la suda totalmente y ni piensas en ello? | CO22: 1. Reproduction | CP22: Direct Translation | CQ22: YES | CR22: SAME
A23: [empieza tema de conversación] | B23: T'he de dir que se't nota que has passat com un moment de revelació on has no dic que haguessin perdut valor, però com a mínim que els has donat molta importància a les amigues, perquè el disc que has publicat, si jo quan el vaig sentir, vaig pensar és un disc absolutament d'amor, però d'amor a les amigues. Em va semblar superbonic. | C23: Sí, va ser com un remplantejament de la paraula amor, també, per mi, que és l'amor, que ha sigut l'amor per mi durant tots aquests anys. Sí que és veritat que fins ara sempre havia escrit molt d'amor de parella, no? I em va semblar de sobte absurd, la Bruna, que és la meva millor amiga des que tinc 8 mesos, vam aprendre a caminar juntes, m'ha acompanyat tota la meva vida, perquè no li havia fet mai una cançó. | D23: T'he de dir que se't nota que has passat com un moment de revelació on has no dic que haguessin perdut valor, però com a mínim que els has donat molta importància a les amigues, perquè el disc que has publicat, si jo quan el vaig sentir, vaig pensar és un disc absolutament d'amor, però d'amor a les amigues. Em va semblar superbonic. | E23: 2. Non-standard linguistic features | F23: 2.2 | G23: Colloquial syntactic structures | H23: Tienes que saber que se nota que has pasado por un momento de revelación, no digo que hayan perdido valor, pero al menos que les has dado mucha importancia a tus amigas, porque el disco que has publicado, cuando lo escuché, pensé que era un disco absolutamente de amor, pero de amor por tus amigas. Me pareció precioso. | I23: 1. Reproduction | J23: Direct Translation | K23: YES | L23: SAME | N23: Te tengo que decir que se nota que has pasado por un momento de revelación, no digo que hayan perdido valor, pero al menos que les has dado mucha importancia a tus amigas, porque el disco que has publicado, cuando lo escuché, pensé que era un disco absolutamente de amor, pero de amor a tus amigas. Me pareció súper bonito. | O23: 1. Reproduction | P23: Direct Translation | Q23: YES | R23: SAME | T23: Te tengo que decir que se nota que has pasado por un momento de revelación, no digo que hubieran perdido valor, pero al menos que les has dado mucha importancia a tus amigas, porque el disco que has publicado, si yo cuando lo escuché, pensé que era un disco absolutamente de amor, pero de amor a las amigas. Me pareció superbonito. | U23: 1. Reproduction | V23: Direct Translation | W23: YES | X23: SAME | Z23: Te tengo que decir que se nota que has pasado por un momento de revelación, no digo que hubieran perdido valor, pero al menos que les has dado mucha importancia a tus amigas, porque el disco que has publicado, cuando lo escuché, pensé que era un disco absolutamente de amor, pero de amor a las amigas. Me pareció súper bonito. | AA23: 1. Reproduction | AB23: Direct Translation | AC23: YES | AD23: SAME | AF23: Te tengo que decir que se nota que has pasado por un momento de revelación, no digo que hayan perdido valor, pero al menos que les has dado mucha importancia a tus amigas, porque el disco que has publicado, cuando lo escuché, pensé que era un disco absolutamente de amor, pero de amor hacia tus amigas. Me pareció súper bonito. | AG23: 1. Reproduction | AH23: Direct Translation | AI23: YES | AJ23: SAME | AL23: Tengo que decirte que se te nota que has pasado por un momento de revelación, en el que no es que hayas perdido valor, pero al menos has dado mucha importancia a las amigas, porque el disco que has publicado, si cuando lo escuché, pensé que era un disco absolutamente de amor, pero de amor hacia las amigas. Me pareció superbonito. | AM23: 1. Reproduction | AN23: Direct Translation | AO23: YES | AP23: SAME | AR23: Tengo que decirte que se te nota que has pasado por un momento de revelación, donde no digo que hayan perdido valor, pero al menos que les has dado mucha importancia a las amigas, porque el disco que has publicado, si yo cuando lo escuché, pensé que era un disco absolutamente de amor, pero de amor a las amigas. Me pareció superbonico. | AS23: 1. Reproduction | AT23: Direct Translation | AU23: YES | AV23: SAME | AX23: Tengo que decirte que se te nota que has pasado por un momento de revelación, donde no digo que hayan perdido valor, pero al menos que les has dado mucha importancia a las amigas, porque el disco que has publicado, si yo cuando lo escuché, pensé que era un disco absolutamente de amor, pero de amor a las amigas. Me pareció superbonico. | AY23: 1. Reproduction | AZ23: Direct Translation | BA23: YES | BB23: SAME | BD23: Tengo que decirte que se te nota que has pasado por un momento de revelación donde no dices que hayan perdido valor, pero al menos que les has dado mucha importancia a las amigas, porque el disco que has publicado, si cuando lo escuché, pensé que era un disco absolutamente de amor, pero de amor hacia las amigas. Me pareció superbonico. | BE23: 1. Reproduction | BF23: Direct Translation | BG23: YES | BH23: SAME | BJ23: Tengo que decirte que se te nota que has pasado por un momento de revelación, donde no digo que hayan perdido valor, pero al menos que les has dado mucha importancia a las amigas, porque el disco que has publicado, si cuando lo escuché, pensé que era un disco absolutamente de amor, pero de amor hacia las amigas. Me pareció superbonito. | BK23: 1. Reproduction | BL23: Direct Translation | BM23: YES | BN23: SAME | BP23: Tengo que decirte que se te nota que has pasado por un momento de revelación donde no digo que hubieran perdido valor, pero como mínimo que les has dado mucha importancia a las amigas, porque el disco que has publicado, si yo cuando lo escuché, pensé que es un disco absolutamente de amor, pero de amor a las amigas. Me pareció superbonito. | BQ23: 1. Reproduction | BR23: Direct Translation | BS23: YES | BT23: SAME | BV23: Tienes que saber que se te nota que has pasado por un momento de revelación donde no digo que hubieran perdido valor, pero como mínimo que les has dado mucha importancia a las amigas, porque el disco que has publicado, si yo cuando lo escuché, pensé que es un disco absolutamente de amor, pero de amor a las amigas. Me pareció super bonito | BW23: 1. Reproduction | BX23: Direct Translation | BY23: YES | BZ23: SAME | CB23: Tengo que decirte que se te nota que has pasado por un momento de revelación donde no digo que hubieran perdido valor, pero como mínimo que les has dado mucha importancia a las amigas, porque el disco que has publicado, si yo cuando lo escuché, pensé que es un disco absolutamente de amor, pero de amor a las amigas. Me pareció superbonito. | CC23: 1. Reproduction | CD23: Direct Translation | CE23: YES | CF23: SAME | CH23: Tengo que decirte que se te nota que has pasado por un momento de revelación donde no digo que hubieran perdido valor, pero como mínimo que les has dado mucha importancia a las amigas, porque el disco que has publicado, si yo cuando lo escuché, pensé que es un disco absolutamente de amor, pero de amor a las amigas. Me pareció superbonito. | CI23: 1. Reproduction | CJ23: Direct Translation | CK23: YES | CL23: SAME | CN23: Me tienes que decir que se te nota que has pasado por un momento de revelación donde no digo que hubieran perdido valor, pero como mínimo que les has dado mucha importancia a las amigas, porque el disco que has publicado, si yo cuando lo escuché, pensé que era un disco absolutamente de amor, pero de amor a las amigas. Me pareció superbonito. | CO23: 1. Reproduction | CP23: Direct Translation | CQ23: YES | CR23: SAME
A24: [empieza tema de conversación] | B24: Bueno, pensa que és que el que enredeix un artista són moltes coses. Hi ha la discogràfica, el management, el booking, l'editorial... Hi ha un tema judicial... Hi ha moltes coses que la gent no coneix i que també és un esforç. | C24: Jo, perquè tinc ma mare, que m'ajuda en tot, Però és crazy, hi ha gent molt interessada. | D24: Bueno, pensa que és que el que enredeix un artista són moltes coses. Hi ha la discogràfica, el management, el booking, l'editorial... Hi ha un tema judicial... Hi ha moltes coses que la gent no coneix i que també és un esforç. | E24: 1. Lexicon and Vocabulary | F24: 1.8 | G24: Neologisms | H24: Mira, lo que complica la vida a un artista son muchas cosas. Está la discográfica, la gestión, la contratación de conciertos, la editorial... Hay temas legales... Hay muchas cosas que la gente no conoce y que también requieren mucho esfuerzo. | I24: 1. Reproduction | J24: Direct Translation | K24: NO | N24: Bueno, piensa que hay muchas cosas que complican el trabajo de un artista. Está la discográfica, la gestión, la contratación de conciertos, la editorial... Hay temas legales... Hay muchas cosas que la gente no conoce y que también suponen un esfuerzo. | O24: 1. Reproduction | P24: Direct Translation | Q24: NO | T24: Bueno, piensa que hay muchas cosas que complican la vida de un artista. Está la discográfica, la gestión, la contratación de conciertos, la editorial... Hay temas legales... Hay muchas cosas que la gente no conoce y que también suponen un esfuerzo. | U24: 1. Reproduction | V24: Direct Translation | W24: NO | Z24: Bueno, piensa que hay muchas cosas que pueden complicarle la vida a un artista. Están la discográfica, la gestión, la contratación de conciertos, la editorial... Hay temas legales... Hay muchas cosas que la gente no conoce y que también requieren mucho esfuerzo. | AA24: 1. Reproduction | AB24: Direct Translation | AC24: NO | AF24: Bueno, piensa que lo que complica la vida a un artista son muchas cosas. Está la discográfica, la gestión, la contratación de conciertos, la editorial... Hay temas legales... Hay muchas cosas que la gente no conoce y que también suponen un esfuerzo. | AG24: 1. Reproduction | AH24: Direct Translation | AI24: NO | AL24: Bueno, pienso que lo que enreda a un artista son muchas cosas. Hay la discográfica, el management, el booking, la editorial... Hay un tema judicial... Hay muchas cosas que la gente no conoce y que también son un esfuerzo. | AM24: 1. Reproduction | AN24: Retention | AO24: YES | AP24: SAME | AR24: Bueno, piensa que es que lo que enreda a un artista son muchas cosas. Hay la discográfica, el management, el booking, la editorial... Hay un tema judicial... Hay muchas cosas que la gente no conoce y que también es un esfuerzo. | AS24: 1. Reproduction | AT24: Retention | AU24: YES | AV24: SAME | AX24: Bueno, piensa que es que lo que enreda a un artista son muchas cosas. Hay la discográfica, el management, el booking, la editorial... Hay un tema judicial... Hay muchas cosas que la gente no conoce y que también es un esfuerzo. | AY24: 1. Reproduction | AZ24: Retention | BA24: YES | BB24: SAME | BD24: *Bueno, pienso que es que lo que complica a un artista son muchas cosas. Hay la discográfica, el management, el booking, la editorial... Hay un tema legal... Hay muchas cosas que la gente no conoce y que también es un esfuerzo. | BE24: 1. Reproduction | BF24: Retention | BG24: YES | BH24: SAME | BJ24: Bueno, pienso que lo que enreda a un artista son muchas cosas. Hay la discográfica, el management, el booking, la editorial... Hay un tema judicial... Hay muchas cosas que la gente no conoce y que también es un esfuerzo. | BK24: 1. Reproduction | BL24: Retention | BM24: YES | BN24: SAME | BP24: Bueno, piensa que es que lo que enreda a un artista son muchas cosas. Hay la discográfica, el management, el booking, la editorial... Hay un tema judicial... Hay muchas cosas que la gente no conoce y que también es un esfuerzo. | BQ24: 1. Reproduction | BR24: Retention | BS24: YES | BT24: SAME | BV24: Bueno, piensa que es que el que enreda un artista son muchas cosas. Hay la discográfica, el management, el booking, la editorial... Hay un tema judicial... Hay muchas cosas que la gente no conoce y que también es un esfuerzo. | BW24: 1. Reproduction | BX24: Retention | BY24: YES | BZ24: SAME | CB24: Bueno, piensa que es que el que enreda un artista son muchas cosas. Hay la discográfica, el management, el booking, la editorial... Hay un tema judicial... Hay muchas cosas que la gente no conoce y que también es un esfuerzo. | CC24: 1. Reproduction | CD24: Retention | CE24: YES | CF24: SAME | CH24: Bueno, piensa que es que lo que enreda a un artista son muchas cosas. Hay la discográfica, el management, el booking, la editorial... Hay un tema judicial... Hay muchas cosas que la gente no conoce y que también es un esfuerzo. | CI24: 1. Reproduction | CJ24: Retention | CK24: YES | CL24: SAME | CN24: Bueno, piensa que es que lo que enreda a un artista son muchas cosas. Está la discográfica, el management, el booking, la editorial... Hay un tema judicial... Hay muchas cosas que la gente no conoce y que también es un esfuerzo. | CO24: 1. Reproduction | CP24: Retention | CQ24: YES | CR24: SAME
A25: [empieza tema de conversación] | B25: Jo ho entenc, perquè jo soc bastant extrovertida, la gent que em coneix sap que m'agrada molt divertir-me, que m'agrada molt conèixer persones noves, al final també forma part de la meva feina i m'he de trobar amb gent de diferents edats, diferents àmbits, però explicar les coses així més personals, més de sentiments, més d'obrir-me, sempre em diuen les meves amigues que em costa una mica més. Llavors ho valoren quan faig un missatge de dir SOS... us vull explicar això, perquè alguna cosa està passant. | C25: Saps que això és una teoria que jo sempre he defensat? Que les persones que aparentment són més extrovertides de vegades som les més reservades, saps? | D25: Jo ho entenc, perquè jo soc bastant extrovertida, la gent que em coneix sap que m'agrada molt divertir-me, que m'agrada molt conèixer persones noves, al final també forma part de la meva feina i m'he de trobar amb gent de diferents edats, diferents àmbits, però explicar les coses així més personals, més de sentiments, més d'obrir-me, sempre em diuen les meves amigues que em costa una mica més. Llavors ho valoren quan faig un missatge de dir SOS... us vull explicar això, perquè alguna cosa està passant. | E25: 1. Lexicon and Vocabulary | F25: 1.6 | G25: References to popular culture and memes | H25: Entiendo, porque yo soy bastante extrovertida, y la gente que me conoce sabe que me gusta mucho divertirme, que me gusta mucho conocer gente nueva. Al final, también forma parte de mi trabajo, y tengo que relacionarme con gente de diferentes edades y ámbitos. Pero cuando intento hablar de cosas más personales, más sobre sentimientos, más sobre abrirme, mis amigas siempre me dicen que me cuesta un poco más. Entonces, cuando envío un mensaje diciendo "¡Socorro!", lo valoran, porque significa que algo está pasando. | I25: 4. Creative Shifts | J25: Abstraction – Paraphrase | K25: NO | N25: Lo entiendo, porque yo soy bastante extrovertida, y la gente que me conoce sabe que me gusta mucho divertirme, que me gusta mucho conocer gente nueva. Al final, también forma parte de mi trabajo y tengo que relacionarme con gente de diferentes edades, de diferentes ámbitos. Pero cuando explico cosas más personales, más sobre sentimientos, más sobre abrirme, siempre me dicen mis amigas que me cuesta un poco más. Entonces, valoran mucho cuando hago un mensaje diciendo "SOS...", os quiero explicar esto, porque algo está pasando. | O25: 1. Reproduction | P25: Retention | Q25: YES | R25: SAME | T25: Lo entiendo, porque yo soy bastante extrovertida, la gente que me conoce sabe que me gusta mucho divertirme, que me gusta mucho conocer gente nueva, al final también forma parte de mi trabajo y me tengo que encontrar con gente de diferentes edades, diferentes ámbitos, pero explicar las cosas así, más personales, más de sentimientos, más de abrirme, siempre me dicen mis amigas que me cuesta un poco más. Entonces lo valoran cuando hago un mensaje de decir "SOS... os quiero explicar esto, porque algo está pasando". | U25: 1. Reproduction | V25: Retention | W25: YES | X25: SAME | Z25: Lo entiendo, porque yo soy bastante extrovertida, y la gente que me conoce sabe que me gusta mucho divertirme, que me gusta mucho conocer gente nueva. Al final, también forma parte de mi trabajo y tengo que relacionarme con personas de diferentes edades y ámbitos. Pero cuando explico cosas más personales, más sobre sentimientos, más sobre abrirme, mis amigas siempre me dicen que me cuesta un poco más. Entonces, valoran mucho cuando hago un mensaje diciendo "SOS...", porque quiero contarles algo, porque algo está pasando. | AA25: 1. Reproduction | AB25: Retention | AC25: YES | AD25: SAME | AF25: Lo entiendo, porque yo soy bastante extrovertida, y la gente que me conoce sabe que me gusta mucho divertirme, que me gusta mucho conocer gente nueva. Al final, también forma parte de mi trabajo y tengo que relacionarme con gente de diferentes edades, de diferentes ámbitos. Pero cuando explico cosas más personales, más sobre sentimientos, más sobre abrirme, mis amigas siempre me dicen que me cuesta un poco más. Entonces, valoran mucho cuando hago un mensaje diciendo "¡SOS...! Os quiero explicar esto, porque algo está pasando". | AG25: 1. Reproduction | AH25: Retention | AI25: YES | AJ25: SAME | AL25: Entiendo lo que dices, porque soy bastante extrovertida, la gente que me conoce sabe que me gusta mucho divertirme, que me gusta mucho conocer personas nuevas, al final también forma parte de mi trabajo y me tengo que encontrar con gente de diferentes edades, de diferentes ámbitos, pero explicar las cosas así, más personales, más de sentimientos, más de abrirme, siempre me dicen mis amigas que me cuesta un poco más. Entonces, cuando hago un mensaje diciendo SOS… quiero explicaros esto, porque algo está pasando. | AM25: 1. Reproduction | AN25: Retention | AO25: YES | AP25: SAME | AR25: Entiendo, porque yo soy bastante extrovertida, la gente que me conoce sabe que me gusta mucho divertirme, que me gusta mucho conocer personas nuevas, al final también forma parte de mi trabajo y me tengo que encontrar con gente de diferentes edades, diferentes ámbitos, pero explicar las cosas así, más personales, más de sentimientos, más de abrirme, siempre me lo dicen mis amigas que me cuesta un poco más. Luego lo valoran cuando hago un mensaje de "SOS... quiero explicaros esto, porque algo está pasando". | AS25: 1. Reproduction | AT25: Retention | AU25: YES | AV25: SAME | AX25: Entiendo, porque yo soy bastante extrovertida, la gente que me conoce sabe que me gusta mucho divertirme, que me gusta mucho conocer personas nuevas, al final también forma parte de mi trabajo y me tengo que encontrar con gente de diferentes edades, diferentes ámbitos, pero explicar las cosas así, tan personales, tan de sentimientos, tan de abrirme, siempre me lo dicen mis amigas que me cuesta un poco más. Entonces lo valoran cuando hago un mensaje de "SOS... quiero explicaros esto, porque algo está pasando". | AY25: 1. Reproduction | AZ25: Retention | BA25: YES | BB25: SAME | BD25: Claro, entiendo, porque soy bastante extrovertida, la gente que me conoce sabe que me gusta mucho divertirme, que me gusta mucho conocer personas nuevas, al final también forma parte de mi trabajo y me tengo que encontrar con gente de diferentes edades, diferentes ámbitos, pero explicar las cosas así, más personales, más de sentimientos, más de abrirme, siempre me dicen mis amigas que me cuesta un poco más. Entonces valoran cuando hago un mensaje diciendo "SOS... quiero explicaros esto, porque algo está pasando". | BE25: 1. Reproduction | BF25: Retention | BG25: YES | BH25: SAME | BJ25: Jo lo entiendo, porque soy bastante extrovertida, la gente que me conoce sabe que me gusta mucho divertirme, que me gusta mucho conocer personas nuevas, al final también forma parte de mi trabajo y me tengo que encontrar con gente de diferentes edades, diferentes ámbitos, pero explicar las cosas así, más personales, más de sentimientos, más de abrirme, siempre me dicen mis amigas que me cuesta un poco más. Luego lo valoran cuando hago un mensaje de decir SOS... quiero explicaros esto, porque algo está pasando. | BK25: 1. Reproduction | BL25: Retention | BM25: YES | BN25: SAME | BP25: Yo lo entiendo, porque yo soy bastante extrovertida, la gente que me conoce sabe que me gusta mucho divertirme, que me gusta mucho conocer gente nueva, al final también forma parte de mi trabajo y me tengo que encontrar con gente de diferentes edades, diferentes ámbitos, pero explicar las cosas así más personales, más de sentimientos, más de abrirme, siempre me dicen mis amigas que me cuesta un poco más. Entonces lo valoran cuando hago un mensaje de decir SOS... os quiero explicar esto, porque algo está pasando. | BQ25: 1. Reproduction | BR25: Retention | BS25: YES | BT25: SAME | BV25: Yo lo entiendo, porque yo soy bastante extrovertida, la gente que me conoce sabe que me gusta mucho divertirme, que me gusta mucho conocer personas nuevas, al final también forma parte de mi trabajo y me tengo que encontrar con gente de diferentes edades, diferentes ámbitos, pero explicar las cosas así más personales, más de sentimientos, más de abrirme, siempre me dicen mis amigas que me cuesta un poco más. Entonces lo valoran cuando hago un mensaje de decir SOS... os quiero explicar esto, porque algo está pasando. | BW25: 1. Reproduction | BX25: Retention | BY25: YES | BZ25: SAME | CB25: Yo lo entiendo, porque yo soy bastante extrovertida, la gente que me conoce sabe que me gusta mucho divertirme, que me gusta mucho conocer personas nuevas, al final también forma parte de mi trabajo y me tengo que encontrar con gente de diferentes edades, diferentes ámbitos, pero explicar las cosas así más personales, más de sentimientos, más de abrirme, siempre me dicen mis amigas que me cuesta un poco más. Entonces lo valoran cuando hago un mensaje de decir SOS... os quiero explicar esto, porque algo está pasando. | CC25: 1. Reproduction | CD25: Retention | CE25: YES | CF25: SAME | CH25: Yo lo entiendo, porque yo soy bastante extrovertida, la gente que me conoce sabe que me gusta mucho divertirme, que me gusta mucho conocer gente nueva, al final también forma parte de mi trabajo y me tengo que encontrar con gente de diferentes edades, diferentes ámbitos, pero explicar las cosas así más personales, más de sentimientos, más de abrirme, siempre me dicen mis amigas que me cuesta un poco más. Entonces lo valoran cuando hago un mensaje de decir SOS... os quiero explicar esto, porque algo está pasando. | CI25: 1. Reproduction | CJ25: Retention | CK25: YES | CL25: SAME | CN25: Yo lo entiendo, porque yo soy bastante extrovertida, la gente que me conoce sabe que me gusta mucho divertirme, que me gusta mucho conocer gente nueva, al final también forma parte de mi trabajo y me tengo que encontrar con gente de diferentes edades, diferentes ámbitos, pero explicar las cosas así más personales, más de sentimientos, más de abrirme, siempre me dicen mis amigas que me cuesta un poco más. Entonces lo valoran cuando hago un mensaje de decir SOS... os quiero explicar esto, porque algo está pasando. | CO25: 1. Reproduction | CP25: Retention | CQ25: YES | CR25: SAME
A26: [empieza tema de conversación] | B26: Superrandom, quin signe ets? Soc Aries. Tothom em diu, jo no en tinc ni puta idea, però tothom que dic "Aries" em mira fatal. És que les dones Aries són una mica red flag, però a mi m'agraden. | C26: És que jo tampoc sé res, però jo vaig dir, em compro unes cartes, ja està. Però no porto les cartes, però jo te les volia llegir, però vaig pensar, no, perquè no entenc res del que I què sou vosaltres? | D26: Superrandom, quin signe ets? Soc Aries. Tothom em diu, jo no en tinc ni puta idea, però tothom que dic "Aries" em mira fatal. És que les dones Aries són una mica red flag, però a mi m'agraden. | E26: 1. Lexicon and Vocabulary | F26: 1.5 | G26: Informal intensifiers and quantifiers | H26: Qué casualidad, ¿cuál es tu signo? Soy Aries. Todo el mundo me dice eso, pero yo ni idea, y cuando digo "Aries", todo el mundo me mira mal. Es que las mujeres Aries son un poco... problemáticas, pero a mí me gustan | I26: 2. Omissions | J26: Shortcut Solution | K26: NO | N26: Superrandom, ¿cuál es tu signo? Yo soy Aries. Todo el mundo me dice, pero yo no tengo ni idea, y cuando digo "Aries", todo el mundo me mira como si tuviera algo. Es que las mujeres Aries son un poco problemáticas, pero a mí me gustan. | O26: 2. Omissions | P26: Shortcut Solution | Q26: NO | T26: Superrandom, ¿qué signo eres? Yo soy Aries. Todo el mundo me dice, yo no tengo ni idea, pero a todo el mundo que le digo "Aries" le miro fatal. Es que las mujeres Aries son un poco una señal de alerta, pero a mí me gustan. | U26: 2. Omissions | V26: Shortcut Solution | W26: NO | Z26: Superrandom, ¿qué signo eres? Yo soy Aries. Todo el mundo me dice, pero yo ni idea, pero cuando digo "Aries", todo el mundo me mira mal. Es que las mujeres Aries son un poco una señal de alerta, pero a mí me gustan. | AA26: 2. Omissions | AB26: Shortcut Solution | AC26: NO | AF26: Qué casualidad, ¿cuál es tu signo? Soy Aries. Todo el mundo me dice, pero yo no tengo ni idea, aunque cuando digo "Aries" la gente me mira fatal. Es que las mujeres Aries son un poco problemáticas, pero a mí me gustan. | AG26: 2. Omissions | AH26: Shortcut Solution | AI26: NO | AL26: Superrandom, ¿qué signo eres? Soy Aries. A todos les dicen, yo no tengo ni puta idea, pero todo el mundo que dice "Aries" me mira fatal. Es que las mujeres Aries son un poco red flag, pero a mí me gustan. | AM26: 1. Reproduction | AN26: Direct Translation | AO26: YES | AP26: SAME | AR26: Superrandom, ¿qué signo eres? Soy Aries. Todo el mundo me dice, yo no tengo ni puta idea, pero todo el mundo que dice "Aries" me mira fatal. Es que las mujeres Aries son un poco red flag, pero a mí me gustan. | AS26: 1. Reproduction | AT26: Direct Translation | AU26: YES | AV26: SAME | AX26: Superrandom, ¿qué signo eres? Soy Aries. Todo el mundo me lo dice, yo no sé ni puta idea, pero todo el mundo que dice "Aries" me mira fatal. Es que las mujeres Aries son un poco red flag, pero a mí me gustan. | AY26: 1. Reproduction | AZ26: Direct Translation | BA26: YES | BB26: SAME | BD26: Superrandom, ¿qué signo eres? Soy Aries. Todo el mundo me lo dice, pero yo no tengo ni puta idea, pero todo el mundo que dice "Aries" me mira fatal. Es que las mujeres Aries son un poco red flag, pero a mí me gustan. | BE26: 1. Reproduction | BF26: Direct Translation | BG26: YES | BH26: SAME | BJ26: Superrandom, ¿qué signo eres? Soy Aries. Todo el mundo me lo dice, yo no tengo ni puta idea, pero todo el mundo que dice "Aries" me mira fatal. Es que las chicas Aries son un poco red flag, pero a mí me gustan. | BK26: 1. Reproduction | BL26: Direct Translation | BM26: YES | BN26: SAME | BP26: Superrandom, ¿qué signo eres? Soy Aries. Todo el mundo me dice, yo no tengo ni puta idea, pero todo el mundo que digo "Aries" me mira fatal. Es que las mujeres Aries son un poco bandera roja, pero a mí me gustan. | BQ26: 1. Reproduction | BR26: Direct Translation | BS26: YES | BT26: SAME | BV26: Superrandom, ¿qué signo eres? Soy Aries. Todo el mundo me dice, yo no tengo ni puta idea, pero todo el mundo que digo "Aries" me mira fatal. Es que las mujeres Aries son un poco bandera roja, pero a mí me gustan. | BW26: 1. Reproduction | BX26: Direct Translation | BY26: YES | BZ26: SAME | CB26: Superrandom, ¿qué signo eres? Soy Aries. Todo el mundo me dice, yo no tengo ni puta idea, pero todo el mundo que digo "Aries" me mira fatal. Es que las mujeres Aries son un poco bandera roja, pero a mí me gustan. | CC26: 1. Reproduction | CD26: Direct Translation | CE26: YES | CF26: SAME | CH26: Superrandom, ¿qué signo eres? Soy Aries. Todo el mundo me dice, yo no tengo ni puta idea, pero todo el mundo que digo "Aries" me mira fatal. Es que las mujeres Aries son un poco bandera roja, pero a mí me gustan. | CI26: 1. Reproduction | CJ26: Direct Translation | CK26: YES | CL26: SAME | CN26: Superrandom, ¿qué signo eres? Soy Aries. Todo el mundo me dice, yo no tengo ni puta idea, pero todo el mundo que digo "Aries" me mira fatal. Es que las mujeres Aries son un poco bandera roja, pero a mí me gustan. | CO26: 1. Reproduction | CP26: Direct Translation | CQ26: YES | CR26: SAME
A27: [empieza tema de conversación] | B27: En tot cas, una altra cosa que també volem saber és com és el teu dia a dia. Què fa una estrella de Catalunya? O sigui, el meu dia a dia és treballar tot el puto dia, la veritat. | C27: Ara acabo la gira, o sigui, a finals de novembre, perquè li vaig dir a ma mare, en plan, que és la que em porta tot. Li vaig dir, mama, ja està. Jo a partir del novembre, al febrer torno a començar una altra gira. | D27: En tot cas, una altra cosa que també volem saber és com és el teu dia a dia. Què fa una estrella de Catalunya? O sigui, el meu dia a dia és treballar tot el puto dia, la veritat. | E27: 1. Lexicon and Vocabulary | F27: 1.5 | G27: Informal intensifiers and quantifiers | H27: En cualquier caso, otra cosa que también queremos saber es cómo es tu día a día. ¿Qué hace una estrella de Cataluña? O sea, la verdad es que mi día a día consiste en trabajar todo el día. | I27: 2. Omissions | J27: Shortcut Solution | K27: NO | N27: En cualquier caso, otra cosa que también queremos saber es cómo es tu día a día. ¿Qué hace una estrella en Cataluña? O sea, la verdad es que mi día a día consiste en trabajar todo el puto día. | O27: 1. Reproduction | P27: Direct Translation | Q27: YES | R27: SAME | T27: En cualquier caso, otra cosa que también queremos saber es cómo es tu día a día. ¿Qué hace una estrella de Cataluña? O sea, la verdad es que mi día a día consiste en trabajar todo el puto día. | U27: 1. Reproduction | V27: Direct Translation | W27: YES | X27: SAME | Z27: En cualquier caso, otra cosa que también queremos saber es cómo es tu día a día. ¿Qué hace una estrella de Cataluña? O sea, la verdad es que mi día a día consiste en trabajar todo el puto día. | AA27: 1. Reproduction | AB27: Direct Translation | AC27: YES | AD27: SAME | AF27: En cualquier caso, otra cosa que también queremos saber es cómo es tu día a día. ¿Qué hace una estrella de Cataluña? O sea, la verdad es que mi día a día consiste en trabajar todo el día. | AG27: 2. Omissions | AH27: Shortcut Solution | AI27: NO | AL27: En todo caso, otra cosa que también queremos saber es cómo es tu día a día. ¿Qué hace una estrella de Catalunya? O sea, mi día a día es trabajar todo el puto día, la verdad. | AM27: 1. Reproduction | AN27: Direct Translation | AO27: YES | AP27: SAME | AR27: En todo caso, otra cosa que también queremos saber es cómo es tu día a día. ¿Qué hace una estrella de Catalunya? O sea, mi día a día es trabajar todo el puto día, la verdad. | AS27: 1. Reproduction | AT27: Direct Translation | AU27: YES | AV27: SAME | AX27: En todo caso, otra cosa que también queremos saber es cómo es tu día a día. ¿Qué hace una estrella de Catalunya? O sea, mi día a día es trabajar todo el puto día, la verdad. | AY27: 1. Reproduction | AZ27: Direct Translation | BA27: YES | BB27: SAME | BD27: En todo caso, otra cosa que también queremos saber es cómo es tu día a día. ¿Qué hace una estrella de Cataluña? O sea, mi día a día es trabajar todo el puto día, la verdad. | BE27: 1. Reproduction | BF27: Direct Translation | BG27: YES | BH27: SAME | BJ27: En todo caso, otra cosa que también queremos saber es cómo es tu día a día. ¿Qué hace una estrella de Catalunya? O sea, mi día a día es trabajar todo el puto día, la verdad. | BK27: 1. Reproduction | BL27: Direct Translation | BM27: YES | BN27: SAME | BP27: En todo caso, otra cosa que también queremos saber es cómo es tu día a día. ¿Qué hace una estrella de Cataluña? O sea, mi día a día es trabajar todo el puto día, la verdad. | BQ27: 1. Reproduction | BR27: Direct Translation | BS27: YES | BT27: SAME | BV27: En todo caso, otra cosa que también queremos saber es cómo es tu día a día. ¿Qué hace una estrella de Cataluña? O sea, mi día a día es trabajar todo el puto día, la verdad. | BW27: 1. Reproduction | BX27: Direct Translation | BY27: YES | BZ27: SAME | CB27: En todo caso, otra cosa que también queremos saber es cómo es tu día a día. ¿Qué hace una estrella de Cataluña? O sea, mi día a día es trabajar todo el puto día, la verdad. | CC27: 1. Reproduction | CD27: Direct Translation | CE27: YES | CF27: SAME | CH27: En todo caso, otra cosa que también queremos saber es cómo es tu día a día. ¿Qué hace una estrella de Cataluña? O sea, mi día a día es trabajar todo el puto día, la verdad. | CI27: 1. Reproduction | CJ27: Direct Translation | CK27: YES | CL27: SAME | CN27: En todo caso, otra cosa que también queremos saber es cómo es tu día a día. ¿Qué hace una estrella de Cataluña? O sea, mi día a día es trabajar todo el puto día, la verdad. | CO27: 1. Reproduction | CP27: Direct Translation | CQ27: YES | CR27: SAME
A28: [empieza tema de conversación] | B28: I la meva germana, la Paula, que és la que em porta tota la part de producció de videoclips i tal, també està fins la polla, en plan, superinsistents, però bueno, també ho he creat jo, o sigui, jo ja soc conscient de que si no paro de filtrar coses, en plan, tot el dia estic filtrant coses. | C28: I la penya es pica ja pel Twitter, rollo, si no, i ara esperar 7 mesos, no? Pues no la treguis, doncs no la filtris, no sé què, és que m'encanta. | D28: I la meva germana, la Paula, que és la que em porta tota la part de producció de videoclips i tal, també està fins la polla, en plan, superinsistents, però bueno, també ho he creat jo, o sigui, jo ja soc conscient de que si no paro de filtrar coses, en plan, tot el dia estic filtrant coses. | E28: 3. Pragmatics and Discourse | F28: 3.1 | G28: Discourse markers | H28: Y mi hermana, Paula, que se encarga de toda la parte de producción de videoclips y cosas así, también está muy ocupada, de hecho, muy insistente, pero bueno, también lo he creado yo, así que yo ya soy consciente de que si no paro de filtrar cosas, estoy filtrando cosas todo el día. | I28: 2. Omissions | J28: Shortcut Solution | K28: NO | N28: Y mi hermana, Paula, que se encarga de toda la parte de producción de los videoclips y demás, también está hasta arriba de trabajo, súper insistente, pero bueno, también lo he creado yo, o sea, yo ya soy consciente de que si no paro de filtrar cosas, paso todo el día filtrando cosas. | O28: 2. Omissions | P28: Shortcut Solution | Q28: NO | T28: Y mi hermana, Paula, que se encarga de toda la parte de producción de videoclips y demás, también está hasta arriba de trabajo, en plan, superinsistente, pero bueno, también lo he creado yo, o sea, yo ya soy consciente de que si no paro de filtrar cosas, en plan, estoy filtrando cosas todo el día. | U28: 1. Reproduction | V28: Direct Translation | W28: YES | X28: SAME | Z28: Y mi hermana, Paula, que se encarga de toda la parte de producción de los videoclips y demás, también está muy ocupada, es súper insistente, pero bueno, también lo he creado yo, así que soy consciente de que si no dejo de filtrar cosas, paso todo el día filtrando. | AA28: 2. Omissions | AB28: Shortcut Solution | AC28: NO | AF28: Y mi hermana, Paula, que se encarga de toda la parte de producción de los videoclips y demás, también está muy ocupada, súper insistente, pero bueno, también lo he creado yo, así que, yo ya soy consciente de que si no dejo de filtrar cosas, paso el día entero filtrando. | AG28: 2. Omissions | AH28: Shortcut Solution | AI28: NO | AL28: También mi hermana, la Paula, que es la que me lleva toda la parte de producción de videoclips y cosas por el estilo, también está hasta arriba, en plan, superinsistente, pero bueno, también lo he creado yo, o sea, ya soy consciente de que si no paro de filtrar cosas, en plan, todo el día estoy filtrando cosas. | AM28: 1. Reproduction | AN28: Direct Translation | AO28: YES | AP28: SAME | AR28: Y mi hermana, la Paula, que es la que me lleva toda la parte de producción de videoclips y tal, también está hasta la madre, en plan, superinsistente, pero bueno, también lo he creado yo, o sea, ya soy consciente de que si no paro de filtrar cosas, en plan, todo el día estoy filtrando cosas. | AS28: 1. Reproduction | AT28: Direct Translation | AU28: YES | AV28: SAME | AX28: Mi hermana, la Paula, que es la que me lleva toda la parte de producción de videoclips y cosas por el estilo, también está hasta la madre, en plan, superinsistente, pero bueno, también lo he creado yo, o sea, ya soy consciente de que si no paro de filtrar cosas, en plan, todo el día estoy filtrando cosas. | AY28: 1. Reproduction | AZ28: Direct Translation | BA28: YES | BB28: SAME | BD28: Y mi hermana, la Paula, que es la que me lleva toda la parte de producción de videoclips y tal, también está hasta arriba, en plan, superinsistente, pero bueno, también lo he creado yo, o sea, ya soy consciente de que si no paro de filtrar cosas, en plan, todo el día estoy filtrando cosas. | BE28: 1. Reproduction | BF28: Direct Translation | BG28: YES | BH28: SAME | BJ28: Y mi hermana, la Paula, que es la que me maneja toda la parte de producción de videoclips y demás, también está hasta arriba, en plan, superinsistente, pero bueno, también lo he creado yo, es decir, ya soy consciente de que si no paro de filtrar cosas, en plan, todo el día estoy filtrando cosas. | BK28: 1. Reproduction | BL28: Direct Translation | BM28: YES | BN28: SAME | BP28: Y mi hermana, la Paula, que es la que se encarga de toda la parte de producción de videoclips y tal, también está hasta los cojones, en plan, muy insistentes, pero bueno, también lo he creado yo, o sea, yo ya soy consciente de que si no paro de filtrar cosas, en plan, todo el día estoy filtrando cosas. | BQ28: 1. Reproduction | BR28: Direct Translation | BS28: YES | BT28: SAME | BV28: Y mi hermana, la Paula, que es la que se encarga de toda la parte de producción de videoclips y tal, también está hasta los cojones, en plan, insistentes, pero bueno, también lo he creado yo, o sea, yo ya soy consciente de que si no paro de filtrar cosas, en plan, todo el día estoy filtrando cosas. | BW28: 1. Reproduction | BX28: Direct Translation | BY28: YES | BZ28: SAME | CB28: Y mi hermana, la Paula, que es la que se encarga de toda la parte de producción de videoclips y tal, también está hasta la polla, en plan, insistentes, pero bueno, también lo he creado yo, o sea, yo ya soy consciente de que si no paro de filtrar cosas, en plan, todo el día estoy filtrando cosas. | CC28: 1. Reproduction | CD28: Direct Translation | CE28: YES | CF28: SAME | CH28: Y mi hermana, la Paula, que es la que se encarga de toda la parte de producción de videoclips y tal, también está hasta la polla, en plan, insistentes, pero bueno, también lo he creado yo, o sea, yo ya soy consciente de que si no paro de filtrar cosas, en plan, todo el día estoy filtrando cosas. | CI28: 1. Reproduction | CJ28: Direct Translation | CK28: YES | CL28: SAME | CN28: Y mi hermana, la Paula, que es la que se encarga de toda la parte de producción de videoclips y tal, también está hasta la polla, en plan, superinsistentes, pero bueno, también lo he creado yo, o sea, yo ya soy consciente de que si no paro de filtrar cosas, en plan, todo el día estoy filtrando cosas. | CO28: 1. Reproduction | CP28: Direct Translation | CQ28: YES | CR28: SAME
A29: [empieza tema de conversación] | B29: Una altra cosa que ja hem mencionat vagament és que ens cancel·lin a Twitter tota l'estona. Mira, de veritat, si cada tuit que faig algú m'ha de dir ojalà et moris, pues, tia, és que tu ho estàs dient ara, però jo fa com bastants anys que ho dic. | C29: [acaba tema de conversación] | D29: Una altra cosa que ja hem mencionat vagament és que ens cancel·lin a Twitter tota l'estona. Mira, de veritat, si cada tuit que faig algú m'ha de dir ojalà et moris, pues, tia, és que tu ho estàs dient ara, però jo fa com bastants anys que ho dic. | E29: 3. Pragmatics and Discourse | F29: 3.2 | G29: Familiar address or vocatives | H29: Otra cosa que ya hemos mencionado vagamente es que nos cancelan en Twitter constantemente. Mira, en serio, si cada vez que publico algo alguien me dice "ojalá te mueras", pues, mira, tú estás diciendo eso ahora, pero yo llevo como bastantes años escuchando eso. | I29: 4. Creative Shifts | J29: Abstraction – Superordinate Term | K29: NO | N29: Otra cosa que ya hemos mencionado vagamente es que nos cancelan en Twitter constantemente. Mira, en serio, si cada vez que tuiteo alguien me dice "ojalá te mueras", pues, tío, es que tú lo estás diciendo ahora, pero yo lo he escuchado bastantes años. | O29: 1. Reproduction | P29: Direct Translation | Q29: YES | R29: SAME | T29: Otro tema que ya hemos mencionado brevemente es que nos cancelan en Twitter constantemente. Mira, de verdad, si cada vez que publico algo alguien me dice "ojalá te mueras", pues, oye, tú estás diciendo eso ahora, pero yo lo he escuchado bastantes años. | U29: 4. Creative Shifts | V29: Abstraction – Superordinate Term | W29: NO | Z29: Otra cosa que ya hemos mencionado vagamente es que nos cancelan en Twitter constantemente. Mira, en serio, si cada vez que publico un tuit alguien me dice "ojalá te mueras", pues, mira, tú lo estás diciendo ahora, pero yo llevo diciendo eso desde hace bastantes años. | AA29: 4. Creative Shifts | AB29: Abstraction – Superordinate Term | AC29: NO | AF29: Otra cosa que ya hemos mencionado vagamente es que nos cancelan en Twitter constantemente. Mira, en serio, si cada vez que escribo algo alguien me dice "ojalá te mueras", pues, mira, tú lo estás diciendo ahora, pero yo lo he escuchado durante bastantes años. | AG29: 4. Creative Shifts | AH29: Abstraction – Superordinate Term | AI29: NO | AL29: Otra cosa que ya hemos mencionado de pas es que nos cancelan en Twitter todo el rato. Mira, de verdad, si cada tuit que hago alguien me tiene que decir "ojalá te murieras", pues, tía, es que tú lo estás diciendo ahora, pero yo lo digo hace como bastantes años que lo digo. | AM29: 1. Reproduction | AN29: Direct Translation | AO29: YES | AP29: SAME | AR29: Una otra cosa que ya hemos mencionado vagamente es que nos cancelan en Twitter todo el rato. Mira, de verdad, si cada tuit que hago alguien me tiene que decir "ojalá te murieras", pues, tía, es que tú lo estás diciendo ahora, pero yo hago como bastantes años que lo digo. | AS29: 1. Reproduction | AT29: Direct Translation | AU29: YES | AV29: SAME | AX29: Una otra cosa que ya hemos mencionado vagamente es que nos cancelan en Twitter todo el rato. Mira, de verdad, si cada tuit que hago alguien me tiene que decir ojalá te murieras, pues, tía, es que tú lo estás diciendo ahora, pero yo hago como bastantes años que lo digo. | AY29: 1. Reproduction | AZ29: Direct Translation | BA29: YES | BB29: SAME | BD29: "Otra cosa que ya mencionamos de pas es que nos cancelan en Twitter todo el rato. Mira, de verdad, si cada tuit que hago alguien me tiene que decir 'ojalá te mueras', pues, tía, es que tú lo estás diciendo ahora, pero yo hace como bastantes años que lo digo." | BE29: 1. Reproduction | BF29: Direct Translation | BG29: YES | BH29: SAME | BJ29: Una cosa más que ya hemos mencionado de pasada es que nos cancelan en Twitter todo el rato. Mira, de verdad, si cada tuit que hago alguien me tiene que decir "ojalá te murieras", pues, tía, es que tú lo estás diciendo ahora, pero yo lo digo hace como bastantes años. | BK29: 1. Reproduction | BL29: Direct Translation | BM29: YES | BN29: SAME | BP29: Otra cosa que ya hemos mencionado vagamente es que nos bloqueen en Twitter todo el tiempo. Mira, de verdad, si cada tuit que hago alguien me tiene que decir ojalá te mueras, pues, tía, es que tú lo estás diciendo ahora, pero yo hace como bastantes años que lo digo. | BQ29: 1. Reproduction | BR29: Direct Translation | BS29: YES | BT29: SAME | BV29: Otra cosa que ya hemos mencionado vagamente es que nos cancelen en Twitter todo el rato. Mira, de verdad, si cada tuit que hago alguien me tiene que decir ojalá te mueras, pues, tía, es que tú lo estás diciendo ahora, pero yo hace como bastantes años que lo digo. | BW29: 1. Reproduction | BX29: Direct Translation | BY29: YES | BZ29: SAME | CB29: Otra cosa que ya hemos mencionado vagamente es que nos cancelen en Twitter todo el rato. Mira, de verdad, si cada tuit que hago alguien me tiene que decir ojalá te mueras, pues, tía, es que tú lo estás diciendo ahora, pero yo hace como bastantes años que lo digo. | CC29: 1. Reproduction | CD29: Direct Translation | CE29: YES | CF29: SAME | CH29: Otra cosa que ya hemos mencionado de pasada es que nos bloqueen en Twitter todo el rato. Mira, de verdad, si cada tuit que hago alguien me tiene que decir ojalá te mueras, pues, tía, es que tú lo estás diciendo ahora, pero yo hace como bastantes años que lo digo. | CI29: 1. Reproduction | CJ29: Direct Translation | CK29: YES | CL29: SAME | CN29: Otra cosa que ya hemos mencionado vagamente es que nos cancelen en Twitter todo el tiempo. Mira, de verdad, si cada tuit que hago alguien me tiene que decir ojalá te mueras, pues, tía, es que tú lo estás diciendo ahora, pero yo hace como bastantes años que lo digo. | CO29: 1. Reproduction | CP29: Direct Translation | CQ29: YES | CR29: SAME
A30: [empieza tema de conversación] | B30: Tia, una persona que està servint molt de cony és la Aitana Ocaña, és la millor, ha fet un glow up de cony que em cago a sobre. Però que em cago a sobre, eh? | C30: Ella, per mi, ha fet el mateix que va haver de fer la Miley Cyrus ballant i xupant un martell. Se l'ha infantilitzat, doncs ella va i serveix cony. Punto, ja està, i és el que li toca. | D30: Tia, una persona que està servint molt de cony és la Aitana Ocaña, és la millor, ha fet un glow up de cony que em cago a sobre. Però que em cago a sobre, eh? | E30: 4. Register and Tone | F30: 4.1 | G30: Hyperbole and exaggeration | H30: Tía, una persona que está triunfando muchísimo es Aitana Ocaña, es la mejor, ha tenido una transformación increíble que me deja sin palabras. Pero, ¡de verdad, me deja sin palabras! | I30: 4. Creative Shifts | J30: Abstraction – Paraphrase | K30: NO | N30: Tía, una persona que está destacando muchísimo es Aitana Ocaña, es la mejor, ha tenido una transformación increíble que me deja sin palabras. Pero, en serio, ¡me deja sin palabras! | O30: 4. Creative Shifts | P30: Abstraction – Paraphrase | Q30: NO | T30: Tía, una persona que está triunfando muchísimo es Aitana Ocaña, es la mejor, ha tenido un cambio brutal que me supero. Pero que me supero, eh. | U30: 3. Errors | W30: NO | Z30: Tía, una persona que está triunfando muchísimo es Aitana Ocaña, es la mejor, ha tenido una transformación increíble que me deja sin palabras. Pero, de verdad, me deja sin palabras. | AA30: 4. Creative Shifts | AB30: Abstraction – Paraphrase | AC30: NO | AF30: Tía, una persona que está destacando muchísimo es Aitana Ocaña, es la mejor, ha tenido una transformación increíble que me deja sin palabras. Pero, en serio, me deja sin palabras. | AG30: 4. Creative Shifts | AH30: Abstraction – Paraphrase | AI30: NO | AL30: Tía, una persona que está sirviendo mucho de cony es la Aitana Ocaña, es la mejor, ha hecho un glow up de cony que me cago a sobre. Pero que me cago a sobre, eh? | AM30: 1. Reproduction | AN30: Retention | AO30: NO | AR30: Tía, una persona que está sirviendo mucho de cony es la Aitana Ocaña, es la mejor, ha hecho un glow up de cony que me cago a sobre. Pero que me cago a sobre, eh? | AS30: 1. Reproduction | AT30: Retention | AU30: NO | AX30: Tía, una persona que está sirviendo mucho de cony es la Aitana Ocaña, es la mejor, ha hecho un glow up de cony que me cago a sobre. Pero que me cago a sobre, eh? | AY30: 1. Reproduction | AZ30: Retention | BA30: NO | BD30: Tía, una persona que está sirviendo mucho cony es la Aitana Ocaña, es la mejor, ha hecho un *glow up* de cony que me cago a sobre. Pero que me cago a sobre, eh? | BE30: 1. Reproduction | BF30: Retention | BG30: NO | BJ30: Tía, una persona que está sirviendo mucha droga es la Aitana Ocaña, es la mejor, ha hecho un *glow up* de droga que me cago a sobre. Pero que me cago a sobre, eh? | BK30: 1. Reproduction | BL30: Retention | BM30: NO | BP30: Tía, una persona que está sirviendo mucho de coño es Aitana Ocaña, es la mejor, ha hecho un glow up de coño que me cago en ella. Pero que me cago en ella, eh? | BQ30: 3. Errors | BS30: NO | BV30: Tía, una persona que está sirviendo mucho de coño es Aitana Ocaña, es la mejor, ha hecho un glow up de coño que me cago encima. Pero que me cago encima, eh? | BW30: 1. Reproduction | BX30: Direct Translation | BY30: YES | BZ30: SAME | CB30: Tía, una persona que está chupando mucho coño es Aitana Ocaña, es la mejor, ha hecho un glow up de coño que me cago en ella. Pero que me cago en ella, ¿eh? | CC30: 3. Errors | CE30: NO | CH30: Tía, una persona que está chupando mucho coño es Aitana Ocaña, es la mejor, ha hecho un glow up de coño que me cago en ella. Pero que me cago en ella, ¿eh? | CI30: 3. Errors | CK30: NO | CN30: Tía, una persona que está sirviendo mucho de cony es la Aitana Ocaña, es la mejor, ha hecho un glow up de cony que me cago en la madre. Pero que me cago en la madre, eh? | CO30: 4. Creative Shifts | CP30: Abstraction – Superordinate Term | CQ30: NO
A31: [empieza tema de conversación] | B31: A mesura que et fas gran, comences a conèixer un tipus de gent, és que l'altre dia estava en un dinar que em va impressionar molt, i una persona a la taula està parlant de relacions obertes, i digueren "Què relacions obertes ni que polles?" Aquí el que s'ha de fer és tu et tires a qui vulguis i no li dius a la teva parella. De tota la vida s'ha fet sempre així per algo". | C31: També hi ha gent que, és com en pla, l'altre dia algú em va dir, sí, quan ja portes 3 anys amb la teva parella ja s'entén que li poses els cuernos. | D31: A mesura que et fas gran, comences a conèixer un tipus de gent, és que l'altre dia estava en un dinar que em va impressionar molt, i una persona a la taula està parlant de relacions obertes, i digueren "Què relacions obertes ni que polles?" Aquí el que s'ha de fer és tu et tires a qui vulguis i no li dius a la teva parella. De tota la vida s'ha fet sempre així per algo". | E31: 1. Lexicon and Vocabulary | F31: 1.5 | G31: Informal intensifiers and quantifiers | H31: A medida que uno crece, empieza a conocer a cierto tipo de gente, y el otro día estaba en una comida que me impresionó mucho. Una persona en la mesa estaba hablando de relaciones abiertas, y dijo: "¿Qué son esas cosas de relaciones abiertas? ¡Venga ya!". Lo que hay que hacer, según él, es "tirar a quien te dé la gana y no decirle nada a tu pareja. Siempre se ha hecho así, por algo". | I31: 4. Creative Shifts | J31: Abstraction – Superordinate Term | K31: NO | N31: A medida que te haces mayor, empiezas a conocer cierto tipo de gente, y el otro día estuve en una comida que me impresionó mucho. Una persona en la mesa estaba hablando de relaciones abiertas, y dijo: "¿Qué son las relaciones abiertas, cojones? Aquí lo que hay que hacer es que te tiras con quien quieras y no se lo dices a tu pareja. Siempre se ha hecho así, por algo". | O31: 4. Creative Shifts | P31: Abstraction – Superordinate Term | Q31: NO | T31: A medida que te haces mayor, empiezas a conocer un tipo de gente, y el otro día estuve en una comida que me impresionó mucho. Una persona en la mesa estaba hablando de relaciones abiertas, y dijo: "¿Qué relaciones abiertas, ni de coña?". Y añadió: "Aquí lo que se tiene que hacer es tirarte con quien quieras y no decirle nada a tu pareja. Así se ha hecho siempre, por algo". | U31: 3. Errors | W31: NO | Z31: A medida que creces, empiezas a conocer a cierto tipo de gente. El otro día estuve en una comida que me impresionó mucho, y una persona en la mesa estaba hablando de relaciones abiertas, y dijo: "¿Qué son esas cosas de relaciones abiertas? ¡Qué tonterías!". Lo que hay que hacer, según esa persona, es "tirar a quien quieras y no decirle nada a tu pareja. Así se ha hecho siempre, por algo". | AA31: 4. Creative Shifts | AB31: Abstraction – Superordinate Term | AC31: NO | AF31: A medida que uno crece, empieza a conocer cierto tipo de gente, y el otro día estaba en una comida que me impresionó mucho. Una persona en la mesa estaba hablando de relaciones abiertas, y dijo: "Pero, ¿qué son esas cosas de relaciones abiertas? ¿A qué viene?". Lo que hay que hacer, según él, es "tirar a quien quieras y no decirle nada a tu pareja. Así se ha hecho siempre, por algo". | AG31: 3. Errors | AI31: NO | AL31: A medida que te vas haciendo mayor, empiezas a conocer un tipo de gente, es que el otro día estaba en un comedor que me impresionó mucho, y una persona a la mesa estaba hablando de relaciones abiertas, y decía: "¿Qué relaciones abiertas ni que pollos?" Lo que se tiene que hacer es que tú te tiras a quien quieras y no se lo dices a tu pareja. De toda la vida se ha hecho siempre así por algo". | AM31: 3. Errors | AO31: NO | AR31: A medida que te vas haciendo mayor, comienzas a conocer un tipo de gente, es que el otro día estaba en un cena que me impresionó mucho, y una persona a la mesa estaba hablando de relaciones abiertas, y dijeron "¿Qué relaciones abiertas ni que cojones?" Aquí lo que se tiene que hacer es que tú te tiras a quien quieras y no le dices a tu pareja. De toda la vida se ha hecho siempre así por algo". | AS31: 4. Creative Shifts | AT31: Modification – Cultural | AU31: YES | AV31: SAME | AX31: A medida que te vas haciendo mayor, empiezas a conocer un tipo de gente, es que el otro día estaba en un comedor que me impresionó mucho, y una persona a la mesa estaba hablando de relaciones abiertas, y decía: "¿Qué relaciones abiertas ni que pollos?" Lo que se tiene que hacer es que tú te tiras a quien quieras y no se lo dices a tu pareja. De toda la vida se ha hecho siempre así por algo". | AY31: 3. Errors | BA31: NO | BD31: A medida que te vas haciendo mayor, empiezas a conocer un tipo de gente, es que el otro día estaba en un comedor que me impresionó mucho, y una persona a la mesa estaba hablando de relaciones abiertas, y dijo: "¿Qué relaciones abiertas ni que pollos?" Aquí lo que se hace es que tú te tiras a quien quieras y no se lo dices a tu pareja. De toda la vida se ha hecho siempre así por algo". | BE31: 3. Errors | BG31: NO | BJ31: A medida que te vas haciendo mayor, empiezas a conocer un tipo de gente, es que el otro día estaba en un comedor que me impresionó mucho, y una persona a la mesa estaba hablando de relaciones abiertas, y decía: "¿Qué relaciones abiertas ni que pollos?" Lo que se tiene que hacer es que tú te tiras a quien quieras y no se lo dices a tu pareja. De toda la vida se ha hecho siempre así por algo". | BK31: 3. Errors | BM31: NO | BP31: A medida que te haces mayor, empiezas a conocer un tipo de gente, es que el otro día estaba en una comida que me impresionó mucho, y una persona en la mesa estaba hablando de relaciones abiertas, y dijo "¿Qué relaciones abiertas ni que pollas? Aquí lo que hay que hacer es que te tiras a quien quieras y no se lo dices a tu pareja. De toda la vida se ha hecho siempre así por algo". | BQ31: 1. Reproduction | BR31: Direct Translation | BS31: YES | BT31: SAME | BV31: A medida que te haces mayor, empiezas a conocer un tipo de gente, es que el otro día estaba en una comida que me impresionó mucho, y una persona en la mesa está hablando de relaciones abiertas, y dijeron "Qué relaciones abiertas ni que pollas?" Aquí lo que hay que hacer es tú te tiras a quien quieras y no se lo dices a tu pareja. De toda la vida se ha hecho siempre así por algo". | BW31: 1. Reproduction | BX31: Direct Translation | BY31: YES | BZ31: SAME | CB31: A medida que te haces mayor, empiezas a conocer un tipo de gente, es que el otro día estaba en una comida que me impresionó mucho, y una persona en la mesa está hablando de relaciones abiertas, y dijeron "Qué relaciones abiertas ni que pollas?" Aquí lo que hay que hacer es tú te tiras a quien quieras y no se lo dices a tu pareja. De toda la vida se ha hecho siempre así por algo". | CC31: 1. Reproduction | CD31: Direct Translation | CE31: YES | CF31: SAME | CH31: A medida que te haces mayor, empiezas a conocer un tipo de gente, es que el otro día estaba en una comida que me impresionó mucho, y una persona en la mesa estaba hablando de relaciones abiertas, y dijo "¿Qué relaciones abiertas ni que pollas? Aquí lo que hay que hacer es que te tiras a quien quieras y no se lo dices a tu pareja. De toda la vida se ha hecho siempre así por algo". | CI31: 1. Reproduction | CJ31: Direct Translation | CK31: YES | CL31: SAME | CN31: A medida que te haces mayor, empiezas a conocer un tipo de gente, es que el otro día estaba en una comida que me impresionó mucho, y una persona en la mesa estaba hablando de relaciones abiertas, y dijeron "Qué relaciones abiertas ni que pollas?" Aquí lo que hay que hacer es que te tiras a quien quieras y no se lo dices a tu pareja. De toda la vida se ha hecho siempre así por algo". | CO31: 1. Reproduction | CP31: Direct Translation | CQ31: YES | CR31: SAME
A32: [empieza tema de conversación] | B32: Però això als millenials els passa molt, perquè crec que totes aquestes fases que haurien de haver viscut a l'adolescència,i no ho han viscut i llavors ho estan vivint tot com tard, saps? Perquè totes aquestes coses els han arribat tard. | C32: [acaba tema de conversación] | D32: Però això als mil·lenials els passa molt, perquè crec que totes aquestes fases que haurien de haver viscut a l'adolescència,i no ho han viscut i llavors ho estan vivint tot com tard, saps? Perquè totes aquestes coses els han arribat tard. | E32: 1. Lexicon and Vocabulary | F32: 1.6 | G32: References to popular culture and memes | H32: Pero esto le pasa mucho a la generación millennial, porque creo que todas esas etapas que deberían haber vivido en la adolescencia, y que no vivieron, ahora las están experimentando todas de forma tardía, ¿sabes? Porque todas esas cosas les llegaron tarde. | I32: 3. Errors | K32: NO | N32: Pero esto le pasa mucho a los millennials, porque creo que todas esas fases que deberían haber vivido en la adolescencia, y no las vivieron, ahora las están experimentando todo con retraso, ¿sabes? Porque todas esas cosas les llegaron tarde. | O32: 3. Errors | Q32: NO | T32: Pero esto le pasa mucho a los millennials, porque creo que todas esas fases que deberían haber vivido en la adolescencia, y no las vivieron, ahora las están viviendo todo como si fuera tarde, ¿sabes? Porque todas esas cosas les llegaron tarde. | U32: 3. Errors | W32: NO | Z32: Pero esto le pasa mucho a los millennials, porque creo que todas esas etapas que deberían haber vivido en la adolescencia, y no las vivieron, las están viviendo todo más tarde, ¿sabes? Porque todas esas cosas les llegaron tarde. | AA32: 3. Errors | AC32: NO | AF32: Pero esto le pasa mucho a los millennials, porque creo que todas esas etapas que deberían haber vivido en la adolescencia, y no vivieron, ahora las están experimentando todas, ¿sabes? Porque todas esas cosas les llegaron tarde. | AG32: 3. Errors | AI32: NO | AL32: Pero a los millenials les pasa mucho, porque creo que todas esas fases que deberían haber vivido en la adolescencia, no las han vivido y entonces las están viviendo todas de golpe, ¿sabes? Porque todas esas cosas les han llegado tarde. | AM32: 3. Errors | AO32: NO | AR32: Pero esto a los millenials les pasa mucho, porque creo que todas esas fases que deberían haber vivido en la adolescencia, y no las han vivido, y entonces las están viviendo todas a la vez, ¿sabes? Porque todas esas cosas les han llegado tarde. | AS32: 3. Errors | AU32: NO | AX32: Pero esto a los millenials les pasa mucho, porque creo que todas esas fases que deberían haber vivido en la adolescencia, y no las han vivido y entonces las están viviendo todo como tarde, ¿sabes? Porque todas esas cosas les han llegado tarde. | AY32: 3. Errors | BA32: NO | BD32: Pero esto les pasa mucho a los millenials, porque creo que todas esas fases que deberían haber vivido en la adolescencia, no las han vivido y entonces las están viviendo todas a la vez, ¿sabes? Porque todas esas cosas les han llegado tarde. | BE32: 3. Errors | BG32: NO | BJ32: Pero esto les pasa mucho a los millenials, porque creo que todas esas fases que deberían haber vivido en la adolescencia, no las han vivido y entonces las están viviendo todas a la vez, ¿sabes? Porque todas esas cosas les han llegado tarde. | BK32: 3. Errors | BM32: NO | BP32: Pero esto les pasa mucho a los millennials, porque creo que todas esas fases que deberían haber vivido en la adolescencia, y no lo han vivido y entonces las están viviendo todo como tarde, sabes? Porque todas esas cosas les han llegado tarde. | BQ32: 3. Errors | BS32: NO | BV32: Pero esto a los millennials les pasa mucho, porque creo que todas esas fases que deberían haber vivido en la adolescencia, y no lo han vivido y entonces lo están viviendo todo como tarde, sabes? Porque todas esas cosas les han llegado tarde. | BW32: 3. Errors | BY32: NO | CB32: Pero esto les pasa mucho a los millennials, porque creo que todas esas fases que deberían haber vivido en la adolescencia, y no lo han vivido y entonces las están viviendo todo como tarde, sabes? Porque todas esas cosas les han llegado tarde. | CC32: 3. Errors | CE32: NO | CH32: Pero esto les pasa mucho a los millennials, porque creo que todas esas fases que deberían haber vivido en la adolescencia, y no lo han vivido y entonces las están viviendo todo como tarde, sabes? Porque todas esas cosas les han llegado tarde. | CI32: 3. Errors | CK32: NO | CN32: Pero eso a los millennials les pasa mucho, porque creo que todas esas fases que deberían haber vivido en la adolescencia, y no lo han vivido y entonces lo están viviendo todo como tarde, sabes? Porque todas esas cosas les han llegado tarde. | CO32: 3. Errors | CQ32: NO
A33: [empieza tema de conversación] | B33: O sigui, generació Z som superintuitives, llavors per això no sabem utilitzar aquestes coses que són com que t'has de mirar un tutorial, aprendre-t'ho de memòria, com funciona. | C33: No entenc res, a mi m'ho feien fer quan anava a l'ESO, i jo estava fatal | D33: O sigui, generació Z som superintuitives, llavors per això no sabem utilitzar aquestes coses que són com que t'has de mirar un tutorial, aprendre-t'ho de memòria, com funciona. | E33: 1. Lexicon and Vocabulary | F33: 1.5 | G33: Informal intensifiers and quantifiers | H33: O sea, nosotros, la Generación Z, somos muy intuitivos, por eso no sabemos utilizar estas cosas que requieren que te veas un tutorial, que aprendas de memoria cómo funcionan. | I33: 4. Creative Shifts | J33: Abstraction – Superordinate Term | K33: NO | N33: O sea, nosotros, la Generación Z, somos súper intuitivas, así que por eso no sabemos utilizar estas cosas que requieren que te mires un tutorial, que te lo aprendas de memoria, cómo funciona. | O33: 3. Errors | Q33: NO | T33: O sea, nosotros, la generación Z, somos súper intuitivos, así que por eso no sabemos utilizar estas cosas que requieren que te veas un tutorial, que te lo aprendas de memoria, que entiendas cómo funcionan. | U33: 3. Errors | W33: NO | Z33: O sea, nosotros, la Generación Z, somos súper intuitivos, y por eso no sabemos utilizar estas cosas que requieren que te veas un tutorial, que te lo aprendas de memoria, que entiendas cómo funcionan. | AA33: 3. Errors | AC33: NO | AF33: O sea, nosotros, la Generación Z, somos súper intuitivos, así que por eso no sabemos utilizar estas cosas que requieren que te veas un tutorial, que lo aprendas de memoria, que entiendas cómo funciona. | AG33: 3. Errors | AI33: NO | AL33: También hay que decir que la generación Z somos muy intuitivas, por eso no sabemos usar estas cosas que son como que te tienes que mirar un tutorial, memorizar cómo se hace, entender cómo funciona. | AM33: 4. Creative Shifts | AN33: Abstraction – Superordinate Term | AO33: NO | AR33: O sea, la generación Z somos superintuitivas, entonces por eso no sabemos utilizar estas cosas que son como que te tienes que mirar un tutorial, aprender-te lo de memoria, cómo funciona. | AS33: 1. Reproduction | AT33: Direct Translation | AU33: YES | AV33: SAME | AX33: O sea, la generación Z somos superintuitivas, entonces por eso no sabemos utilizar estas cosas que son como que te tienes que mirar un tutorial, aprendértelo de memoria, cómo funciona. | AY33: 1. Reproduction | AZ33: Direct Translation | BA33: YES | BB33: SAME | BD33: O sea que, la generación Z somos superintuitivas, entonces por eso no sabemos usar estas cosas que son como que tienes que mirar un tutorial, aprenderlo de memoria, como funciona. | BE33: 1. Reproduction | BF33: Direct Translation | BG33: YES | BH33: SAME | BJ33: O sea, la generación Z somos superintuitivas, entonces por eso no sabemos usar estas cosas que son como que te tienes que ver un tutorial, aprendértelo de memoria, cómo funciona. | BK33: 1. Reproduction | BL33: Direct Translation | BM33: YES | BN33: SAME | BP33: Entonces, la generación Z somos superintuitivas, entonces por eso no sabemos utilizar esas cosas que son como que te tienes que mirar un tutorial, aprenderte de memoria cómo funciona. | BQ33: 1. Reproduction | BR33: Direct Translation | BS33: YES | BT33: SAME | BV33: O sea, generación Z somos superintuitivas, entonces por eso no sabemos utilizar esas cosas que son como que te tienes que mirar un tutorial, aprenderlo de memoria, cómo funciona. | BW33: 1. Reproduction | BX33: Direct Translation | BY33: YES | BZ33: SAME | CB33: Entonces, la generación Z somos superintuitivas, entonces por eso no sabemos utilizar esas cosas que son como que te tienes que mirar un tutorial, aprenderte de memoria cómo funciona. | CC33: 1. Reproduction | CD33: Direct Translation | CE33: YES | CF33: SAME | CH33: Entonces, la generación Z somos superintuitivas, entonces por eso no sabemos utilizar esas cosas que son como que te tienes que mirar un tutorial, aprenderte de memoria cómo funciona. | CI33: 1. Reproduction | CJ33: Direct Translation | CK33: YES | CL33: SAME | CN33: O sea, generación Z somos superintuitivas, entonces por eso no sabemos utilizar esas cosas que son como que te tienes que mirar un tutorial, aprenderlo de memoria, cómo funciona. | CO33: 1. Reproduction | CP33: Direct Translation | CQ33: YES | CR33: SAME
